Workbook

Sheet Inst_tentativas
B2: BD GISTM — Modelo por Principios (prototipo)
B4: Este archivo reestructura la base BD_GISTM.xlsx en un modelo relacional de 3 tablas para que el avance se calcule por Principio, permitiendo que un mismo documento aporte a varios Principios sin duplicar su información.
B9: Hoja | C9: Qué contiene / cómo se usa
B10: 1. Documentos | C10: Un documento = una sola fila. Aquí editas estado, % avance, fechas, consultor, URL, etc. Nunca se repite.
B12: 2. Criterios GISTM | C12: Catálogo fijo del estándar: Tema > Principio > Requisito > Criterio, con su ponderación. No cambia por proyecto.
B14: 3. Documento_x_Criterio | C14: Tabla puente: una fila por cada vínculo Documento-Criterio. Aquí es donde un documento puede aparecer varias veces si aporta a varios Principios. Incluye "% Contribución" para casos donde el documento cubre solo parcialmente un criterio.
B16: 4. Avance por Principio | C16: Calculado automáticamente con fórmulas (SUMIFS/SUMPRODUCT) a partir de la tabla puente. No se edita a mano.
B18: 5. Avance por Tema | C18: Mismo cálculo agregado a nivel de Tema.
B21: Cómo agregar un documento nuevo que cubre 2 Principios
B22: 1) Agrega UNA fila en "Documentos" con sus datos (estado, % avance, etc.) y un ID_Documento nuevo.
B23: 2) En "Documento_x_Criterio" agrega las filas (una por cada criterio al que aporta), usando el mismo ID_Documento y el ID_Criterio correspondiente.
B24: 3) "Avance por Principio" se actualiza solo, sin tocar fórmulas.

Sheet Documentos
A1: ID_Documento | B1: Documento | C1: Tipo Documento | D1: Código | E1: Estado | F1: % Avance Individual | G1: Consultor | H1: Área Responsable | I1: Fecha Iniciado | J1: Fecha RevA | K1: Fecha RevB | L1: Fecha Rev0 | M1: Frecuencia (meses) | N1: Caducidad | O1: URL | P1: Compañía | Q1: Depósito | R1: Capacidad | S1: Vida Útil
A2: D001 | B2: Compromiso de DDHH | C2: Política | D2: GA-DOC-01-2024 | E2: =IF(AND(L2>0,L2<>"-"),"Rev0",IF(AND(K2>0,K2<>"-"),"RevB",IF(AND(J2>0,J2<>"-"),"RevA",IF(AND(I2>0,I2<>"-"),"Iniciado","No Asignado")))) -> Rev0 | F2: {=_xlfn.IFS(E2="No Asignado",0,E2="Iniciado",0.2,E2="RevA",0.4,E2="RevB",0.7,E2="Rev0",1)} -> 1 | G2: Consultor 1 | H2: Sustentabilidad | I2: 45292 | J2: 45312 | K2: 45337 | L2: 45717 | M2: 36 | N2: 46797 | O2: https://drive.google.com/drive/folders/1IaEo6qPMz_Vb8OOQY3e1RIre4Fj4qXZL?usp=drive_link | P2: Mining Company | Q2: Embalse N°1 | R2: 2000 M Ton | S2: 20 años
A3: D002 | B3: Informe de Proceso de Debida Diligencia | C3: Informe | D3: GA-DOC-01-2024 | E3: =IF(AND(L3>0,L3<>"-"),"Rev0",IF(AND(K3>0,K3<>"-"),"RevB",IF(AND(J3>0,J3<>"-"),"RevA",IF(AND(I3>0,I3<>"-"),"Iniciado","No Asignado")))) -> RevB | F3: {=_xlfn.IFS(E3="No Asignado",0,E3="Iniciado",0.2,E3="RevA",0.4,E3="RevB",0.7,E3="Rev0",1)} -> 0.7 | G3: Consultor 1 | H3: Sustentabilidad | I3: 45292 | J3: 45312 | K3: 45337 | L3: - | M3: 12 | N3: - | O3: https://drive.google.com/drive/folders/1IaEo6qPMz_Vb8OOQY3e1RIre4Fj4qXZL?usp=drive_link | P3: Mining Company | Q3: Embalse N°1 | R3: 2000 M Ton | S3: 20 años
A4: D003 | B4: Nota Técnica No Afectación Pueblos Indígenas | C4: Nota Técnica | D4: GA-DOC-01-2024 | E4: =IF(AND(L4>0,L4<>"-"),"Rev0",IF(AND(K4>0,K4<>"-"),"RevB",IF(AND(J4>0,J4<>"-"),"RevA",IF(AND(I4>0,I4<>"-"),"Iniciado","No Asignado")))) -> Iniciado | F4: {=_xlfn.IFS(E4="No Asignado",0,E4="Iniciado",0.2,E4="RevA",0.4,E4="RevB",0.7,E4="Rev0",1)} -> 0.2 | G4: Consultor 1 | H4: Sustentabilidad | I4: 45292 | J4: - | K4: - | L4: - | M4: 6 | N4: - | O4: https://drive.google.com/drive/folders/1IaEo6qPMz_Vb8OOQY3e1RIre4Fj4qXZL?usp=drive_link | P4: Mining Company | Q4: Embalse N°1 | R4: 2000 M Ton | S4: 20 años
A5: D004 | B5: Informe de Identificación de Grupos Potenciales Afectados | C5: Informe | D5: GA-DOC-01-2024 | E5: =IF(AND(L5>0,L5<>"-"),"Rev0",IF(AND(K5>0,K5<>"-"),"RevB",IF(AND(J5>0,J5<>"-"),"RevA",IF(AND(I5>0,I5<>"-"),"Iniciado","No Asignado")))) -> Iniciado | F5: {=_xlfn.IFS(E5="No Asignado",0,E5="Iniciado",0.2,E5="RevA",0.4,E5="RevB",0.7,E5="Rev0",1)} -> 0.2 | G5: Consultor 3 | H5: Sustentabilidad | I5: 45292 | J5: - | K5: - | L5: - | M5: 12 | N5: - | O5: https://drive.google.com/drive/folders/1IaEo6qPMz_Vb8OOQY3e1RIre4Fj4qXZL?usp=drive_link | P5: Mining Company | Q5: Embalse N°1 | R5: 2000 M Ton | S5: 20 años
A6: D005 | B6: Procedimiento de Comunicación | C6: Procedimiento | D6: GA-DOC-01-2024 | E6: =IF(AND(L6>0,L6<>"-"),"Rev0",IF(AND(K6>0,K6<>"-"),"RevB",IF(AND(J6>0,J6<>"-"),"RevA",IF(AND(I6>0,I6<>"-"),"Iniciado","No Asignado")))) -> Iniciado | F6: {=_xlfn.IFS(E6="No Asignado",0,E6="Iniciado",0.2,E6="RevA",0.4,E6="RevB",0.7,E6="Rev0",1)} -> 0.2 | G6: Consultor 3 | H6: Sustentabilidad | I6: 45292 | J6: - | K6: - | L6: - | M6: 6 | N6: - | O6: https://drive.google.com/drive/folders/1IaEo6qPMz_Vb8OOQY3e1RIre4Fj4qXZL?usp=drive_link | P6: Mining Company | Q6: Embalse N°1 | R6: 2000 M Ton | S6: 20 años
A7: D006 | B7: Informe de Contexto Social, Económico y Ambiental | C7: Informe | D7: GA-DOC-01-2024 | E7: =IF(AND(L7>0,L7<>"-"),"Rev0",IF(AND(K7>0,K7<>"-"),"RevB",IF(AND(J7>0,J7<>"-"),"RevA",IF(AND(I7>0,I7<>"-"),"Iniciado","No Asignado")))) -> Iniciado | F7: {=_xlfn.IFS(E7="No Asignado",0,E7="Iniciado",0.2,E7="RevA",0.4,E7="RevB",0.7,E7="Rev0",1)} -> 0.2 | G7: Consultor 3 | H7: Medio Ambiente | I7: 45292 | J7: - | K7: - | L7: - | M7: 12 | N7: - | O7: https://drive.google.com/drive/folders/1IaEo6qPMz_Vb8OOQY3e1RIre4Fj4qXZL?usp=drive_link | P7: Mining Company | Q7: Embalse N°1 | R7: 2000 M Ton | S7: 20 años
A8: D007 | B8: Informe de Caracterización del Sitio | C8: Informe | D8: GA-DOC-01-2024 | E8: =IF(AND(L8>0,L8<>"-"),"Rev0",IF(AND(K8>0,K8<>"-"),"RevB",IF(AND(J8>0,J8<>"-"),"RevA",IF(AND(I8>0,I8<>"-"),"Iniciado","No Asignado")))) -> Rev0 | F8: {=_xlfn.IFS(E8="No Asignado",0,E8="Iniciado",0.2,E8="RevA",0.4,E8="RevB",0.7,E8="Rev0",1)} -> 1 | G8: Consultor 3 | H8: Medio Ambiente | I8: 45332 | J8: 45347 | K8: 45356 | L8: 45731 | M8: 12 | N8: 46091 | O8: https://drive.google.com/drive/folders/1IaEo6qPMz_Vb8OOQY3e1RIre4Fj4qXZL?usp=drive_link | P8: Mining Company | Q8: Embalse N°1 | R8: 2000 M Ton | S8: 20 años
A9: D008 | B9: Informe Análisis de Rotura de Presa (DBA) | C9: Informe | D9: GA-DOC-01-2024 | E9: =IF(AND(L9>0,L9<>"-"),"Rev0",IF(AND(K9>0,K9<>"-"),"RevB",IF(AND(J9>0,J9<>"-"),"RevA",IF(AND(I9>0,I9<>"-"),"Iniciado","No Asignado")))) -> Rev0 | F9: {=_xlfn.IFS(E9="No Asignado",0,E9="Iniciado",0.2,E9="RevA",0.4,E9="RevB",0.7,E9="Rev0",1)} -> 1 | G9: Consultor 1 | H9: Medio Ambiente | I9: 45332 | J9: 45347 | K9: 45356 | L9: 45731 | M9: 12 | N9: 46091 | O9: https://drive.google.com/drive/folders/1IaEo6qPMz_Vb8OOQY3e1RIre4Fj4qXZL?usp=drive_link | P9: Mining Company | Q9: Embalse N°1 | R9: 2000 M Ton | S9: 20 años
A10: D009 | B10: Informe Exposición y Vulnerabilidad | C10: Informe | D10: GA-DOC-01-2024 | E10: =IF(AND(L10>0,L10<>"-"),"Rev0",IF(AND(K10>0,K10<>"-"),"RevB",IF(AND(J10>0,J10<>"-"),"RevA",IF(AND(I10>0,I10<>"-"),"Iniciado","No Asignado")))) -> Rev0 | F10: {=_xlfn.IFS(E10="No Asignado",0,E10="Iniciado",0.2,E10="RevA",0.4,E10="RevB",0.7,E10="Rev0",1)} -> 1 | G10: Consultor 1 | H10: Medio Ambiente | I10: 45332 | J10: 45347 | K10: 45356 | L10: 45731 | M10: 12 | N10: 46091 | O10: https://drive.google.com/drive/folders/1IaEo6qPMz_Vb8OOQY3e1RIre4Fj4qXZL?usp=drive_link | P10: Mining Company | Q10: Embalse N°1 | R10: 2000 M Ton | S10: 20 años
A11: D010 | B11: Informe de Hidrología y Evaporación con Cambio Climático | C11: Informe | D11: GA-DOC-01-2024 | E11: =IF(AND(L11>0,L11<>"-"),"Rev0",IF(AND(K11>0,K11<>"-"),"RevB",IF(AND(J11>0,J11<>"-"),"RevA",IF(AND(I11>0,I11<>"-"),"Iniciado","No Asignado")))) -> RevA | F11: {=_xlfn.IFS(E11="No Asignado",0,E11="Iniciado",0.2,E11="RevA",0.4,E11="RevB",0.7,E11="Rev0",1)} -> 0.4 | G11: Consultor 1 | H11: Medio Ambiente | I11: 45332 | J11: 45347 | K11: - | L11: - | M11: 12 | N11: - | O11: https://drive.google.com/drive/folders/1IaEo6qPMz_Vb8OOQY3e1RIre4Fj4qXZL?usp=drive_link | P11: Mining Company | Q11: Embalse N°1 | R11: 2000 M Ton | S11: 20 años
A12: D011 | B12: Informe de Análisis de Alternativas | C12: Informe | D12: GA-DOC-01-2024 | E12: =IF(AND(L12>0,L12<>"-"),"Rev0",IF(AND(K12>0,K12<>"-"),"RevB",IF(AND(J12>0,J12<>"-"),"RevA",IF(AND(I12>0,I12<>"-"),"Iniciado","No Asignado")))) -> Iniciado | F12: {=_xlfn.IFS(E12="No Asignado",0,E12="Iniciado",0.2,E12="RevA",0.4,E12="RevB",0.7,E12="Rev0",1)} -> 0.2 | G12: Consultor 1 | H12: Medio Ambiente | I12: 45332 | J12: - | K12: - | L12: - | M12: 12 | N12: - | O12: https://drive.google.com/drive/folders/1IaEo6qPMz_Vb8OOQY3e1RIre4Fj4qXZL?usp=drive_link | P12: Mining Company | Q12: Embalse N°1 | R12: 2000 M Ton | S12: 20 años
A13: D012 | B13: Procedimiento de Mejora continua | C13: Procedimiento | D13: GA-DOC-01-2024 | E13: =IF(AND(L13>0,L13<>"-"),"Rev0",IF(AND(K13>0,K13<>"-"),"RevB",IF(AND(J13>0,J13<>"-"),"RevA",IF(AND(I13>0,I13<>"-"),"Iniciado","No Asignado")))) -> Iniciado | F13: {=_xlfn.IFS(E13="No Asignado",0,E13="Iniciado",0.2,E13="RevA",0.4,E13="RevB",0.7,E13="Rev0",1)} -> 0.2 | G13: Consultor 1 | H13: Medio Ambiente | I13: 45332 | J13: - | K13: - | L13: - | M13: 6 | N13: - | O13: https://drive.google.com/drive/folders/1IaEo6qPMz_Vb8OOQY3e1RIre4Fj4qXZL?usp=drive_link | P13: Mining Company | Q13: Embalse N°1 | R13: 2000 M Ton | S13: 20 años
A14: D013 | B14: Informe de impactos sociales, medioambientales y económicos | C14: Informe | D14: GA-DOC-01-2024 | E14: =IF(AND(L14>0,L14<>"-"),"Rev0",IF(AND(K14>0,K14<>"-"),"RevB",IF(AND(J14>0,J14<>"-"),"RevA",IF(AND(I14>0,I14<>"-"),"Iniciado","No Asignado")))) -> Iniciado | F14: {=_xlfn.IFS(E14="No Asignado",0,E14="Iniciado",0.2,E14="RevA",0.4,E14="RevB",0.7,E14="Rev0",1)} -> 0.2 | G14: Consultor 1 | H14: Medio Ambiente | I14: 45332 | J14: - | K14: - | L14: - | M14: 12 | N14: - | O14: https://drive.google.com/drive/folders/1IaEo6qPMz_Vb8OOQY3e1RIre4Fj4qXZL?usp=drive_link | P14: Mining Company | Q14: Embalse N°1 | R14: 2000 M Ton | S14: 20 años
A15: D014 | B15: Procedimiento de Gestión del Cambio | C15: Procedimiento | D15: GA-DOC-01-2024 | E15: =IF(AND(L15>0,L15<>"-"),"Rev0",IF(AND(K15>0,K15<>"-"),"RevB",IF(AND(J15>0,J15<>"-"),"RevA",IF(AND(I15>0,I15<>"-"),"Iniciado","No Asignado")))) -> Iniciado | F15: {=_xlfn.IFS(E15="No Asignado",0,E15="Iniciado",0.2,E15="RevA",0.4,E15="RevB",0.7,E15="Rev0",1)} -> 0.2 | G15: Consultor 1 | H15: Medio Ambiente | I15: 45332 | J15: - | K15: - | L15: - | M15: 6 | N15: - | O15: https://drive.google.com/drive/folders/1IaEo6qPMz_Vb8OOQY3e1RIre4Fj4qXZL?usp=drive_link | P15: Mining Company | Q15: Embalse N°1 | R15: 2000 M Ton | S15: 20 años
A16: D015 | B16: Informe Clasificación por Consecuencia | C16: Informe | D16: GA-DOC-01-2024 | E16: =IF(AND(L16>0,L16<>"-"),"Rev0",IF(AND(K16>0,K16<>"-"),"RevB",IF(AND(J16>0,J16<>"-"),"RevA",IF(AND(I16>0,I16<>"-"),"Iniciado","No Asignado")))) -> Iniciado | F16: {=_xlfn.IFS(E16="No Asignado",0,E16="Iniciado",0.2,E16="RevA",0.4,E16="RevB",0.7,E16="Rev0",1)} -> 0.2 | G16: Consultor 2 | H16: Operaciones | I16: 45332 | J16: - | K16: - | L16: - | M16: 12 | N16: - | O16: https://drive.google.com/drive/folders/1IaEo6qPMz_Vb8OOQY3e1RIre4Fj4qXZL?usp=drive_link | P16: Mining Company | Q16: Embalse N°1 | R16: 2000 M Ton | S16: 20 años
A17: D016 | B17: Informe de Bases de Diseño | C17: Informe | D17: GA-DOC-01-2024 | E17: =IF(AND(L17>0,L17<>"-"),"Rev0",IF(AND(K17>0,K17<>"-"),"RevB",IF(AND(J17>0,J17<>"-"),"RevA",IF(AND(I17>0,I17<>"-"),"Iniciado","No Asignado")))) -> Iniciado | F17: {=_xlfn.IFS(E17="No Asignado",0,E17="Iniciado",0.2,E17="RevA",0.4,E17="RevB",0.7,E17="Rev0",1)} -> 0.2 | G17: Consultor 2 | H17: Operaciones | I17: 45337 | J17: - | K17: - | L17: - | M17: 12 | N17: - | O17: https://drive.google.com/drive/folders/1IaEo6qPMz_Vb8OOQY3e1RIre4Fj4qXZL?usp=drive_link | P17: Mining Company | Q17: Embalse N°1 | R17: 2000 M Ton | S17: 20 años
A18: D017 | B18: Nota Técnica Pérdida Incremental | C18: Nota Técnica | D18: GA-DOC-01-2024 | E18: =IF(AND(L18>0,L18<>"-"),"Rev0",IF(AND(K18>0,K18<>"-"),"RevB",IF(AND(J18>0,J18<>"-"),"RevA",IF(AND(I18>0,I18<>"-"),"Iniciado","No Asignado")))) -> RevA | F18: {=_xlfn.IFS(E18="No Asignado",0,E18="Iniciado",0.2,E18="RevA",0.4,E18="RevB",0.7,E18="Rev0",1)} -> 0.4 | G18: Consultor 2 | H18: Operaciones | I18: 45337 | J18: 45347 | K18: - | L18: - | M18: 6 | N18: - | O18: https://drive.google.com/drive/folders/1IaEo6qPMz_Vb8OOQY3e1RIre4Fj4qXZL?usp=drive_link | P18: Mining Company | Q18: Embalse N°1 | R18: 2000 M Ton | S18: 20 años
A19: D018 | B19: Nota Técnica Análisis Multicriterio en TMS | C19: Nota Técnica | D19: GA-DOC-01-2024 | E19: =IF(AND(L19>0,L19<>"-"),"Rev0",IF(AND(K19>0,K19<>"-"),"RevB",IF(AND(J19>0,J19<>"-"),"RevA",IF(AND(I19>0,I19<>"-"),"Iniciado","No Asignado")))) -> RevA | F19: {=_xlfn.IFS(E19="No Asignado",0,E19="Iniciado",0.2,E19="RevA",0.4,E19="RevB",0.7,E19="Rev0",1)} -> 0.4 | G19: Consultor 2 | H19: Operaciones | I19: 45337 | J19: 45347 | K19: - | L19: - | M19: 6 | N19: - | O19: https://drive.google.com/drive/folders/1IaEo6qPMz_Vb8OOQY3e1RIre4Fj4qXZL?usp=drive_link | P19: Mining Company | Q19: Embalse N°1 | R19: 2000 M Ton | S19: 20 años
A20: D019 | B20: Informe Anual de Desempeño del Depósito | C20: Informe | D20: GA-DOC-01-2024 | E20: =IF(AND(L20>0,L20<>"-"),"Rev0",IF(AND(K20>0,K20<>"-"),"RevB",IF(AND(J20>0,J20<>"-"),"RevA",IF(AND(I20>0,I20<>"-"),"Iniciado","No Asignado")))) -> RevB | F20: {=_xlfn.IFS(E20="No Asignado",0,E20="Iniciado",0.2,E20="RevA",0.4,E20="RevB",0.7,E20="Rev0",1)} -> 0.7 | G20: Consultor 2 | H20: Operaciones | I20: 45337 | J20: 45347 | K20: 45354 | L20: - | M20: 12 | N20: - | O20: https://drive.google.com/drive/folders/1IaEo6qPMz_Vb8OOQY3e1RIre4Fj4qXZL?usp=drive_link | P20: Mining Company | Q20: Embalse N°1 | R20: 2000 M Ton | S20: 20 años
A21: D020 | B21: Balance Hídrico | C21: Informe | D21: GA-DOC-01-2024 | E21: =IF(AND(L21>0,L21<>"-"),"Rev0",IF(AND(K21>0,K21<>"-"),"RevB",IF(AND(J21>0,J21<>"-"),"RevA",IF(AND(I21>0,I21<>"-"),"Iniciado","No Asignado")))) -> Rev0 | F21: {=_xlfn.IFS(E21="No Asignado",0,E21="Iniciado",0.2,E21="RevA",0.4,E21="RevB",0.7,E21="Rev0",1)} -> 1 | G21: Consultor 2 | H21: Operaciones | I21: 45337 | J21: 45347 | K21: 45354 | L21: 45740 | M21: 12 | N21: 46100 | O21: https://drive.google.com/drive/folders/1IaEo6qPMz_Vb8OOQY3e1RIre4Fj4qXZL?usp=drive_link | P21: Mining Company | Q21: Embalse N°1 | R21: 2000 M Ton | S21: 20 años
A22: D021 | B22: Análisis FMEA | C22: Informe | D22: GA-DOC-01-2024 | E22: =IF(AND(L22>0,L22<>"-"),"Rev0",IF(AND(K22>0,K22<>"-"),"RevB",IF(AND(J22>0,J22<>"-"),"RevA",IF(AND(I22>0,I22<>"-"),"Iniciado","No Asignado")))) -> Rev0 | F22: {=_xlfn.IFS(E22="No Asignado",0,E22="Iniciado",0.2,E22="RevA",0.4,E22="RevB",0.7,E22="Rev0",1)} -> 1 | G22: Consultor 1 | H22: Operaciones | I22: 45337 | J22: 45347 | K22: 45354 | L22: 45740 | M22: 12 | N22: 46100 | O22: https://drive.google.com/drive/folders/1IaEo6qPMz_Vb8OOQY3e1RIre4Fj4qXZL?usp=drive_link | P22: Mining Company | Q22: Embalse N°1 | R22: 2000 M Ton | S22: 20 años
A23: D022 | B23: Plan de cierre | C23: Informe | D23: GA-DOC-01-2024 | E23: =IF(AND(L23>0,L23<>"-"),"Rev0",IF(AND(K23>0,K23<>"-"),"RevB",IF(AND(J23>0,J23<>"-"),"RevA",IF(AND(I23>0,I23<>"-"),"Iniciado","No Asignado")))) -> Rev0 | F23: {=_xlfn.IFS(E23="No Asignado",0,E23="Iniciado",0.2,E23="RevA",0.4,E23="RevB",0.7,E23="Rev0",1)} -> 1 | G23: Consultor 1 | H23: Operaciones | I23: 45340 | J23: 45347 | K23: 45354 | L23: 45741 | M23: 12 | N23: 46101 | O23: https://drive.google.com/drive/folders/1IaEo6qPMz_Vb8OOQY3e1RIre4Fj4qXZL?usp=drive_link | P23: Mining Company | Q23: Embalse N°1 | R23: 2000 M Ton | S23: 20 años
A24: D023 | B24: Reporte ALARP | C24: Informe | D24: GA-DOC-01-2024 | E24: =IF(AND(L24>0,L24<>"-"),"Rev0",IF(AND(K24>0,K24<>"-"),"RevB",IF(AND(J24>0,J24<>"-"),"RevA",IF(AND(I24>0,I24<>"-"),"Iniciado","No Asignado")))) -> RevA | F24: {=_xlfn.IFS(E24="No Asignado",0,E24="Iniciado",0.2,E24="RevA",0.4,E24="RevB",0.7,E24="Rev0",1)} -> 0.4 | G24: Consultor 1 | H24: Operaciones | I24: 45340 | J24: 45347 | K24: - | L24: - | M24: 12 | N24: - | O24: https://drive.google.com/drive/folders/1IaEo6qPMz_Vb8OOQY3e1RIre4Fj4qXZL?usp=drive_link | P24: Mining Company | Q24: Embalse N°1 | R24: 2000 M Ton | S24: 20 años
A25: D024 | B25: Nota Técnica Comunidades Aledañas | C25: Nota Técnica | D25: GA-DOC-01-2024 | E25: =IF(AND(L25>0,L25<>"-"),"Rev0",IF(AND(K25>0,K25<>"-"),"RevB",IF(AND(J25>0,J25<>"-"),"RevA",IF(AND(I25>0,I25<>"-"),"Iniciado","No Asignado")))) -> Iniciado | F25: {=_xlfn.IFS(E25="No Asignado",0,E25="Iniciado",0.2,E25="RevA",0.4,E25="RevB",0.7,E25="Rev0",1)} -> 0.2 | G25: Consultor 1 | H25: Operaciones | I25: 45340 | J25: - | K25: - | L25: - | M25: 6 | N25: - | O25: https://drive.google.com/drive/folders/1IaEo6qPMz_Vb8OOQY3e1RIre4Fj4qXZL?usp=drive_link | P25: Mining Company | Q25: Embalse N°1 | R25: 2000 M Ton | S25: 20 años
A26: D025 | B26: Reporte de Registro de Construcción (CRR) | C26: Informe | D26: GA-DOC-01-2024 | E26: =IF(AND(L26>0,L26<>"-"),"Rev0",IF(AND(K26>0,K26<>"-"),"RevB",IF(AND(J26>0,J26<>"-"),"RevA",IF(AND(I26>0,I26<>"-"),"Iniciado","No Asignado")))) -> Iniciado | F26: {=_xlfn.IFS(E26="No Asignado",0,E26="Iniciado",0.2,E26="RevA",0.4,E26="RevB",0.7,E26="Rev0",1)} -> 0.2 | G26: Consultor 3 | H26: Operaciones | I26: 45340 | J26: - | K26: - | L26: - | M26: 12 | N26: - | O26: https://drive.google.com/drive/folders/1IaEo6qPMz_Vb8OOQY3e1RIre4Fj4qXZL?usp=drive_link | P26: Mining Company | Q26: Embalse N°1 | R26: 2000 M Ton | S26: 20 años
A27: D026 | B27: Informe Verificación construcción contra intención de diseño (CDIV) | C27: Informe | D27: GA-DOC-01-2024 | E27: =IF(AND(L27>0,L27<>"-"),"Rev0",IF(AND(K27>0,K27<>"-"),"RevB",IF(AND(J27>0,J27<>"-"),"RevA",IF(AND(I27>0,I27<>"-"),"Iniciado","No Asignado")))) -> Iniciado | F27: {=_xlfn.IFS(E27="No Asignado",0,E27="Iniciado",0.2,E27="RevA",0.4,E27="RevB",0.7,E27="Rev0",1)} -> 0.2 | G27: Consultor 3 | H27: Operaciones | I27: 45340 | J27: - | K27: - | L27: - | M27: 12 | N27: - | O27: https://drive.google.com/drive/folders/1IaEo6qPMz_Vb8OOQY3e1RIre4Fj4qXZL?usp=drive_link | P27: Mining Company | Q27: Embalse N°1 | R27: 2000 M Ton | S27: 20 años
A28: D027 | B28: Manual Articulador TMS | C28: Manual | D28: GA-DOC-01-2024 | E28: =IF(AND(L28>0,L28<>"-"),"Rev0",IF(AND(K28>0,K28<>"-"),"RevB",IF(AND(J28>0,J28<>"-"),"RevA",IF(AND(I28>0,I28<>"-"),"Iniciado","No Asignado")))) -> Iniciado | F28: {=_xlfn.IFS(E28="No Asignado",0,E28="Iniciado",0.2,E28="RevA",0.4,E28="RevB",0.7,E28="Rev0",1)} -> 0.2 | G28: Consultor 3 | H28: Operaciones | I28: 45340 | J28: - | K28: - | L28: - | M28: 12 | N28: - | O28: https://drive.google.com/drive/folders/1IaEo6qPMz_Vb8OOQY3e1RIre4Fj4qXZL?usp=drive_link | P28: Mining Company | Q28: Embalse N°1 | R28: 2000 M Ton | S28: 20 años
A29: D028 | B29: Manual Operación, Mantención y Vigilancia (OMS) | C29: Manual | D29: GA-DOC-01-2024 | E29: =IF(AND(L29>0,L29<>"-"),"Rev0",IF(AND(K29>0,K29<>"-"),"RevB",IF(AND(J29>0,J29<>"-"),"RevA",IF(AND(I29>0,I29<>"-"),"Iniciado","No Asignado")))) -> Iniciado | F29: {=_xlfn.IFS(E29="No Asignado",0,E29="Iniciado",0.2,E29="RevA",0.4,E29="RevB",0.7,E29="Rev0",1)} -> 0.2 | G29: Consultor 3 | H29: Operaciones | I29: 45340 | J29: - | K29: - | L29: - | M29: 12 | N29: - | O29: https://drive.google.com/drive/folders/1IaEo6qPMz_Vb8OOQY3e1RIre4Fj4qXZL?usp=drive_link | P29: Mining Company | Q29: Embalse N°1 | R29: 2000 M Ton | S29: 20 años
A30: D029 | B30: Manual Sistema Gestión Medioambiental y Social | C30: Manual | D30: GA-DOC-01-2024 | E30: =IF(AND(L30>0,L30<>"-"),"Rev0",IF(AND(K30>0,K30<>"-"),"RevB",IF(AND(J30>0,J30<>"-"),"RevA",IF(AND(I30>0,I30<>"-"),"Iniciado","No Asignado")))) -> Iniciado | F30: {=_xlfn.IFS(E30="No Asignado",0,E30="Iniciado",0.2,E30="RevA",0.4,E30="RevB",0.7,E30="Rev0",1)} -> 0.2 | G30: Consultor 3 | H30: Operaciones | I30: 45340 | J30: - | K30: - | L30: - | M30: 12 | N30: - | O30: https://drive.google.com/drive/folders/1IaEo6qPMz_Vb8OOQY3e1RIre4Fj4qXZL?usp=drive_link | P30: Mining Company | Q30: Embalse N°1 | R30: 2000 M Ton | S30: 20 años
A31: D030 | B31: Programa QA/QC | C31: Informe | D31: GA-DOC-01-2024 | E31: =IF(AND(L31>0,L31<>"-"),"Rev0",IF(AND(K31>0,K31<>"-"),"RevB",IF(AND(J31>0,J31<>"-"),"RevA",IF(AND(I31>0,I31<>"-"),"Iniciado","No Asignado")))) -> Iniciado | F31: {=_xlfn.IFS(E31="No Asignado",0,E31="Iniciado",0.2,E31="RevA",0.4,E31="RevB",0.7,E31="Rev0",1)} -> 0.2 | G31: Consultor 3 | H31: Operaciones | I31: 45342 | J31: - | K31: - | L31: - | M31: 12 | N31: - | O31: https://drive.google.com/drive/folders/1IaEo6qPMz_Vb8OOQY3e1RIre4Fj4qXZL?usp=drive_link | P31: Mining Company | Q31: Embalse N°1 | R31: 2000 M Ton | S31: 20 años
A32: D031 | B32: Plan de Capacitaciones | C32: Informe | D32: GA-DOC-01-2024 | E32: =IF(AND(L32>0,L32<>"-"),"Rev0",IF(AND(K32>0,K32<>"-"),"RevB",IF(AND(J32>0,J32<>"-"),"RevA",IF(AND(I32>0,I32<>"-"),"Iniciado","No Asignado")))) -> Rev0 | F32: {=_xlfn.IFS(E32="No Asignado",0,E32="Iniciado",0.2,E32="RevA",0.4,E32="RevB",0.7,E32="Rev0",1)} -> 1 | G32: Consultor 3 | H32: Operaciones | I32: 45342 | J32: 45352 | K32: 45366 | L32: 45751 | M32: 12 | N32: 46111 | O32: https://drive.google.com/drive/folders/1IaEo6qPMz_Vb8OOQY3e1RIre4Fj4qXZL?usp=drive_link | P32: Mining Company | Q32: Embalse N°1 | R32: 2000 M Ton | S32: 20 años
A33: D032 | B33: Informe de responsabilidad ante desviaciones (DAR) | C33: Informe | D33: GA-DOC-01-2024 | E33: =IF(AND(L33>0,L33<>"-"),"Rev0",IF(AND(K33>0,K33<>"-"),"RevB",IF(AND(J33>0,J33<>"-"),"RevA",IF(AND(I33>0,I33<>"-"),"Iniciado","No Asignado")))) -> Rev0 | F33: {=_xlfn.IFS(E33="No Asignado",0,E33="Iniciado",0.2,E33="RevA",0.4,E33="RevB",0.7,E33="Rev0",1)} -> 1 | G33: Consultor 3 | H33: Operaciones | I33: 45342 | J33: 45352 | K33: 45366 | L33: 45751 | M33: 12 | N33: 46111 | O33: https://drive.google.com/drive/folders/1IaEo6qPMz_Vb8OOQY3e1RIre4Fj4qXZL?usp=drive_link | P33: Mining Company | Q33: Embalse N°1 | R33: 2000 M Ton | S33: 20 años
A34: D033 | B34: Programa de Monitoreo Integrado | C34: Informe | D34: GA-DOC-01-2024 | E34: =IF(AND(L34>0,L34<>"-"),"Rev0",IF(AND(K34>0,K34<>"-"),"RevB",IF(AND(J34>0,J34<>"-"),"RevA",IF(AND(I34>0,I34<>"-"),"Iniciado","No Asignado")))) -> RevB | F34: {=_xlfn.IFS(E34="No Asignado",0,E34="Iniciado",0.2,E34="RevA",0.4,E34="RevB",0.7,E34="Rev0",1)} -> 0.7 | G34: Consultor 3 | H34: Operaciones | I34: 45342 | J34: 45352 | K34: 45366 | L34: - | M34: 12 | N34: - | O34: https://drive.google.com/drive/folders/1IaEo6qPMz_Vb8OOQY3e1RIre4Fj4qXZL?usp=drive_link | P34: Mining Company | Q34: Embalse N°1 | R34: 2000 M Ton | S34: 20 años
A35: D034 | B35: Informes periódicos del EoR | C35: Informe | D35: GA-DOC-01-2024 | E35: =IF(AND(L35>0,L35<>"-"),"Rev0",IF(AND(K35>0,K35<>"-"),"RevB",IF(AND(J35>0,J35<>"-"),"RevA",IF(AND(I35>0,I35<>"-"),"Iniciado","No Asignado")))) -> RevA | F35: {=_xlfn.IFS(E35="No Asignado",0,E35="Iniciado",0.2,E35="RevA",0.4,E35="RevB",0.7,E35="Rev0",1)} -> 0.4 | G35: Consultor 1 | H35: Operaciones | I35: 45342 | J35: 45352 | K35: - | L35: - | M35: 12 | N35: - | O35: https://drive.google.com/drive/folders/1IaEo6qPMz_Vb8OOQY3e1RIre4Fj4qXZL?usp=drive_link | P35: Mining Company | Q35: Embalse N°1 | R35: 2000 M Ton | S35: 20 años
A36: D035 | B36: Plan de Respuesta de Acción Desencadenante (TARPS) | C36: Informe | D36: GA-DOC-01-2024 | E36: =IF(AND(L36>0,L36<>"-"),"Rev0",IF(AND(K36>0,K36<>"-"),"RevB",IF(AND(J36>0,J36<>"-"),"RevA",IF(AND(I36>0,I36<>"-"),"Iniciado","No Asignado")))) -> No Asignado | F36: {=_xlfn.IFS(E36="No Asignado",0,E36="Iniciado",0.2,E36="RevA",0.4,E36="RevB",0.7,E36="Rev0",1)} -> 0 | G36: Consultor 1 | H36: Operaciones | I36: 0 | J36: - | K36: - | L36: - | M36: 12 | N36: - | O36: https://drive.google.com/drive/folders/1IaEo6qPMz_Vb8OOQY3e1RIre4Fj4qXZL?usp=drive_link | P36: Mining Company | Q36: Embalse N°1 | R36: 2000 M Ton | S36: 20 años
A37: D036 | B37: Firma del EoR e Ingeniero responsable | C37: Registro | D37: GA-DOC-01-2024 | E37: =IF(AND(L37>0,L37<>"-"),"Rev0",IF(AND(K37>0,K37<>"-"),"RevB",IF(AND(J37>0,J37<>"-"),"RevA",IF(AND(I37>0,I37<>"-"),"Iniciado","No Asignado")))) -> No Asignado | F37: {=_xlfn.IFS(E37="No Asignado",0,E37="Iniciado",0.2,E37="RevA",0.4,E37="RevB",0.7,E37="Rev0",1)} -> 0 | G37: Consultor 5 | H37: Operaciones | I37: 0 | J37: - | K37: - | L37: - | M37: 12 | N37: - | O37: https://drive.google.com/drive/folders/1IaEo6qPMz_Vb8OOQY3e1RIre4Fj4qXZL?usp=drive_link | P37: Mining Company | Q37: Embalse N°1 | R37: 2000 M Ton | S37: 20 años
A38: D037 | B38: Política de Relaves | C38: Política | D38: GA-DOC-01-2024 | E38: =IF(AND(L38>0,L38<>"-"),"Rev0",IF(AND(K38>0,K38<>"-"),"RevB",IF(AND(J38>0,J38<>"-"),"RevA",IF(AND(I38>0,I38<>"-"),"Iniciado","No Asignado")))) -> No Asignado | F38: {=_xlfn.IFS(E38="No Asignado",0,E38="Iniciado",0.2,E38="RevA",0.4,E38="RevB",0.7,E38="Rev0",1)} -> 0 | G38: Consultor 5 | H38: Operaciones | I38: 0 | J38: - | K38: - | L38: - | M38: 36 | N38: - | O38: https://drive.google.com/drive/folders/1IaEo6qPMz_Vb8OOQY3e1RIre4Fj4qXZL?usp=drive_link | P38: Mining Company | Q38: Embalse N°1 | R38: 2000 M Ton | S38: 20 años
A39: D038 | B39: Procedimiento de Pago de Incentivos | C39: Procedimiento | D39: GA-DOC-01-2024 | E39: =IF(AND(L39>0,L39<>"-"),"Rev0",IF(AND(K39>0,K39<>"-"),"RevB",IF(AND(J39>0,J39<>"-"),"RevA",IF(AND(I39>0,I39<>"-"),"Iniciado","No Asignado")))) -> No Asignado | F39: {=_xlfn.IFS(E39="No Asignado",0,E39="Iniciado",0.2,E39="RevA",0.4,E39="RevB",0.7,E39="Rev0",1)} -> 0 | G39: Consultor 5 | H39: Operaciones | I39: 0 | J39: - | K39: - | L39: - | M39: 6 | N39: - | O39: https://drive.google.com/drive/folders/1IaEo6qPMz_Vb8OOQY3e1RIre4Fj4qXZL?usp=drive_link | P39: Mining Company | Q39: Embalse N°1 | R39: 2000 M Ton | S39: 20 años
A40: D039 | B40: Manual de Roles y Responsabilidades | C40: Manual | D40: GA-DOC-01-2024 | E40: =IF(AND(L40>0,L40<>"-"),"Rev0",IF(AND(K40>0,K40<>"-"),"RevB",IF(AND(J40>0,J40<>"-"),"RevA",IF(AND(I40>0,I40<>"-"),"Iniciado","No Asignado")))) -> Iniciado | F40: {=_xlfn.IFS(E40="No Asignado",0,E40="Iniciado",0.2,E40="RevA",0.4,E40="RevB",0.7,E40="Rev0",1)} -> 0.2 | G40: Consultor 5 | H40: Operaciones | I40: 45347 | J40: - | K40: - | L40: - | M40: 12 | N40: - | O40: https://drive.google.com/drive/folders/1IaEo6qPMz_Vb8OOQY3e1RIre4Fj4qXZL?usp=drive_link | P40: Mining Company | Q40: Embalse N°1 | R40: 2000 M Ton | S40: 20 años
A41: D040 | B41: Plan de sucesión | C41: Procedimiento | D41: GA-DOC-01-2024 | E41: =IF(AND(L41>0,L41<>"-"),"Rev0",IF(AND(K41>0,K41<>"-"),"RevB",IF(AND(J41>0,J41<>"-"),"RevA",IF(AND(I41>0,I41<>"-"),"Iniciado","No Asignado")))) -> Rev0 | F41: {=_xlfn.IFS(E41="No Asignado",0,E41="Iniciado",0.2,E41="RevA",0.4,E41="RevB",0.7,E41="Rev0",1)} -> 1 | G41: Consultor 5 | H41: Operaciones | I41: 45347 | J41: 45363 | K41: 45371 | L41: 45752 | M41: 6 | N41: 45932 | O41: https://drive.google.com/drive/folders/1IaEo6qPMz_Vb8OOQY3e1RIre4Fj4qXZL?usp=drive_link | P41: Mining Company | Q41: Embalse N°1 | R41: 2000 M Ton | S41: 20 años
A42: D041 | B42: Carta de asignación ITRB | C42: Registro | D42: GA-DOC-01-2024 | E42: =IF(AND(L42>0,L42<>"-"),"Rev0",IF(AND(K42>0,K42<>"-"),"RevB",IF(AND(J42>0,J42<>"-"),"RevA",IF(AND(I42>0,I42<>"-"),"Iniciado","No Asignado")))) -> Rev0 | F42: {=_xlfn.IFS(E42="No Asignado",0,E42="Iniciado",0.2,E42="RevA",0.4,E42="RevB",0.7,E42="Rev0",1)} -> 1 | G42: Consultor 5 | H42: Operaciones | I42: 45347 | J42: 45000 | K42: 45371 | L42: 45752 | M42: 12 | N42: 46112 | O42: https://drive.google.com/drive/folders/1IaEo6qPMz_Vb8OOQY3e1RIre4Fj4qXZL?usp=drive_link | P42: Mining Company | Q42: Embalse N°1 | R42: 2000 M Ton | S42: 20 años
A43: D042 | B43: Nota Técnica Términos de Referencia (ToR) | C43: Nota Técnica | D43: GA-DOC-01-2024 | E43: =IF(AND(L43>0,L43<>"-"),"Rev0",IF(AND(K43>0,K43<>"-"),"RevB",IF(AND(J43>0,J43<>"-"),"RevA",IF(AND(I43>0,I43<>"-"),"Iniciado","No Asignado")))) -> RevB | F43: {=_xlfn.IFS(E43="No Asignado",0,E43="Iniciado",0.2,E43="RevA",0.4,E43="RevB",0.7,E43="Rev0",1)} -> 0.7 | G43: Consultor 1 | H43: Operaciones | I43: 45347 | J43: 45000 | K43: 45371 | L43: - | M43: 6 | N43: - | O43: https://drive.google.com/drive/folders/1IaEo6qPMz_Vb8OOQY3e1RIre4Fj4qXZL?usp=drive_link | P43: Mining Company | Q43: Embalse N°1 | R43: 2000 M Ton | S43: 20 años
A44: D043 | B44: Carta / Declaración de no conflicto de intereses. | C44: Registro | D44: GA-DOC-01-2024 | E44: =IF(AND(L44>0,L44<>"-"),"Rev0",IF(AND(K44>0,K44<>"-"),"RevB",IF(AND(J44>0,J44<>"-"),"RevA",IF(AND(I44>0,I44<>"-"),"Iniciado","No Asignado")))) -> Iniciado | F44: {=_xlfn.IFS(E44="No Asignado",0,E44="Iniciado",0.2,E44="RevA",0.4,E44="RevB",0.7,E44="Rev0",1)} -> 0.2 | G44: Consultor 1 | H44: Operaciones | I44: 45347 | J44: - | K44: - | L44: - | M44: 12 | N44: - | O44: https://drive.google.com/drive/folders/1IaEo6qPMz_Vb8OOQY3e1RIre4Fj4qXZL?usp=drive_link | P44: Mining Company | Q44: Embalse N°1 | R44: 2000 M Ton | S44: 20 años
A45: D044 | B45: Carta de Asignación EoR | C45: Registro | D45: GA-DOC-01-2024 | E45: =IF(AND(L45>0,L45<>"-"),"Rev0",IF(AND(K45>0,K45<>"-"),"RevB",IF(AND(J45>0,J45<>"-"),"RevA",IF(AND(I45>0,I45<>"-"),"Iniciado","No Asignado")))) -> Iniciado | F45: {=_xlfn.IFS(E45="No Asignado",0,E45="Iniciado",0.2,E45="RevA",0.4,E45="RevB",0.7,E45="Rev0",1)} -> 0.2 | G45: Consultor 1 | H45: Operaciones | I45: 45352 | J45: - | K45: - | L45: - | M45: 12 | N45: - | O45: https://drive.google.com/drive/folders/1IaEo6qPMz_Vb8OOQY3e1RIre4Fj4qXZL?usp=drive_link | P45: Mining Company | Q45: Embalse N°1 | R45: 2000 M Ton | S45: 20 años
A46: D045 | B46: Nota Técnica Incorporación de EoR | C46: Nota Técnica | D46: GA-DOC-01-2024 | E46: =IF(AND(L46>0,L46<>"-"),"Rev0",IF(AND(K46>0,K46<>"-"),"RevB",IF(AND(J46>0,J46<>"-"),"RevA",IF(AND(I46>0,I46<>"-"),"Iniciado","No Asignado")))) -> Rev0 | F46: {=_xlfn.IFS(E46="No Asignado",0,E46="Iniciado",0.2,E46="RevA",0.4,E46="RevB",0.7,E46="Rev0",1)} -> 1 | G46: Consultor 1 | H46: Operaciones | I46: 45352 | J46: 45034 | K46: 45381 | L46: 45752 | M46: 6 | N46: 45932 | O46: https://drive.google.com/drive/folders/1IaEo6qPMz_Vb8OOQY3e1RIre4Fj4qXZL?usp=drive_link | P46: Mining Company | Q46: Embalse N°1 | R46: 2000 M Ton | S46: 20 años
A47: D046 | B47: Carta de asignación DoR | C47: Registro | D47: GA-DOC-01-2024 | E47: =IF(AND(L47>0,L47<>"-"),"Rev0",IF(AND(K47>0,K47<>"-"),"RevB",IF(AND(J47>0,J47<>"-"),"RevA",IF(AND(I47>0,I47<>"-"),"Iniciado","No Asignado")))) -> Rev0 | F47: {=_xlfn.IFS(E47="No Asignado",0,E47="Iniciado",0.2,E47="RevA",0.4,E47="RevB",0.7,E47="Rev0",1)} -> 1 | G47: Consultor 2 | H47: Operaciones | I47: 45352 | J47: 45034 | K47: 45381 | L47: 45752 | M47: 12 | N47: 46112 | O47: https://drive.google.com/drive/folders/1IaEo6qPMz_Vb8OOQY3e1RIre4Fj4qXZL?usp=drive_link | P47: Mining Company | Q47: Embalse N°1 | R47: 2000 M Ton | S47: 20 años
A48: D047 | B48: Programa para la Ingeniería de Registro | C48: Informe | D48: GA-DOC-01-2024 | E48: =IF(AND(L48>0,L48<>"-"),"Rev0",IF(AND(K48>0,K48<>"-"),"RevB",IF(AND(J48>0,J48<>"-"),"RevA",IF(AND(I48>0,I48<>"-"),"Iniciado","No Asignado")))) -> Rev0 | F48: {=_xlfn.IFS(E48="No Asignado",0,E48="Iniciado",0.2,E48="RevA",0.4,E48="RevB",0.7,E48="Rev0",1)} -> 1 | G48: Consultor 2 | H48: Operaciones | I48: 45352 | J48: 45034 | K48: 45381 | L48: 45752 | M48: 12 | N48: 46112 | O48: https://drive.google.com/drive/folders/1IaEo6qPMz_Vb8OOQY3e1RIre4Fj4qXZL?usp=drive_link | P48: Mining Company | Q48: Embalse N°1 | R48: 2000 M Ton | S48: 20 años
A49: D048 | B49: Matriz Evaluación de Riesgos | C49: Informe | D49: GA-DOC-01-2024 | E49: =IF(AND(L49>0,L49<>"-"),"Rev0",IF(AND(K49>0,K49<>"-"),"RevB",IF(AND(J49>0,J49<>"-"),"RevA",IF(AND(I49>0,I49<>"-"),"Iniciado","No Asignado")))) -> RevB | F49: {=_xlfn.IFS(E49="No Asignado",0,E49="Iniciado",0.2,E49="RevA",0.4,E49="RevB",0.7,E49="Rev0",1)} -> 0.7 | G49: Consultor 1 | H49: Operaciones | I49: 45352 | J49: 45034 | K49: 45381 | L49: - | M49: 12 | N49: - | O49: https://drive.google.com/drive/folders/1IaEo6qPMz_Vb8OOQY3e1RIre4Fj4qXZL?usp=drive_link | P49: Mining Company | Q49: Embalse N°1 | R49: 2000 M Ton | S49: 20 años
A50: D049 | B50: Informe de auditoría Interna | C50: Informe | D50: GA-DOC-01-2024 | E50: =IF(AND(L50>0,L50<>"-"),"Rev0",IF(AND(K50>0,K50<>"-"),"RevB",IF(AND(J50>0,J50<>"-"),"RevA",IF(AND(I50>0,I50<>"-"),"Iniciado","No Asignado")))) -> RevA | F50: {=_xlfn.IFS(E50="No Asignado",0,E50="Iniciado",0.2,E50="RevA",0.4,E50="RevB",0.7,E50="Rev0",1)} -> 0.4 | G50: Consultor 1 | H50: Operaciones | I50: 45352 | J50: 45034 | K50: - | L50: - | M50: 12 | N50: - | O50: https://drive.google.com/drive/folders/1IaEo6qPMz_Vb8OOQY3e1RIre4Fj4qXZL?usp=drive_link | P50: Mining Company | Q50: Embalse N°1 | R50: 2000 M Ton | S50: 20 años
A51: D050 | B51: Actualización Dam Safety Review (DSR) | C51: Informe | D51: GA-DOC-01-2024 | E51: =IF(AND(L51>0,L51<>"-"),"Rev0",IF(AND(K51>0,K51<>"-"),"RevB",IF(AND(J51>0,J51<>"-"),"RevA",IF(AND(I51>0,I51<>"-"),"Iniciado","No Asignado")))) -> Rev0 | F51: {=_xlfn.IFS(E51="No Asignado",0,E51="Iniciado",0.2,E51="RevA",0.4,E51="RevB",0.7,E51="Rev0",1)} -> 1 | G51: Consultor 4 | H51: Operaciones | I51: 45352 | J51: 45034 | K51: 45381 | L51: 45752 | M51: 12 | N51: 46112 | O51: https://drive.google.com/drive/folders/1IaEo6qPMz_Vb8OOQY3e1RIre4Fj4qXZL?usp=drive_link | P51: Mining Company | Q51: Embalse N°1 | R51: 2000 M Ton | S51: 20 años
A52: D051 | B52: Informe de ITRB | C52: Informe | D52: GA-DOC-01-2024 | E52: =IF(AND(L52>0,L52<>"-"),"Rev0",IF(AND(K52>0,K52<>"-"),"RevB",IF(AND(J52>0,J52<>"-"),"RevA",IF(AND(I52>0,I52<>"-"),"Iniciado","No Asignado")))) -> Rev0 | F52: {=_xlfn.IFS(E52="No Asignado",0,E52="Iniciado",0.2,E52="RevA",0.4,E52="RevB",0.7,E52="Rev0",1)} -> 1 | G52: Consultor 4 | H52: Operaciones | I52: 45352 | J52: 45034 | K52: 45381 | L52: 45752 | M52: 12 | N52: 46112 | O52: https://drive.google.com/drive/folders/1IaEo6qPMz_Vb8OOQY3e1RIre4Fj4qXZL?usp=drive_link | P52: Mining Company | Q52: Embalse N°1 | R52: 2000 M Ton | S52: 20 años
A53: D052 | B53: Procedimiento de Involucramiento del Personal | C53: Procedimiento | D53: GA-DOC-01-2024 | E53: =IF(AND(L53>0,L53<>"-"),"Rev0",IF(AND(K53>0,K53<>"-"),"RevB",IF(AND(J53>0,J53<>"-"),"RevA",IF(AND(I53>0,I53<>"-"),"Iniciado","No Asignado")))) -> RevB | F53: {=_xlfn.IFS(E53="No Asignado",0,E53="Iniciado",0.2,E53="RevA",0.4,E53="RevB",0.7,E53="Rev0",1)} -> 0.7 | G53: Consultor 4 | H53: Operaciones | I53: 45352 | J53: 45034 | K53: 45381 | L53: - | M53: 6 | N53: - | O53: https://drive.google.com/drive/folders/1IaEo6qPMz_Vb8OOQY3e1RIre4Fj4qXZL?usp=drive_link | P53: Mining Company | Q53: Embalse N°1 | R53: 2000 M Ton | S53: 20 años
A54: D053 | B54: Procedimiento de Gestión de Conocimiento | C54: Procedimiento | D54: GA-DOC-01-2024 | E54: =IF(AND(L54>0,L54<>"-"),"Rev0",IF(AND(K54>0,K54<>"-"),"RevB",IF(AND(J54>0,J54<>"-"),"RevA",IF(AND(I54>0,I54<>"-"),"Iniciado","No Asignado")))) -> RevB | F54: {=_xlfn.IFS(E54="No Asignado",0,E54="Iniciado",0.2,E54="RevA",0.4,E54="RevB",0.7,E54="Rev0",1)} -> 0.7 | G54: Consultor 4 | H54: Operaciones | I54: 45352 | J54: 45034 | K54: 45381 | L54: - | M54: 6 | N54: - | O54: https://drive.google.com/drive/folders/1IaEo6qPMz_Vb8OOQY3e1RIre4Fj4qXZL?usp=drive_link | P54: Mining Company | Q54: Embalse N°1 | R54: 2000 M Ton | S54: 20 años
A55: D054 | B55: Procedimiento Gestión de Denuncias | C55: Procedimiento | D55: GA-DOC-01-2024 | E55: =IF(AND(L55>0,L55<>"-"),"Rev0",IF(AND(K55>0,K55<>"-"),"RevB",IF(AND(J55>0,J55<>"-"),"RevA",IF(AND(I55>0,I55<>"-"),"Iniciado","No Asignado")))) -> RevA | F55: {=_xlfn.IFS(E55="No Asignado",0,E55="Iniciado",0.2,E55="RevA",0.4,E55="RevB",0.7,E55="Rev0",1)} -> 0.4 | G55: Consultor 5 | H55: Operaciones | I55: 45352 | J55: 45034 | K55: - | L55: - | M55: 6 | N55: - | O55: https://drive.google.com/drive/folders/1IaEo6qPMz_Vb8OOQY3e1RIre4Fj4qXZL?usp=drive_link | P55: Mining Company | Q55: Embalse N°1 | R55: 2000 M Ton | S55: 20 años
A56: D055 | B56: Plan de Preparación y Respuesta ante Emergencia (EPRP) | C56: Informe | D56: GA-DOC-01-2024 | E56: =IF(AND(L56>0,L56<>"-"),"Rev0",IF(AND(K56>0,K56<>"-"),"RevB",IF(AND(J56>0,J56<>"-"),"RevA",IF(AND(I56>0,I56<>"-"),"Iniciado","No Asignado")))) -> RevA | F56: {=_xlfn.IFS(E56="No Asignado",0,E56="Iniciado",0.2,E56="RevA",0.4,E56="RevB",0.7,E56="Rev0",1)} -> 0.4 | G56: Consultor 2 | H56: HSEC | I56: 45352 | J56: 45034 | K56: - | L56: - | M56: 12 | N56: - | O56: https://drive.google.com/drive/folders/1IaEo6qPMz_Vb8OOQY3e1RIre4Fj4qXZL?usp=drive_link | P56: Mining Company | Q56: Embalse N°1 | R56: 2000 M Ton | S56: 20 años
A57: D056 | B57: Plan de Recuperación a Largo Plazo | C57: Informe | D57: GA-DOC-01-2024 | E57: =IF(AND(L57>0,L57<>"-"),"Rev0",IF(AND(K57>0,K57<>"-"),"RevB",IF(AND(J57>0,J57<>"-"),"RevA",IF(AND(I57>0,I57<>"-"),"Iniciado","No Asignado")))) -> RevA | F57: {=_xlfn.IFS(E57="No Asignado",0,E57="Iniciado",0.2,E57="RevA",0.4,E57="RevB",0.7,E57="Rev0",1)} -> 0.4 | G57: Consultor 2 | H57: HSEC | I57: 45352 | J57: 45034 | K57: - | L57: - | M57: 12 | N57: - | O57: https://drive.google.com/drive/folders/1IaEo6qPMz_Vb8OOQY3e1RIre4Fj4qXZL?usp=drive_link | P57: Mining Company | Q57: Embalse N°1 | R57: 2000 M Ton | S57: 20 años
A58: D057 | B58: Informe Recopilatorio de Divulgación Pública | C58: Informe | D58: GA-DOC-01-2024 | E58: =IF(AND(L58>0,L58<>"-"),"Rev0",IF(AND(K58>0,K58<>"-"),"RevB",IF(AND(J58>0,J58<>"-"),"RevA",IF(AND(I58>0,I58<>"-"),"Iniciado","No Asignado")))) -> RevB | F58: {=_xlfn.IFS(E58="No Asignado",0,E58="Iniciado",0.2,E58="RevA",0.4,E58="RevB",0.7,E58="Rev0",1)} -> 0.7 | G58: Consultor 2 | H58: Relaciones Comunitarias | I58: 45352 | J58: 45034 | K58: 45381 | L58: - | M58: 12 | N58: - | O58: https://drive.google.com/drive/folders/1IaEo6qPMz_Vb8OOQY3e1RIre4Fj4qXZL?usp=drive_link | P58: Mining Company | Q58: Embalse N°1 | R58: 2000 M Ton | S58: 20 años
A59: D058 | B59: Procedimiento Gestión de Información Pública | C59: Procedimiento | D59: GA-DOC-01-2024 | E59: =IF(AND(L59>0,L59<>"-"),"Rev0",IF(AND(K59>0,K59<>"-"),"RevB",IF(AND(J59>0,J59<>"-"),"RevA",IF(AND(I59>0,I59<>"-"),"Iniciado","No Asignado")))) -> Rev0 | F59: {=_xlfn.IFS(E59="No Asignado",0,E59="Iniciado",0.2,E59="RevA",0.4,E59="RevB",0.7,E59="Rev0",1)} -> 1 | G59: Consultor 2 | H59: Relaciones Comunitarias | I59: 45352 | J59: 45034 | K59: 45381 | L59: 45752 | M59: 6 | N59: 45932 | O59: https://drive.google.com/drive/folders/1IaEo6qPMz_Vb8OOQY3e1RIre4Fj4qXZL?usp=drive_link | P59: Mining Company | Q59: Embalse N°1 | R59: 2000 M Ton | S59: 20 años

Sheet Criterios GISTM
A1: ID_Criterio | B1: Tema | C1: Nombre Tema | D1: Principio | E1: Descripción Principio | F1: Requisito | G1: Descripción Requisito | H1: Criterio | I1: Descripción Criterio | J1: Ponderación
A2: C001 | B2: I | C2: COMUNIDADES AFECTADAS | D2: Principio 01 | E2: Respetar los derechos de las personas afectadas por el proyecto y lograr su participación significativa en todas las fases del ciclo de vida de las instalaciones de relaves, incluido su cierre. | F2: Requisito 01.1 | G2: Requisito 01.1 Demostrar respeto por los derechos humanos en cumplimiento con los Principios Guía de las Naciones Unidas sobre Empresas, realizar la debida diligencia de los derechos humanos para informar las decisiones de gestión a lo largo del ciclo de vida de la instalación de relaves y abordar los riesgos de los derechos humanos en los escenarios de falla creíbles en la instalación de relaves. Para las instalaciones existentes, el Operador puede optar inicialmente por priorizar las cuestiones de los derechos humanos más importantes de acuerdo al UNGP. | H2: 1.1 - A | I2: 1.1 - A El Operador tiene una política de compromiso para respetar los derechos humanos de acuerdo al UNGP. | J2: =1/3 -> 0.33333333 | L2: 1
A3: C002 | B3: I | C3: COMUNIDADES AFECTADAS | D3: Principio 01 | E3: Respetar los derechos de las personas afectadas por el proyecto y lograr su participación significativa en todas las fases del ciclo de vida de las instalaciones de relaves, incluido su cierre. | F3: Requisito 01.1 | G3: Requisito 01.1 Demostrar respeto por los derechos humanos en cumplimiento con los Principios Guía de las Naciones Unidas sobre Empresas, realizar la debida diligencia de los derechos humanos para informar las decisiones de gestión a lo largo del ciclo de vida de la instalación de relaves y abordar los riesgos de los derechos humanos en los escenarios de falla creíbles en la instalación de relaves. Para las instalaciones existentes, el Operador puede optar inicialmente por priorizar las cuestiones de los derechos humanos más importantes de acuerdo al UNGP. | H3: 1.1 - B | I3: 1.1 - B El Operador ha realizado el proceso de diligencias de derechos humanos específicas al sitio para informarlas decisiones de gestión a través del ciclo de vida de los relaves. | J3: =1/3 -> 0.33333333 | L3: 1
A4: C003 | B4: I | C4: COMUNIDADES AFECTADAS | D4: Principio 01 | E4: Respetar los derechos de las personas afectadas por el proyecto y lograr su participación significativa en todas las fases del ciclo de vida de las instalaciones de relaves, incluido su cierre. | F4: Requisito 01.1 | G4: Requisito 01.1 Demostrar respeto por los derechos humanos en cumplimiento con los Principios Guía de las Naciones Unidas sobre Empresas, realizar la debida diligencia de los derechos humanos para informar las decisiones de gestión a lo largo del ciclo de vida de la instalación de relaves y abordar los riesgos de los derechos humanos en los escenarios de falla creíbles en la instalación de relaves. Para las instalaciones existentes, el Operador puede optar inicialmente por priorizar las cuestiones de los derechos humanos más importantes de acuerdo al UNGP. | H4: 1.1 - C | I4: 1.1 - C El Operador ha abordado los riesgos a los derechos humanos de los escenarios de falla creíbles de la instalación de relaves donde aquellos escenarios existan para tal instalación. | J4: =1/3 -> 0.33333333 | L4: 1
A5: C004 | B5: I | C5: COMUNIDADES AFECTADAS | D5: Principio 01 | E5: Respetar los derechos de las personas afectadas por el proyecto y lograr su participación significativa en todas las fases del ciclo de vida de las instalaciones de relaves, incluido su cierre. | F5: Requisito 01.2 | G5: Requisito 01.2 Donde una nueva instalación de relaves puede impactar los derechos de pueblos indígenas o tribales, incluida sus tierras y derechos a los recursos y su derecho a la libre determinación, trabajar para obtener y mantener un Consentimiento Libre, Previo e Informado (CLPI) al demostrar conformidad con la guía internacional y con el marco de las mejores prácticas reconocidas. | H5: 1.2 - A | I5: 1.2 - A El Operador ha identificado los grupos indígenas o tribales que puedan verse afectados por una nueva instalación de relaves, y entiende como los derechos de estas personas pueden verse impactados, incluyendo sus tierras y derechos a los recursos y su derecho a la libre determinación. | J5: =1/2 -> 0.5 | L5: 1
A6: C005 | B6: I | C6: COMUNIDADES AFECTADAS | D6: Principio 01 | E6: Respetar los derechos de las personas afectadas por el proyecto y lograr su participación significativa en todas las fases del ciclo de vida de las instalaciones de relaves, incluido su cierre. | F6: Requisito 01.2 | G6: Requisito 01.2 Donde una nueva instalación de relaves puede impactar los derechos de pueblos indígenas o tribales, incluida sus tierras y derechos a los recursos y su derecho a la libre determinación, trabajar para obtener y mantener un Consentimiento Libre, Previo e Informado (CLPI) al demostrar conformidad con la guía internacional y con el marco de las mejores prácticas reconocidas. | H6: 1.2 - B | I6: 1.2 - B El Operador trabaja para obtener y mantener el CLPI por parte de los grupos indígenas o tribales, en cumplimiento con la guía internacional y marco de las mejores prácticas reconocidas. | J6: =1/2 -> 0.5 | L6: 1
A7: C006 | B7: I | C7: COMUNIDADES AFECTADAS | D7: Principio 01 | E7: Respetar los derechos de las personas afectadas por el proyecto y lograr su participación significativa en todas las fases del ciclo de vida de las instalaciones de relaves, incluido su cierre. | F7: Requisito 01.3 | G7: Requisito 01.3 Demostrar que las personas afectadas por el proyecto participan de forma significativa a lo largo del ciclo de vida de la instalación de relaves en la construcción de la base de conocimientos que puedan influir en la seguridad pública e integridad de la instalación de relaves. El Operador deberá compartir información para respaldar este proceso | H7: 1.3 - A | I7: 1.3 - A El Operador ha identificado a los grupos afectados por el proyecto. | J7: =1/2 -> 0.5 | L7: 1
A8: C007 | B8: I | C8: COMUNIDADES AFECTADAS | D8: Principio 01 | E8: Respetar los derechos de las personas afectadas por el proyecto y lograr su participación significativa en todas las fases del ciclo de vida de las instalaciones de relaves, incluido su cierre. | F8: Requisito 01.3 | G8: Requisito 01.3 Demostrar que las personas afectadas por el proyecto participan de forma significativa a lo largo del ciclo de vida de la instalación de relaves en la construcción de la base de conocimientos que puedan influir en la seguridad pública e integridad de la instalación de relaves. El Operador deberá compartir información para respaldar este proceso | H8: 1.3 - B | I8: 1.3 - B El Operador ha asumido un compromiso significativo con los grupos afectados por el proyecto a través del ciclo de vida de la instalación de relaves para: - Compartir información relevante y accesible sobre la instalación de relaves; - Construir la base de conocimientos para la instalación de relaves, incluyendo el contexto social, medioambiental y económico local; y, - Buscar retroalimentación en las decisiones que pueden tener relación con la seguridad pública y la integridad de la instalación de relaves. | J8: =1/2 -> 0.5 | L8: 1
A9: C008 | B9: I | C9: COMUNIDADES AFECTADAS | D9: Principio 01 | E9: Respetar los derechos de las personas afectadas por el proyecto y lograr su participación significativa en todas las fases del ciclo de vida de las instalaciones de relaves, incluido su cierre. | F9: Requisito 01.4 | G9: Requisito 01.4 Establecer un mecanismo de reclamos no judicial eficaz a nivel operativo que aborde las quejas y agravios de las personas afectadas por el proyecto relacionado a la instalación de relaves, y proporcionar una solución acorde al UNGP | H9: 1.4 - A | I9: 1.4 - A Se desarrolló e implementó un mecanismo de reclamos accesible y eficaz a nivel operativo para personas afectadas por el proyecto. | J9: =1/3 -> 0.33333333 | L9: 1
A10: C009 | B10: I | C10: COMUNIDADES AFECTADAS | D10: Principio 01 | E10: Respetar los derechos de las personas afectadas por el proyecto y lograr su participación significativa en todas las fases del ciclo de vida de las instalaciones de relaves, incluido su cierre. | F10: Requisito 01.5 | G10: Requisito 01.5 Establecer un mecanismo de reclamos no judicial eficaz a nivel operativo que aborde las quejas y agravios de las personas afectadas por el proyecto relacionado a la instalación de relaves, y proporcionar una solución acorde al UNGP | H10: 1.4 - B | I10: 1.4 - B El mecanismo de reclamos abarca quejas y agravios de las personas afectadas por el proyecto relacionado a la instalación de relaves. | J10: =1/3 -> 0.33333333 | L10: 1
A11: C010 | B11: I | C11: COMUNIDADES AFECTADAS | D11: Principio 01 | E11: Respetar los derechos de las personas afectadas por el proyecto y lograr su participación significativa en todas las fases del ciclo de vida de las instalaciones de relaves, incluido su cierre. | F11: Requisito 01.5 | G11: Requisito 01.5 Establecer un mecanismo de reclamos no judicial eficaz a nivel operativo que aborde las quejas y agravios de las personas afectadas por el proyecto relacionado a la instalación de relaves, y proporcionar una solución acorde al UNGP | H11: 1.4 - C | I11: 1.4 - C El mecanismo de reclamos brinda soluciones de acuerdo a las UNGPs 29-31. | J11: =1/3 -> 0.33333333 | L11: 1
A12: C011 | B12: II | C12: BASE DE CONOCIMIENTOS INTEGRADA | D12: Principio 02 | E12: Elaborar y mantener una base de conocimientos interdisciplinaria para respaldar la gestión de los relaves durante todo su ciclo de vida, incluido su cierre. | F12: Requisito 02.1 | G12: Requisito 02.1 Desarrollar y documentar conocimientos sobre el contexto social, medioambiental y económico local de la instalación de relaves, utilizando métodos alineados con las mejores prácticas internacionales. Actualizar este conocimiento por lo menos cada cinco años, y cada vez haya un cambio material, ya sea en la instalación este conocimiento por lo menos cada cinco años, y cada vez haya un cambio material, ya sea en la instalación de relaves o en el contexto social, medioambiental o económico local. Este conocimiento debe capturar las incertidumbres debidas al cambio climático. | H12: 2.1 - A | I12: 2.1 - A El Operador ha documentado el contexto social, medioambiental y económico específico del sitio con respecto a su instalación de relaves. | J12: =1/3 -> 0.33333333 | L12: 2
A13: C012 | B13: II | C13: BASE DE CONOCIMIENTOS INTEGRADA | D13: Principio 02 | E13: Elaborar y mantener una base de conocimientos interdisciplinaria para respaldar la gestión de los relaves durante todo su ciclo de vida, incluido su cierre. | F13: Requisito 02.1 | G13: Requisito 02.1 Desarrollar y documentar conocimientos sobre el contexto social, medioambiental y económico local de la instalación de relaves, utilizando métodos alineados con las mejores prácticas internacionales. Actualizar este conocimiento por lo menos cada cinco años, y cada vez haya un cambio material, ya sea en la instalación este conocimiento por lo menos cada cinco años, y cada vez haya un cambio material, ya sea en la instalación de relaves o en el contexto social, medioambiental o económico local. Este conocimiento debe capturar las incertidumbres debidas al cambio climático. | H13: 2.1 - B | I13: 2.1 - B Evalúa las incertidumbres asociadas s al cambio climático que pueda impactar la seguridad de la instalación de relaves (véase también requisito GISTM 3.1) | J13: =1/3 -> 0.33333333 | L13: 2
A14: C013 | B14: II | C14: BASE DE CONOCIMIENTOS INTEGRADA | D14: Principio 02 | E14: Elaborar y mantener una base de conocimientos interdisciplinaria para respaldar la gestión de los relaves durante todo su ciclo de vida, incluido su cierre. | F14: Requisito 02.1 | G14: Requisito 02.1 Desarrollar y documentar conocimientos sobre el contexto social, medioambiental y económico local de la instalación de relaves, utilizando métodos alineados con las mejores prácticas internacionales. Actualizar este conocimiento por lo menos cada cinco años, y cada vez haya un cambio material, ya sea en la instalación este conocimiento por lo menos cada cinco años, y cada vez haya un cambio material, ya sea en la instalación de relaves o en el contexto social, medioambiental o económico local. Este conocimiento debe capturar las incertidumbres debidas al cambio climático. | H14: 2.1 - C | I14: 2.1 - C El Operador actualiza la información descrita arriba en un intervalo de por lo menos cinco años, y cada vez que haya un cambio material en la instalación de relaves o relacionado al contexto ambiental, social o económico. | J14: =1/3 -> 0.33333333 | L14: 2
A15: C014 | B15: II | C15: BASE DE CONOCIMIENTOS INTEGRADA | D15: Principio 02 | E15: Elaborar y mantener una base de conocimientos interdisciplinaria para respaldar la gestión de los relaves durante todo su ciclo de vida, incluido su cierre. | F15: Requisito 02.2 | G15: Requisito 02.2 Preparar, documentar y actualizar una caracterización del sitio detallada de la (las) instalación(es) de relaves que incluyan datos sobre el clima, geomorfología, geología, geoquímica, hidrología e hidrogeología (flujo y calidad de aguas superficiales y de subsuelo), geotécnicos y sísmicos. Las propiedades químicas y físicas del relave serán caracterizadas y actualizadas con regularidad para tomar en cuenta la variabilidad de las propiedades y procesamiento del mineral | H15: 2.2 - A | I15: 2.2 - A Existe una caracterización detallada1 del(los) sitio(s) de la instalación de relaves y se actualiza según se justifica a través del ciclo de vida, para reflejar los cambios materiales en las condiciones y nuevos conocimientos. | J15: =1/3 -> 0.33333333 | L15: 2
A16: C015 | B16: II | C16: BASE DE CONOCIMIENTOS INTEGRADA | D16: Principio 02 | E16: Elaborar y mantener una base de conocimientos interdisciplinaria para respaldar la gestión de los relaves durante todo su ciclo de vida, incluido su cierre. | F16: Requisito 02.2 | G16: Requisito 02.2 Preparar, documentar y actualizar una caracterización del sitio detallada de la (las) instalación(es) de relaves que incluyan datos sobre el clima, geomorfología, geología, geoquímica, hidrología e hidrogeología (flujo y calidad de aguas superficiales y de subsuelo), geotécnicos y sísmicos. Las propiedades químicas y físicas del relave serán caracterizadas y actualizadas con regularidad para tomar en cuenta la variabilidad de las propiedades y procesamiento del mineral | H16: 2.2 - B | I16: 2.2 - B La caracterización del sitio es respaldada por datos incluyendo datos en clima, geomorfología, geología, geoquímica, hidrología, hidrogeología (flujo y calidad de aguas superficiales y subsuelo), geotécnicos y sísmicos). | J16: =1/3 -> 0.33333333 | L16: 2
A17: C016 | B17: II | C17: BASE DE CONOCIMIENTOS INTEGRADA | D17: Principio 02 | E17: Elaborar y mantener una base de conocimientos interdisciplinaria para respaldar la gestión de los relaves durante todo su ciclo de vida, incluido su cierre. | F17: Requisito 02.2 | G17: Requisito 02.2 Preparar, documentar y actualizar una caracterización del sitio detallada de la (las) instalación(es) de relaves que incluyan datos sobre el clima, geomorfología, geología, geoquímica, hidrología e hidrogeología (flujo y calidad de aguas superficiales y de subsuelo), geotécnicos y sísmicos. Las propiedades químicas y físicas del relave serán caracterizadas y actualizadas con regularidad para tomar en cuenta la variabilidad de las propiedades y procesamiento del mineral | H17: 2.2 - C | I17: 2.2 - C Existe una caracterización de relaves, considerando las propiedades físicas y geoquímicas, y se actualizan a lo largo del ciclo de vida para tomar en cuenta la variabilidad en las propiedades y el procesamiento del mineral y la deposición de relaves. | J17: =1/3 -> 0.33333333 | L17: 2
A18: C017 | B18: II | C18: BASE DE CONOCIMIENTOS INTEGRADA | D18: Principio 02 | E18: Elaborar y mantener una base de conocimientos interdisciplinaria para respaldar la gestión de los relaves durante todo su ciclo de vida, incluido su cierre. | F18: Requisito 02.3 | G18: Requisito 02.3 Desarrollar y documentar un análisis de brechas para la instalación de relaves, utilizando una metodología que considere modelos de falla creíble, condiciones del sitio, y las propiedades de las lamas. Los resultados del análisis estimarán el área física impactada por una falla potencial. Cuando materiales fluidos (agua o sólidos licuables) estén presentes en una instalación de relaves con una Clasificación de Consecuencias "Altas", "Muy Altas" o "Extremas", los resultados deben incluir estimados del área física impactada por la falla potencial, tiempos de llegada de flujo, profundidad y velocidades, y profundidad de la deposición de material. Actualizar cuando se dé un cambio material, ya sea a la instalación de relaves o al área física impactada. | H18: 2.3 - A | I18: 2.3 - A Donde una instalación de relaves tiene un modelo/escenario de falla creíble1, hay un análisis de brecha documentado para la instalación de relaves, utilizando una metodología que considere los modelos de falla creíbles, condiciones del sitio y propiedades de los relaves. | J18: =1/4 -> 0.25 | L18: 3
A19: C018 | B19: II | C19: BASE DE CONOCIMIENTOS INTEGRADA | D19: Principio 02 | E19: Elaborar y mantener una base de conocimientos interdisciplinaria para respaldar la gestión de los relaves durante todo su ciclo de vida, incluido su cierre. | F19: Requisito 02.3 | G19: Requisito 02.3 Desarrollar y documentar un análisis de brechas para la instalación de relaves, utilizando una metodología que considere modelos de falla creíble, condiciones del sitio, y las propiedades de las lamas. Los resultados del análisis estimarán el área física impactada por una falla potencial. Cuando materiales fluidos (agua o sólidos licuables) estén presentes en una instalación de relaves con una Clasificación de Consecuencias "Altas", "Muy Altas" o "Extremas", los resultados deben incluir estimados del área física impactada por la falla potencial, tiempos de llegada de flujo, profundidad y velocidades, y profundidad de la deposición de material. Actualizar cuando se dé un cambio material, ya sea a la instalación de relaves o al área física impactada. | H19: 2.3 - B | I19: 2.3 - B El área física potencialmente afectada por una falla es estimada y definida. | J19: =1/4 -> 0.25 | L19: 3
A20: C019 | B20: II | C20: BASE DE CONOCIMIENTOS INTEGRADA | D20: Principio 02 | E20: Elaborar y mantener una base de conocimientos interdisciplinaria para respaldar la gestión de los relaves durante todo su ciclo de vida, incluido su cierre. | F20: Requisito 02.3 | G20: Requisito 02.3 Desarrollar y documentar un análisis de brechas para la instalación de relaves, utilizando una metodología que considere modelos de falla creíble, condiciones del sitio, y las propiedades de las lamas. Los resultados del análisis estimarán el área física impactada por una falla potencial. Cuando materiales fluidos (agua o sólidos licuables) estén presentes en una instalación de relaves con una Clasificación de Consecuencias "Altas", "Muy Altas" o "Extremas", los resultados deben incluir estimados del área física impactada por la falla potencial, tiempos de llegada de flujo, profundidad y velocidades, y profundidad de la deposición de material. Actualizar cuando se dé un cambio material, ya sea a la instalación de relaves o al área física impactada. | H20: 2.3 - C | I20: 2.3 - C Para las instalaciones con escenarios de falla creíbles involucrando materiales fluidos (agua y sólidos licuables) y con una clasificación de consecuencias de “Altas”, “Muy Altas” o “Extremas”, se estiman los tiempos de llegada de flujo, profundidades de flujo, velocidades de flujo y profundidad del material depositado. | J20: =1/4 -> 0.25 | L20: 3
A21: C020 | B21: II | C21: BASE DE CONOCIMIENTOS INTEGRADA | D21: Principio 02 | E21: Elaborar y mantener una base de conocimientos interdisciplinaria para respaldar la gestión de los relaves durante todo su ciclo de vida, incluido su cierre. | F21: Requisito 02.3 | G21: Requisito 02.3 Desarrollar y documentar un análisis de brechas para la instalación de relaves, utilizando una metodología que considere modelos de falla creíble, condiciones del sitio, y las propiedades de las lamas. Los resultados del análisis estimarán el área física impactada por una falla potencial. Cuando materiales fluidos (agua o sólidos licuables) estén presentes en una instalación de relaves con una Clasificación de Consecuencias "Altas", "Muy Altas" o "Extremas", los resultados deben incluir estimados del área física impactada por la falla potencial, tiempos de llegada de flujo, profundidad y velocidades, y profundidad de la deposición de material. Actualizar cuando se dé un cambio material, ya sea a la instalación de relaves o al área física impactada. | H21: 2.3 - D | I21: 2.3 - D Para las instalaciones que cumplen con las condiciones a, b y c, el análisis de brecha se completa/ actualiza si se da un cambio material 1 en la instalación de relaves o a la base de conocimientos que resulte en un escenario de falla creíble que pueda llevar a una falla de flujo. | J21: =1/4 -> 0.25 | L21: 3
A22: C021 | B22: II | C22: BASE DE CONOCIMIENTOS INTEGRADA | D22: Principio 02 | E22: Elaborar y mantener una base de conocimientos interdisciplinaria para respaldar la gestión de los relaves durante todo su ciclo de vida, incluido su cierre. | F22: Requisito 02.4 | G22: Requisito 02.4 Para poder identificar los grupos de mayor riesgo, referirse al análisis de brechas actualizado de la instalación de relaves para evaluar y documentar la exposición y vulnerabilidad humana a los escenarios de falla creíble de la instalación de relaves. Actualizar la evaluación cuando se dé un cambio material, ya sea en la instalación de relaves o en la base del conocimiento | H22: 2.4 - A | I22: 2.4 - A Se identifican los grupos de mayor riesgo, considerando el análisis de brechas para aquellas instalaciones con escenarios de fallas creíbles según el Requisito 2.3. | J22: =1/3 -> 0.33333333 | L22: 3
A23: C022 | B23: II | C23: BASE DE CONOCIMIENTOS INTEGRADA | D23: Principio 02 | E23: Elaborar y mantener una base de conocimientos interdisciplinaria para respaldar la gestión de los relaves durante todo su ciclo de vida, incluido su cierre. | F23: Requisito 02.4 | G23: Requisito 02.4 Para poder identificar los grupos de mayor riesgo, referirse al análisis de brechas actualizado de la instalación de relaves para evaluar y documentar la exposición y vulnerabilidad humana a los escenarios de falla creíble de la instalación de relaves. Actualizar la evaluación cuando se dé un cambio material, ya sea en la instalación de relaves o en la base del conocimiento | H23: 2.4 - B | I23: 2.4 - B Se documenta la exposición y vulnerabilidad humana potencial de los escenarios de fallas creíbles de la instalación de relaves. | J23: =1/3 -> 0.33333333 | L23: 3
A24: C023 | B24: II | C24: BASE DE CONOCIMIENTOS INTEGRADA | D24: Principio 02 | E24: Elaborar y mantener una base de conocimientos interdisciplinaria para respaldar la gestión de los relaves durante todo su ciclo de vida, incluido su cierre. | F24: Requisito 02.4 | G24: Requisito 02.4 Para poder identificar los grupos de mayor riesgo, referirse al análisis de brechas actualizado de la instalación de relaves para evaluar y documentar la exposición y vulnerabilidad humana a los escenarios de falla creíble de la instalación de relaves. Actualizar la evaluación cuando se dé un cambio material, ya sea en la instalación de relaves o en la base del conocimiento | H24: 2.4 - C | I24: 2.4 - C La evaluación de la exposición y vulnerabilidad humana se actualiza si es que se da un cambio material 1 a la credibilidad de la falla de flujo potencial y su correspondiente análisis de brecha o base del conocimiento. | J24: =1/3 -> 0.33333333 | L24: 3
A25: C024 | B25: II | C25: BASE DE CONOCIMIENTOS INTEGRADA | D25: Principio 03 | E25: Utilizar los elementos de la base de conocimientos – sociales, ambientales, de la economía local y técnicos – con el fin de informar las decisiones durante el ciclo de vida de la instalación de relaves, incluido su cierre | F25: Requisito 03.1 | G25: Requisito 03.1 Para mejorar la resistencia al cambio climático, evaluar, actualizar con regularidad y utilizar conocimientos del cambio climático a través del ciclo de vida de la instalación de relaves de acuerdo a los principios de la Gestión Adaptativa. | H25: 3.1 - A | I25: 3.1 - A Para mejorar la resistencia, se actualiza con regularidad el conocimiento sobre el cambio climático y se usa para evaluar los riesgos y oportunidades para el ciclo de vida de la instalación de relaves, en cumplimiento con los principios de gestión adaptativa, con la meta de mejorar la resistencia al cambio climático. | J25: 1 | L25: 2
A26: C025 | B26: II | C26: BASE DE CONOCIMIENTOS INTEGRADA | D26: Principio 03 | E26: Utilizar los elementos de la base de conocimientos – sociales, ambientales, de la economía local y técnicos – con el fin de informar las decisiones durante el ciclo de vida de la instalación de relaves, incluido su cierre | F26: Requisito 03.2 | G26: Requisito 03.2 Para nuevas instalaciones de relaves, el Operador deberá utilizar la base de conocimientos y realizará un análisis de alternativas de criterio múltiple de todos los sitios, tecnologías y estrategias factibles para la gestión de relaves. El objetivo de este análisis será de: (i) seleccionar una alternativa que minimice los riesgos a las personas y medioambiente durante el ciclo de vida de la instalación de relaves, y (ii) minimiza el volumen de aguas y relaves colocados en instalaciones de relaves externas. Este análisis será un análisis objetivo de restricciones que será revisado por la Junta de Revisión Independiente de Relaves (ITRB) o un revisor técnico superior independiente. Para las instalaciones de relaves existentes, el Operador deberá revisar y refinar periódicamente las tecnologías y diseños de relaves, y las estrategias de gestión para minimizar riesgos y mejorar resultados medioambientales. Se aplicaría una excepción a las instalaciones que se demuestren estar en un estado de cierre seguro. | H26: 3.2 - A | I26: 3.2 A Para las nuevas instalaciones de relaves, un Análisis de Alternativas1 se realiza para examinar sitios, tecnologías y estrategias factibles para el tratamiento de relaves durante el ciclo de vida, que busca minimizar: - riesgos a las personas y medio ambiente; - volumen de relaves y aguas almacenados en instalaciones superficiales. | J26: =1/3 -> 0.33333333 | L26: 1
A27: C026 | B27: II | C27: BASE DE CONOCIMIENTOS INTEGRADA | D27: Principio 03 | E27: Utilizar los elementos de la base de conocimientos – sociales, ambientales, de la economía local y técnicos – con el fin de informar las decisiones durante el ciclo de vida de la instalación de relaves, incluido su cierre | F27: Requisito 03.2 | G27: Requisito 03.2 Para nuevas instalaciones de relaves, el Operador deberá utilizar la base de conocimientos y realizará un análisis de alternativas de criterio múltiple de todos los sitios, tecnologías y estrategias factibles para la gestión de relaves. El objetivo de este análisis será de: (i) seleccionar una alternativa que minimice los riesgos a las personas y medioambiente durante el ciclo de vida de la instalación de relaves, y (ii) minimiza el volumen de aguas y relaves colocados en instalaciones de relaves externas. Este análisis será un análisis objetivo de restricciones que será revisado por la Junta de Revisión Independiente de Relaves (ITRB) o un revisor técnico superior independiente. Para las instalaciones de relaves existentes, el Operador deberá revisar y refinar periódicamente las tecnologías y diseños de relaves, y las estrategias de gestión para minimizar riesgos y mejorar resultados medioambientales. Se aplicaría una excepción a las instalaciones que se demuestren estar en un estado de cierre seguro. | H27: 3.2 - B | I27: 3.2 B Para instalaciones existentes que no estén en un estado de cierre seguro, hay revisiones periódicas de las tecnologías, diseños y estrategias de tratamiento de relaves, y evaluaciones del potencial para implementar mejoras que surjan de las revisiones. | J27: =1/3 -> 0.33333333 | L27: 1
A28: C027 | B28: II | C28: BASE DE CONOCIMIENTOS INTEGRADA | D28: Principio 03 | E28: Utilizar los elementos de la base de conocimientos – sociales, ambientales, de la economía local y técnicos – con el fin de informar las decisiones durante el ciclo de vida de la instalación de relaves, incluido su cierre | F28: Requisito 03.2 | G28: Requisito 03.2 Para nuevas instalaciones de relaves, el Operador deberá utilizar la base de conocimientos y realizará un análisis de alternativas de criterio múltiple de todos los sitios, tecnologías y estrategias factibles para la gestión de relaves. El objetivo de este análisis será de: (i) seleccionar una alternativa que minimice los riesgos a las personas y medioambiente durante el ciclo de vida de la instalación de relaves, y (ii) minimiza el volumen de aguas y relaves colocados en instalaciones de relaves externas. Este análisis será un análisis objetivo de restricciones que será revisado por la Junta de Revisión Independiente de Relaves (ITRB) o un revisor técnico superior independiente. Para las instalaciones de relaves existentes, el Operador deberá revisar y refinar periódicamente las tecnologías y diseños de relaves, y las estrategias de gestión para minimizar riesgos y mejorar resultados medioambientales. Se aplicaría una excepción a las instalaciones que se demuestren estar en un estado de cierre seguro. | H28: 3.2 - C | I28: 3.2 C Para las nuevas instalaciones, el análisis es revisado por el ITRB o un revisor técnico superior independiente. | J28: =1/3 -> 0.33333333 | L28: 1
A29: C028 | B29: II | C29: BASE DE CONOCIMIENTOS INTEGRADA | D29: Principio 03 | E29: Utilizar los elementos de la base de conocimientos – sociales, ambientales, de la economía local y técnicos – con el fin de informar las decisiones durante el ciclo de vida de la instalación de relaves, incluido su cierre | F29: Requisito 03.3 | G29: Requisito 03.3 Para las nuevas instalaciones de relaves, utilizar la base de conocimientos, incluyendo la incertidumbre debida al cambio climático para evaluar los impactos sociales, medioambientales y económicos locales de la instalación de relaves y su falla potencial a lo largo de su ciclo de vida. Donde las evaluaciones de impacto predicen impactos materiales agudos o crónicos, el Operador deberá desarrollar, documentar e implementar planes de mitigación y gestión usando la jerarquía de mitigación. | H29: 3.3 - A | I29: 3.3 - A Se realizan las evaluaciones de impacto medioambiental, social y económico locales y se informan a la base de conocimiento existente. | J29: =1/4 -> 0.25 | L29: 2
A30: C029 | B30: II | C30: BASE DE CONOCIMIENTOS INTEGRADA | D30: Principio 03 | E30: Utilizar los elementos de la base de conocimientos – sociales, ambientales, de la economía local y técnicos – con el fin de informar las decisiones durante el ciclo de vida de la instalación de relaves, incluido su cierre | F30: Requisito 03.3 | G30: Requisito 03.3 Para las nuevas instalaciones de relaves, utilizar la base de conocimientos, incluyendo la incertidumbre debida al cambio climático para evaluar los impactos sociales, medioambientales y económicos locales de la instalación de relaves y su falla potencial a lo largo de su ciclo de vida. Donde las evaluaciones de impacto predicen impactos materiales agudos o crónicos, el Operador deberá desarrollar, documentar e implementar planes de mitigación y gestión usando la jerarquía de mitigación. | H30: 3.3 - B | I30: 3.3 - B Las evaluaciones ambientales, sociales y económico locales demuestran que las incertidumbres son consideradas en la evaluación de la vida de los impactos de las instalaciones de relaves y si hay algún potencial para una falla creíble a lo largo del ciclo de vida de la instalación de relaves. | J30: =1/4 -> 0.25 | L30: 2
A31: C030 | B31: II | C31: BASE DE CONOCIMIENTOS INTEGRADA | D31: Principio 03 | E31: Utilizar los elementos de la base de conocimientos – sociales, ambientales, de la economía local y técnicos – con el fin de informar las decisiones durante el ciclo de vida de la instalación de relaves, incluido su cierre | F31: Requisito 03.3 | G31: Requisito 03.3 Para las nuevas instalaciones de relaves, utilizar la base de conocimientos, incluyendo la incertidumbre debida al cambio climático para evaluar los impactos sociales, medioambientales y económicos locales de la instalación de relaves y su falla potencial a lo largo de su ciclo de vida. Donde las evaluaciones de impacto predicen impactos materiales agudos o crónicos, el Operador deberá desarrollar, documentar e implementar planes de mitigación y gestión usando la jerarquía de mitigación. | H31: 3.3 - C | I31: 3.3 - C Medidas y planes de mitigación y gestión son desarrollados, documentados e implementados para abarcar los impactos materiales crónicos y agudos. | J31: =1/4 -> 0.25 | L31: 2
A32: C031 | B32: II | C32: BASE DE CONOCIMIENTOS INTEGRADA | D32: Principio 03 | E32: Utilizar los elementos de la base de conocimientos – sociales, ambientales, de la economía local y técnicos – con el fin de informar las decisiones durante el ciclo de vida de la instalación de relaves, incluido su cierre | F32: Requisito 03.3 | G32: Requisito 03.3 Para las nuevas instalaciones de relaves, utilizar la base de conocimientos, incluyendo la incertidumbre debida al cambio climático para evaluar los impactos sociales, medioambientales y económicos locales de la instalación de relaves y su falla potencial a lo largo de su ciclo de vida. Donde las evaluaciones de impacto predicen impactos materiales agudos o crónicos, el Operador deberá desarrollar, documentar e implementar planes de mitigación y gestión usando la jerarquía de mitigación. | H32: 3.3 - D | I32: 3.3 - D Los planes de gestión se basan en los principios y prácticas de una jerarquía de mitigación y planes de gestión para la instalación de relaves y se actualizan a lo largo del ciclo de vida de la instalación de relaves. | J32: =1/4 -> 0.25 | L32: 2
A33: C032 | B33: II | C33: BASE DE CONOCIMIENTOS INTEGRADA | D33: Principio 03 | E33: Utilizar los elementos de la base de conocimientos – sociales, ambientales, de la economía local y técnicos – con el fin de informar las decisiones durante el ciclo de vida de la instalación de relaves, incluido su cierre | F33: Requisito 03.4 | G33: Requisito 03.4 Actualizar la evaluación de los impactos sociales, medioambientales y económicos locales para reflejar un cambio material ya sea para la instalación de relaves o para el contexto social, medioambiental y económico local. Si nuevos datos indican que los impactos de la instalación de relaves han cambiado materialmente, incluso como el resultado de conocimiento del cambio climático o impactos a largo plazo, el Operador deberá actualizar la gestión de la instalación de relaves para reflejar los nuevos datos utilizando las mejores prácticas de Gestión Adaptativa. | H33: 3.4 - A | I33: 3.4 - A El cambio material como ha sido definido por el Operador es aplicado consistentemente para generar actualizaciones en las evaluaciones medioambientales, sociales y económicas de la instalación de relaves. | J33: =1/2 -> 0.5 | L33: 2
A34: C033 | B34: II | C34: BASE DE CONOCIMIENTOS INTEGRADA | D34: Principio 03 | E34: Utilizar los elementos de la base de conocimientos – sociales, ambientales, de la economía local y técnicos – con el fin de informar las decisiones durante el ciclo de vida de la instalación de relaves, incluido su cierre | F34: Requisito 03.4 | G34: Requisito 03.4 Actualizar la evaluación de los impactos sociales, medioambientales y económicos locales para reflejar un cambio material ya sea para la instalación de relaves o para el contexto social, medioambiental y económico local. Si nuevos datos indican que los impactos de la instalación de relaves han cambiado materialmente, incluso como el resultado de conocimiento del cambio climático o impactos a largo plazo, el Operador deberá actualizar la gestión de la instalación de relaves para reflejar los nuevos datos utilizando las mejores prácticas de Gestión Adaptativa. | H34: 3.4 - B | I34: 3.4 - B Se actualiza la gestión de la instalación de relaves de acuerdo a las mejores prácticas de gestión adaptativa si nuevos datos (incluyendo conocimientos sobre cambio climático) indican que los impactos de la instalación de relaves han cambiado materialmente. | J34: =1/2 -> 0.5 | L34: 2
A35: C034 | B35: III | C35: DISEÑO, CONSTRUCCIÓN, OPERACIÓN Y MONITOREO DE LAS INSTALACIONES DE RELAVES | D35: Principio 04 | E35: Desarrollar planes y criterios de diseño para la instalación de relaves con el fin de minimizar los riesgos para todas las fases del ciclo de vida, incluso el cierre y el post cierre. | F35: Requisito 04.1 | G35: Requisito 04.1 Determinar la consecuencia de la clasificación de fallas de la instalación de relaves al evaluar las condiciones de aguas abajo documentadas en la base de conocimientos y seleccionar la clasificación correspondiente a la Clasificación de Consecuencias más elevada para cada categoría en el Anexo 2, Tabla 1. La evaluación y selección de la clasificación se hará en base a los modelos de falla creíbles, y debe ser defendible y documentado. | H35: 4.1 - A | I35: 4.1 - A Se determina la clasificación de consecuencias de fallas de instalaciones de relaves al evaluar las condiciones aguas abajo documentadas en la base de conocimientos y adopta: (i) la clasificación de consecuencias para el nivel más alto en cada categoría en el Anexo 2, Tabla 1, o (ii) un enfoque más conservador mediante la adopción de criterios de diseño de carga post-cierre “Extremos” en el Anexo 2. | J35: =1/3 -> 0.33333333 | L35: 3
A36: C035 | B36: III | C36: DISEÑO, CONSTRUCCIÓN, OPERACIÓN Y MONITOREO DE LAS INSTALACIONES DE RELAVES | D36: Principio 04 | E36: Desarrollar planes y criterios de diseño para la instalación de relaves con el fin de minimizar los riesgos para todas las fases del ciclo de vida, incluso el cierre y el post cierre. | F36: Requisito 04.1 | G36: Requisito 04.1 Determinar la consecuencia de la clasificación de fallas de la instalación de relaves al evaluar las condiciones de aguas abajo documentadas en la base de conocimientos y seleccionar la clasificación correspondiente a la Clasificación de Consecuencias más elevada para cada categoría en el Anexo 2, Tabla 1. La evaluación y selección de la clasificación se hará en base a los modelos de falla creíbles, y debe ser defendible y documentado. | H36: 4.1 - B | I36: 4.1 - B Para a(i) basar la evaluación y selección de la clasificación en modelos/escenarios de fallas creíbles. | J36: =1/3 -> 0.33333333 | L36: 3
A37: C036 | B37: III | C37: DISEÑO, CONSTRUCCIÓN, OPERACIÓN Y MONITOREO DE LAS INSTALACIONES DE RELAVES | D37: Principio 04 | E37: Desarrollar planes y criterios de diseño para la instalación de relaves con el fin de minimizar los riesgos para todas las fases del ciclo de vida, incluso el cierre y el post cierre. | F37: Requisito 04.1 | G37: Requisito 04.1 Determinar la consecuencia de la clasificación de fallas de la instalación de relaves al evaluar las condiciones de aguas abajo documentadas en la base de conocimientos y seleccionar la clasificación correspondiente a la Clasificación de Consecuencias más elevada para cada categoría en el Anexo 2, Tabla 1. La evaluación y selección de la clasificación se hará en base a los modelos de falla creíbles, y debe ser defendible y documentado. | H37: 4.1 - C | I37: 4.1 - C Documentar la evaluación y selección con evidencia defendible. | J37: =1/3 -> 0.33333333 | L37: 3
A38: C037 | B38: III | C38: DISEÑO, CONSTRUCCIÓN, OPERACIÓN Y MONITOREO DE LAS INSTALACIONES DE RELAVES | D38: Principio 04 | E38: Desarrollar planes y criterios de diseño para la instalación de relaves con el fin de minimizar los riesgos para todas las fases del ciclo de vida, incluso el cierre y el post cierre. | F38: Requisito 04.2 | G38: Requisito 04.2 Con el objetivo de mantener flexibilidad en el desarrollo de una nueva instalación de relaves y optimizar costos mientras se da prioridad a la seguridad durante el ciclo de vida de la instalación de relaves. a) Desarrollar diseños preliminares para la instalación de relaves con el criterio de carga de diseño externo consistente tanto con la clasificación de consecuencias de la falla en base a condiciones actuales y la Clasificación de Consecuencias mayor (incluyendo “Extrema”) - b) Informado por la gama de requisitos definidos por los diseños preliminares, ya sea: - Implementar el diseño para los criterios de carga de la Clasificación de Consecuencias “Extremas”; o - Implementar el diseño para el criterio de Clasificación de Consecuencias actual o uno más elevado, y demostrar factibilidad, a nivel de prueba de concepto, para mejorar el diseño para que el criterio de clasificación “Extrema” se mantenga a lo largo del ciclo de vida de la instalación de relaves. c) Si se implementa la opción B.2, revisar la clasificación de las consecuencias de la falla al momento de la Revisión de Seguridad de Represas (RSR) y por lo menos cada cinco años, o más pronto si se da un cambio material en el contexto social, medioambiental y económico local, y completar la actualización de la instalación de relaves acorde a la nueva Clasificación de Consecuencias según lo determinado por la RSR dentro de tres años. Esta revisión procederá hasta que la instalación de relaves haya sido cerrada de forma segura de acuerdo a este Estándar. d) El proceso descrito anteriormente será revisado por la Junta de Revisión de Relaves Independiente (ITRB) o el revisor técnico senior independiente, como sea adecuado para la Clasificación de Consecuencias de la instalación de relaves. Sujeto al Requisito 4.7, los Requisitos 4.2c y 4.2 también serán aplicados a instalaciones de relaves existentes. | H38: 4.2 - A | I38: 4.2 - A Se preparan diseños preliminares para la instalación de relaves, con consideración de las etapas del ciclo de vida, utilizando criterios de carga de diseños externos consistentes con la clasificación de consecuencias de fallas basada en condiciones actuales y la Clasificación de Consecuencias mayor (incluyendo “Extrema”). | J38: =1/5 -> 0.2 | L38: 3
A39: C038 | B39: III | C39: DISEÑO, CONSTRUCCIÓN, OPERACIÓN Y MONITOREO DE LAS INSTALACIONES DE RELAVES | D39: Principio 04 | E39: Desarrollar planes y criterios de diseño para la instalación de relaves con el fin de minimizar los riesgos para todas las fases del ciclo de vida, incluso el cierre y el post cierre. | F39: Requisito 04.2 | G39: Requisito 04.2 Con el objetivo de mantener flexibilidad en el desarrollo de una nueva instalación de relaves y optimizar costos mientras se da prioridad a la seguridad durante el ciclo de vida de la instalación de relaves. a) Desarrollar diseños preliminares para la instalación de relaves con el criterio de carga de diseño externo consistente tanto con la clasificación de consecuencias de la falla en base a condiciones actuales y la Clasificación de Consecuencias mayor (incluyendo “Extrema”) - b) Informado por la gama de requisitos definidos por los diseños preliminares, ya sea: - Implementar el diseño para los criterios de carga de la Clasificación de Consecuencias “Extremas”; o - Implementar el diseño para el criterio de Clasificación de Consecuencias actual o uno más elevado, y demostrar factibilidad, a nivel de prueba de concepto, para mejorar el diseño para que el criterio de clasificación “Extrema” se mantenga a lo largo del ciclo de vida de la instalación de relaves. c) Si se implementa la opción B.2, revisar la clasificación de las consecuencias de la falla al momento de la Revisión de Seguridad de Represas (RSR) y por lo menos cada cinco años, o más pronto si se da un cambio material en el contexto social, medioambiental y económico local, y completar la actualización de la instalación de relaves acorde a la nueva Clasificación de Consecuencias según lo determinado por la RSR dentro de tres años. Esta revisión procederá hasta que la instalación de relaves haya sido cerrada de forma segura de acuerdo a este Estándar. d) El proceso descrito anteriormente será revisado por la Junta de Revisión de Relaves Independiente (ITRB) o el revisor técnico senior independiente, como sea adecuado para la Clasificación de Consecuencias de la instalación de relaves. Sujeto al Requisito 4.7, los Requisitos 4.2c y 4.2 también serán aplicados a instalaciones de relaves existentes. | H39: 4.2 - B | I39: 4.2 - B Adoptar (i) los criterios de carga externa de la Clasificación de Consecuencias “Extrema”, o (ii) adoptar los criterios de carga de la Clasificación de Consecuencias actual o una mayor, y demostrar la factibilidad, a nivel de prueba de concepto, para mejorar el diseño para que el criterio de clasificación “Extremo” se mantenga a lo largo del ciclo de vida de la instalación de relaves. | J39: =1/5 -> 0.2 | L39: 3
A40: C039 | B40: III | C40: DISEÑO, CONSTRUCCIÓN, OPERACIÓN Y MONITOREO DE LAS INSTALACIONES DE RELAVES | D40: Principio 04 | E40: Desarrollar planes y criterios de diseño para la instalación de relaves con el fin de minimizar los riesgos para todas las fases del ciclo de vida, incluso el cierre y el post cierre. | F40: Requisito 04.2 | G40: Requisito 04.2 Con el objetivo de mantener flexibilidad en el desarrollo de una nueva instalación de relaves y optimizar costos mientras se da prioridad a la seguridad durante el ciclo de vida de la instalación de relaves. a) Desarrollar diseños preliminares para la instalación de relaves con el criterio de carga de diseño externo consistente tanto con la clasificación de consecuencias de la falla en base a condiciones actuales y la Clasificación de Consecuencias mayor (incluyendo “Extrema”) - b) Informado por la gama de requisitos definidos por los diseños preliminares, ya sea: - Implementar el diseño para los criterios de carga de la Clasificación de Consecuencias “Extremas”; o - Implementar el diseño para el criterio de Clasificación de Consecuencias actual o uno más elevado, y demostrar factibilidad, a nivel de prueba de concepto, para mejorar el diseño para que el criterio de clasificación “Extrema” se mantenga a lo largo del ciclo de vida de la instalación de relaves. c) Si se implementa la opción B.2, revisar la clasificación de las consecuencias de la falla al momento de la Revisión de Seguridad de Represas (RSR) y por lo menos cada cinco años, o más pronto si se da un cambio material en el contexto social, medioambiental y económico local, y completar la actualización de la instalación de relaves acorde a la nueva Clasificación de Consecuencias según lo determinado por la RSR dentro de tres años. Esta revisión procederá hasta que la instalación de relaves haya sido cerrada de forma segura de acuerdo a este Estándar. d) El proceso descrito anteriormente será revisado por la Junta de Revisión de Relaves Independiente (ITRB) o el revisor técnico senior independiente, como sea adecuado para la Clasificación de Consecuencias de la instalación de relaves. Sujeto al Requisito 4.7, los Requisitos 4.2c y 4.2 también serán aplicados a instalaciones de relaves existentes. | H40: 4.2 - C | I40: 4.2 - C Si la opción b(ii) anterior es implementada, la Clasificación de Consecuencias es revisada al momento de la Revisión de Seguridad de Represas (DRS) 1 y por lo menos cada cinco años, o antes si se da algún cambio material en el contexto social, medioambiental o económico local, y completar la mejora de la instalación de relaves conforme a la nueva Clasificación de Consecuencias determinada por la DSR dentro de tres años. Esta revisión procederá hasta que la instalación de relaves haya sido cerrada de forma segura de acuerdo a este Estándar. | J40: =1/5 -> 0.2 | L40: 3
A41: C040 | B41: III | C41: DISEÑO, CONSTRUCCIÓN, OPERACIÓN Y MONITOREO DE LAS INSTALACIONES DE RELAVES | D41: Principio 04 | E41: Desarrollar planes y criterios de diseño para la instalación de relaves con el fin de minimizar los riesgos para todas las fases del ciclo de vida, incluso el cierre y el post cierre. | F41: Requisito 04.2 | G41: Requisito 04.2 Con el objetivo de mantener flexibilidad en el desarrollo de una nueva instalación de relaves y optimizar costos mientras se da prioridad a la seguridad durante el ciclo de vida de la instalación de relaves. a) Desarrollar diseños preliminares para la instalación de relaves con el criterio de carga de diseño externo consistente tanto con la clasificación de consecuencias de la falla en base a condiciones actuales y la Clasificación de Consecuencias mayor (incluyendo “Extrema”) - b) Informado por la gama de requisitos definidos por los diseños preliminares, ya sea: - Implementar el diseño para los criterios de carga de la Clasificación de Consecuencias “Extremas”; o - Implementar el diseño para el criterio de Clasificación de Consecuencias actual o uno más elevado, y demostrar factibilidad, a nivel de prueba de concepto, para mejorar el diseño para que el criterio de clasificación “Extrema” se mantenga a lo largo del ciclo de vida de la instalación de relaves. c) Si se implementa la opción B.2, revisar la clasificación de las consecuencias de la falla al momento de la Revisión de Seguridad de Represas (RSR) y por lo menos cada cinco años, o más pronto si se da un cambio material en el contexto social, medioambiental y económico local, y completar la actualización de la instalación de relaves acorde a la nueva Clasificación de Consecuencias según lo determinado por la RSR dentro de tres años. Esta revisión procederá hasta que la instalación de relaves haya sido cerrada de forma segura de acuerdo a este Estándar. d) El proceso descrito anteriormente será revisado por la Junta de Revisión de Relaves Independiente (ITRB) o el revisor técnico senior independiente, como sea adecuado para la Clasificación de Consecuencias de la instalación de relaves. Sujeto al Requisito 4.7, los Requisitos 4.2c y 4.2 también serán aplicados a instalaciones de relaves existentes. | H41: 4.2 - D | I41: 4.2 - D El proceso descrito en a, b y c, deberá ser revisado por la Junta de Revisión de Relaves Independiente (ITRB) o el revisor técnico senior independiente, según sea apropiado para la Clasificación de Consecuencias de la instalación de relaves. | J41: =1/5 -> 0.2 | L41: 3
A42: C041 | B42: III | C42: DISEÑO, CONSTRUCCIÓN, OPERACIÓN Y MONITOREO DE LAS INSTALACIONES DE RELAVES | D42: Principio 04 | E42: Desarrollar planes y criterios de diseño para la instalación de relaves con el fin de minimizar los riesgos para todas las fases del ciclo de vida, incluso el cierre y el post cierre. | F42: Requisito 04.2 | G42: Requisito 04.2 Con el objetivo de mantener flexibilidad en el desarrollo de una nueva instalación de relaves y optimizar costos mientras se da prioridad a la seguridad durante el ciclo de vida de la instalación de relaves. a) Desarrollar diseños preliminares para la instalación de relaves con el criterio de carga de diseño externo consistente tanto con la clasificación de consecuencias de la falla en base a condiciones actuales y la Clasificación de Consecuencias mayor (incluyendo “Extrema”) - b) Informado por la gama de requisitos definidos por los diseños preliminares, ya sea: - Implementar el diseño para los criterios de carga de la Clasificación de Consecuencias “Extremas”; o - Implementar el diseño para el criterio de Clasificación de Consecuencias actual o uno más elevado, y demostrar factibilidad, a nivel de prueba de concepto, para mejorar el diseño para que el criterio de clasificación “Extrema” se mantenga a lo largo del ciclo de vida de la instalación de relaves. c) Si se implementa la opción B.2, revisar la clasificación de las consecuencias de la falla al momento de la Revisión de Seguridad de Represas (RSR) y por lo menos cada cinco años, o más pronto si se da un cambio material en el contexto social, medioambiental y económico local, y completar la actualización de la instalación de relaves acorde a la nueva Clasificación de Consecuencias según lo determinado por la RSR dentro de tres años. Esta revisión procederá hasta que la instalación de relaves haya sido cerrada de forma segura de acuerdo a este Estándar. d) El proceso descrito anteriormente será revisado por la Junta de Revisión de Relaves Independiente (ITRB) o el revisor técnico senior independiente, como sea adecuado para la Clasificación de Consecuencias de la instalación de relaves. Sujeto al Requisito 4.7, los Requisitos 4.2c y 4.2 también serán aplicados a instalaciones de relaves existentes. | H42: 4.2 - E | I42: 4.2 - E Sujeto al Requisito 4.7, los Requisitos 4.2 c y 4.2 d deberán aplicarse también a instalaciones de relaves existentes. | J42: =1/5 -> 0.2 | L42: 3
A43: C042 | B43: III | C43: DISEÑO, CONSTRUCCIÓN, OPERACIÓN Y MONITOREO DE LAS INSTALACIONES DE RELAVES | D43: Principio 04 | E43: Desarrollar planes y criterios de diseño para la instalación de relaves con el fin de minimizar los riesgos para todas las fases del ciclo de vida, incluso el cierre y el post cierre. | F43: Requisito 04.3 | G43: Requisito 04.3 El Ejecutivo Responsable deberá tomar la decisión de adoptar un diseño para el criterio actual de Clasificación de Consecuencias y para mantener la flexibilidad para actualizar el diseño al criterio de clasificación más elevado posteriormente en el ciclo de vida de la instalación de relaves. Esta decisión deberá ser documentada. | H43: 4.3 - A | I43: 4.3 - A Las cargas extremas ya están en su lugar. | J43: =1/2 -> 0.5 | L43: 1
A44: C043 | B44: III | C44: DISEÑO, CONSTRUCCIÓN, OPERACIÓN Y MONITOREO DE LAS INSTALACIONES DE RELAVES | D44: Principio 04 | E44: Desarrollar planes y criterios de diseño para la instalación de relaves con el fin de minimizar los riesgos para todas las fases del ciclo de vida, incluso el cierre y el post cierre. | F44: Requisito 04.3 | G44: Requisito 04.3 El Ejecutivo Responsable deberá tomar la decisión de adoptar un diseño para el criterio actual de Clasificación de Consecuencias y para mantener la flexibilidad para actualizar el diseño al criterio de clasificación más elevado posteriormente en el ciclo de vida de la instalación de relaves. Esta decisión deberá ser documentada. | H44: 4.3 - B | I44: 4.3 - B Si no se adopta el criterio de carga externo de Clasificación de Consecuencias Extremas, el Ejecutivo Responsable deberá tomar la decisión de adoptar un diseño para el criterio actual de Clasificación de Consecuencias y mantener la flexibilidad para actualizar el diseño para el criterio de clasificación más alto más adelante en el ciclo de vida de la instalación de relaves. | J44: =1/2 -> 0.5 | L44: 1
A45: C044 | B45: III | C45: DISEÑO, CONSTRUCCIÓN, OPERACIÓN Y MONITOREO DE LAS INSTALACIONES DE RELAVES | D45: Principio 04 | E45: Desarrollar planes y criterios de diseño para la instalación de relaves con el fin de minimizar los riesgos para todas las fases del ciclo de vida, incluso el cierre y el post cierre. | F45: Requisito 04.4 | G45: Requisito 04.4 Seleccionar, identificar explícitamente y documentar todos los criterios de diseño que son adecuados para minimizar los riesgos de todos los modelos de falla creíbles para todas las fases del ciclo de vida de la instalación de relaves | H45: 4.4 - A | I45: 4.4 - A Seleccionar e identificar criterios de diseño que son adecuados para minimizar los riesgos para todos los modelos de falla creíbles durante cada fase del ciclo de vida de la instalación de relaves. | J45: =1/2 -> 0.5 | L45: 3
A46: C045 | B46: III | C46: DISEÑO, CONSTRUCCIÓN, OPERACIÓN Y MONITOREO DE LAS INSTALACIONES DE RELAVES | D46: Principio 04 | E46: Desarrollar planes y criterios de diseño para la instalación de relaves con el fin de minimizar los riesgos para todas las fases del ciclo de vida, incluso el cierre y el post cierre. | F46: Requisito 04.4 | G46: Requisito 04.4 Seleccionar, identificar explícitamente y documentar todos los criterios de diseño que son adecuados para minimizar los riesgos de todos los modelos de falla creíbles para todas las fases del ciclo de vida de la instalación de relaves | H46: 4.4 - B | I46: 4.4 - B Documentar el razonamiento detrás del criterio de diseño seleccionado para minimizar riesgos. | J46: =1/2 -> 0.5 | L46: 3
A47: C046 | B47: III | C47: DISEÑO, CONSTRUCCIÓN, OPERACIÓN Y MONITOREO DE LAS INSTALACIONES DE RELAVES | D47: Principio 04 | E47: Desarrollar planes y criterios de diseño para la instalación de relaves con el fin de minimizar los riesgos para todas las fases del ciclo de vida, incluso el cierre y el post cierre. | F47: Requisito 04.5 | G47: Requisito 04.5 Aplicar criterios de diseño, tales como factores de seguridad para la estabilidad de taludes y el manejo de filtraciones, que consideren las propiedades estimadas de los materiales y el desempeño esperado de los elementos de diseño, y la calidad de la implementación de los sistemas de gestión de riesgos. Estos problemas | H47: 4.5 - A | I47: 4.5 - A Un desarrollo y aplicación de un criterio de diseño1 tales como factores de seguridad para la estabilidad de taludes y manejo de filtraciones, para cada fase del ciclo de vida que considere: las propiedades operativas2 estimadas de los materiales y desempeño esperado de los elementos de diseño y la calidad de la implementación de los sistemas de gestión de riesgos. | J47: =1/2 -> 0.5 | L47: 3
A48: C047 | B48: III | C48: DISEÑO, CONSTRUCCIÓN, OPERACIÓN Y MONITOREO DE LAS INSTALACIONES DE RELAVES | D48: Principio 04 | E48: Desarrollar planes y criterios de diseño para la instalación de relaves con el fin de minimizar los riesgos para todas las fases del ciclo de vida, incluso el cierre y el post cierre. | F48: Requisito 04.5 | G48: Requisito 04.5 Aplicar criterios de diseño, tales como factores de seguridad para la estabilidad de taludes y el manejo de filtraciones, que consideren las propiedades estimadas de los materiales y el desempeño esperado de los elementos de diseño, y la calidad de la implementación de los sistemas de gestión de riesgos. Estos problemas | H48: 4.5 - B | I48: 4.5 - B Tener en cuenta estos problemas de diseño e implementación en las evaluaciones que estén basadas en análisis de deformación. | J48: =1/2 -> 0.5 | L48: 3
A49: C048 | B49: III | C49: DISEÑO, CONSTRUCCIÓN, OPERACIÓN Y MONITOREO DE LAS INSTALACIONES DE RELAVES | D49: Principio 04 | E49: Desarrollar planes y criterios de diseño para la instalación de relaves con el fin de minimizar los riesgos para todas las fases del ciclo de vida, incluso el cierre y el post cierre. | F49: Requisito 04.6 | G49: Requisito 04.6 Identificar y abarcar los modelos de falla frágil con un criterio de diseño conservador, independiente de mecanismos de activación, para minimizar su impacto en el desempeño de la instalación de relaves. | H49: 4.6 - A | I49: 4.6 - A Se documenta una evaluación del potencial del modelo de falla frágil y se abordan los análisis en el Reporte de Diseño Base (DBR). | J49: 1 | L49: 3
A50: C049 | B50: III | C50: DISEÑO, CONSTRUCCIÓN, OPERACIÓN Y MONITOREO DE LAS INSTALACIONES DE RELAVES | D50: Principio 04 | E50: Desarrollar planes y criterios de diseño para la instalación de relaves con el fin de minimizar los riesgos para todas las fases del ciclo de vida, incluso el cierre y el post cierre. | F50: Requisito 04.7 | G50: Requisito 04.7 Las Instalaciones de relaves existentes deben cumplir con los Requisitos bajo el Principio 4, a excepción de aquellos aspectos en los que el Ingeniero de Registro (EOR), con revisión por parte de la ITRB o un revisor técnico senior independiente, determine que la mejorar de una instalación de relaves existente no es viable o no se puede aplicar de forma retroactiva. En este caso el Ejecutivo Responsable deberá aprobar y documentar la implementación de las medidas para reducir tanto la probabilidad de, como las consecuencias de una falla de una instalación de relaves, para así reducir el riesgo a un nivel tan bajo como sea razonablemente factible (ALARP). La base y el tiempo para abordar la mejora de instalaciones de relaves existentes deberá estar informado sobre los riesgos y debe llevarse a cabo tan pronto como sea razonablemente posible. | H50: 4.7 - A | I50: 4.7 - A Que las instalaciones de relaves existentes deberán cumplir con los requisitos bajo el Principio 4, a excepción de aquellos aspectos donde el Ingeniero de Registro (EOR), con revisión de la ITRB o de un revisor técnico senior independiente, como sea adecuado, determine que una mejora de una instalación de relaves existente no es requerida, viable o no se puede aplicar de forma retroactiva. | J50: =1/3 -> 0.33333333 | L50: 3
A51: C050 | B51: III | C51: DISEÑO, CONSTRUCCIÓN, OPERACIÓN Y MONITOREO DE LAS INSTALACIONES DE RELAVES | D51: Principio 04 | E51: Desarrollar planes y criterios de diseño para la instalación de relaves con el fin de minimizar los riesgos para todas las fases del ciclo de vida, incluso el cierre y el post cierre. | F51: Requisito 04.7 | G51: Requisito 04.7 Las Instalaciones de relaves existentes deben cumplir con los Requisitos bajo el Principio 4, a excepción de aquellos aspectos en los que el Ingeniero de Registro (EOR), con revisión por parte de la ITRB o un revisor técnico senior independiente, determine que la mejorar de una instalación de relaves existente no es viable o no se puede aplicar de forma retroactiva. En este caso el Ejecutivo Responsable deberá aprobar y documentar la implementación de las medidas para reducir tanto la probabilidad de, como las consecuencias de una falla de una instalación de relaves, para así reducir el riesgo a un nivel tan bajo como sea razonablemente factible (ALARP). La base y el tiempo para abordar la mejora de instalaciones de relaves existentes deberá estar informado sobre los riesgos y debe llevarse a cabo tan pronto como sea razonablemente posible. | H51: 4.7 - B | I51: 4.7 - B Que si la condición (a). de arriba aplica, el Ejecutivo Responsable deberá aprobar y documentar la implementación de medidas para reducir tanto la probabilidad de, como las consecuencias de una falla de una instalación de relaves para reducir el riesgo a un nivel tan bajo como sea razonablemente factible (ALARP). | J51: =1/3 -> 0.33333333 | L51: 3
A52: C051 | B52: III | C52: DISEÑO, CONSTRUCCIÓN, OPERACIÓN Y MONITOREO DE LAS INSTALACIONES DE RELAVES | D52: Principio 04 | E52: Desarrollar planes y criterios de diseño para la instalación de relaves con el fin de minimizar los riesgos para todas las fases del ciclo de vida, incluso el cierre y el post cierre. | F52: Requisito 04.7 | G52: Requisito 04.7 Las Instalaciones de relaves existentes deben cumplir con los Requisitos bajo el Principio 4, a excepción de aquellos aspectos en los que el Ingeniero de Registro (EOR), con revisión por parte de la ITRB o un revisor técnico senior independiente, determine que la mejorar de una instalación de relaves existente no es viable o no se puede aplicar de forma retroactiva. En este caso el Ejecutivo Responsable deberá aprobar y documentar la implementación de las medidas para reducir tanto la probabilidad de, como las consecuencias de una falla de una instalación de relaves, para así reducir el riesgo a un nivel tan bajo como sea razonablemente factible (ALARP). La base y el tiempo para abordar la mejora de instalaciones de relaves existentes deberá estar informado sobre los riesgos y debe llevarse a cabo tan pronto como sea razonablemente posible. | H52: 4.7 - C | I52: 4.7 - C La base y tiempo para abordar la mejora de las instalaciones de relaves existentes deberá estar informado sobre los riesgos y debe llevarse a cabo tan pronto como sea razonablemente factible. | J52: =1/3 -> 0.33333333 | L52: 3
A53: C052 | B53: III | C53: DISEÑO, CONSTRUCCIÓN, OPERACIÓN Y MONITOREO DE LAS INSTALACIONES DE RELAVES | D53: Principio 04 | E53: Desarrollar planes y criterios de diseño para la instalación de relaves con el fin de minimizar los riesgos para todas las fases del ciclo de vida, incluso el cierre y el post cierre. | F53: Requisito 04.8 | G53: Requisito 04.8 El EOR deberá preparar un Reporte de Base de Diseño (DBR) que detalle las hipótesis y criterios del diseño, incluyendo las restricciones de operación, y que proporcione una base para el diseño de todas las fases del ciclo de vida de la instalación de relaves. El DBR deberá ser revisado por la ITRB o por un revisor técnico senior independiente. El EOR deberá actualizar el DBR cada vez que haya un cambio material en las hipótesis de diseño, criterios de diseño, diseño o base de conocimiento y confirmar la consistencia entre estos elementos. | H53: 4.8 - A | I53: 4.8 - A Que el EOR preparará un Reporte de Base de Diseño (DBR) 1, 2, que detalle las hipótesis y criterios de diseño, incluyendo las restricciones de operación, y que proporcione la base para el diseño de todas las fases del ciclo de vida de la instalación de relaves. | J53: =1/3 -> 0.33333333 | L53: 3
A54: C053 | B54: III | C54: DISEÑO, CONSTRUCCIÓN, OPERACIÓN Y MONITOREO DE LAS INSTALACIONES DE RELAVES | D54: Principio 04 | E54: Desarrollar planes y criterios de diseño para la instalación de relaves con el fin de minimizar los riesgos para todas las fases del ciclo de vida, incluso el cierre y el post cierre. | F54: Requisito 04.8 | G54: Requisito 04.8 El EOR deberá preparar un Reporte de Base de Diseño (DBR) que detalle las hipótesis y criterios del diseño, incluyendo las restricciones de operación, y que proporcione una base para el diseño de todas las fases del ciclo de vida de la instalación de relaves. El DBR deberá ser revisado por la ITRB o por un revisor técnico senior independiente. El EOR deberá actualizar el DBR cada vez que haya un cambio material en las hipótesis de diseño, criterios de diseño, diseño o base de conocimiento y confirmar la consistencia entre estos elementos. | H54: 4.8 - B | I54: 4.8 - B Que el DBR será revisado por la ITRB o el revisor técnico senior independiente. | J54: =1/3 -> 0.33333333 | L54: 3
A55: C054 | B55: III | C55: DISEÑO, CONSTRUCCIÓN, OPERACIÓN Y MONITOREO DE LAS INSTALACIONES DE RELAVES | D55: Principio 04 | E55: Desarrollar planes y criterios de diseño para la instalación de relaves con el fin de minimizar los riesgos para todas las fases del ciclo de vida, incluso el cierre y el post cierre. | F55: Requisito 04.8 | G55: Requisito 04.8 El EOR deberá preparar un Reporte de Base de Diseño (DBR) que detalle las hipótesis y criterios del diseño, incluyendo las restricciones de operación, y que proporcione una base para el diseño de todas las fases del ciclo de vida de la instalación de relaves. El DBR deberá ser revisado por la ITRB o por un revisor técnico senior independiente. El EOR deberá actualizar el DBR cada vez que haya un cambio material en las hipótesis de diseño, criterios de diseño, diseño o base de conocimiento y confirmar la consistencia entre estos elementos. | H55: 4.8 - C | I55: 4.8 - C Que el EOR actualizará el DBR cada vez que haya un cambio material en las hipótesis del diseño, criterios del diseño, diseño o base de conocimiento y confirmar la consistencia interna entre estos elementos. | J55: =1/3 -> 0.33333333 | L55: 3
A56: C055 | B56: III | C56: DISEÑO, CONSTRUCCIÓN, OPERACIÓN Y MONITOREO DE LAS INSTALACIONES DE RELAVES | D56: Principio 05 | E56: Desarrollar un diseño sólido que integre la base de conocimientos y minimice el riesgo de falla que pueda afectar a las personas y el medio ambiente durante todas las fases del ciclo de vida de la instalación de relaves, incluso el cierre y post cierre. | F56: Requisito 05.1 | G56: Requisito 05.1 Para las nuevas instalaciones de relaves, incorporar el resultado del análisis de alternativas de criterio múltiple incluyendo el uso de tecnologías de relaves en el diseño de la instalación de relaves. Para expansiones de instalaciones de relaves existentes, investigar el potencial para refinar las tecnologías de relaves y enfoques de diseño con el objetivo de minimizar los riesgos a las personas y medioambiente a lo largo del ciclo de vida de la instalación de relaves. | H56: 5.1 - A | I56: 5.1 - A Que, para las nuevas instalaciones de relaves, el diseño incorpora los resultados del análisis de alternativas1 (según el Requisito 3.2). | J56: =1/3 -> 0.33333333 | L56: 1
A57: C056 | B57: III | C57: DISEÑO, CONSTRUCCIÓN, OPERACIÓN Y MONITOREO DE LAS INSTALACIONES DE RELAVES | D57: Principio 05 | E57: Desarrollar un diseño sólido que integre la base de conocimientos y minimice el riesgo de falla que pueda afectar a las personas y el medio ambiente durante todas las fases del ciclo de vida de la instalación de relaves, incluso el cierre y post cierre. | F57: Requisito 05.1 | G57: Requisito 05.1 Para las nuevas instalaciones de relaves, incorporar el resultado del análisis de alternativas de criterio múltiple incluyendo el uso de tecnologías de relaves en el diseño de la instalación de relaves. Para expansiones de instalaciones de relaves existentes, investigar el potencial para refinar las tecnologías de relaves y enfoques de diseño con el objetivo de minimizar los riesgos a las personas y medioambiente a lo largo del ciclo de vida de la instalación de relaves. | H57: 5.1 - B | I57: 5.1 - B Que, para las expansiones de instalaciones existentes, se evalúan los resultados de las revisiones periódicas de refinamientos potenciales de tecnologías de relaves y enfoques de diseño (según Requisito 3.2). | J57: =1/3 -> 0.33333333 | L57: 1
A58: C057 | B58: III | C58: DISEÑO, CONSTRUCCIÓN, OPERACIÓN Y MONITOREO DE LAS INSTALACIONES DE RELAVES | D58: Principio 05 | E58: Desarrollar un diseño sólido que integre la base de conocimientos y minimice el riesgo de falla que pueda afectar a las personas y el medio ambiente durante todas las fases del ciclo de vida de la instalación de relaves, incluso el cierre y post cierre. | F58: Requisito 05.1 | G58: Requisito 05.1 Para las nuevas instalaciones de relaves, incorporar el resultado del análisis de alternativas de criterio múltiple incluyendo el uso de tecnologías de relaves en el diseño de la instalación de relaves. Para expansiones de instalaciones de relaves existentes, investigar el potencial para refinar las tecnologías de relaves y enfoques de diseño con el objetivo de minimizar los riesgos a las personas y medioambiente a lo largo del ciclo de vida de la instalación de relaves. | H58: 5.1 - C | I58: 5.1 - C Donde el diseño difiere del análisis de alternativas, hay una justificación que incorpora el objetivo de minimizar los riesgos a las personas y medioambiente a lo largo del ciclo de vida de la instalación de relaves. | J58: =1/3 -> 0.33333333 | L58: 1
A59: C058 | B59: III | C59: DISEÑO, CONSTRUCCIÓN, OPERACIÓN Y MONITOREO DE LAS INSTALACIONES DE RELAVES | D59: Principio 05 | E59: Desarrollar un diseño sólido que integre la base de conocimientos y minimice el riesgo de falla que pueda afectar a las personas y el medio ambiente durante todas las fases del ciclo de vida de la instalación de relaves, incluso el cierre y post cierre. | F59: Requisito 05.2 | G59: Requisito 05.2 Desarrollar un diseño robusto que considere el contexto técnico, social, medioambiental y económico local, la Clasificación de Consecuencias de una instalación de relaves, condiciones del sitio, gestión de aguas, operaciones de la planta minera, problemas operacionales y de construcción de relaves, y que demuestre la factibilidad de un cierre seguro de la instalación de relaves. El diseño debe ser revisado y actualizado conforme el desempeño y los datos de sitio lleguen a estar disponibles y en respuesta a los cambios materiales a la instalación de relaves o su desempeño. | H59: 5.2 - A | I59: 5.2 - A Que un diseño robusto1,2 considera: - El contexto técnico, social, medioambiental, y económico local de la instalación de relaves. - La Clasificación de Consecuencias, condiciones del sitio, gestión de aguas, operaciones de planta minera, y problemas operacionales y de construcción de relaves. - El diseño muestra la factibilidad del cierre seguro de la instalación de relaves. | J59: =1/2 -> 0.5 | L59: 3
A60: C059 | B60: III | C60: DISEÑO, CONSTRUCCIÓN, OPERACIÓN Y MONITOREO DE LAS INSTALACIONES DE RELAVES | D60: Principio 05 | E60: Desarrollar un diseño sólido que integre la base de conocimientos y minimice el riesgo de falla que pueda afectar a las personas y el medio ambiente durante todas las fases del ciclo de vida de la instalación de relaves, incluso el cierre y post cierre. | F60: Requisito 05.2 | G60: Requisito 05.2 Desarrollar un diseño robusto que considere el contexto técnico, social, medioambiental y económico local, la Clasificación de Consecuencias de una instalación de relaves, condiciones del sitio, gestión de aguas, operaciones de la planta minera, problemas operacionales y de construcción de relaves, y que demuestre la factibilidad de un cierre seguro de la instalación de relaves. El diseño debe ser revisado y actualizado conforme el desempeño y los datos de sitio lleguen a estar disponibles y en respuesta a los cambios materiales a la instalación de relaves o su desempeño. | H60: 5.2 - B | I60: 5.2 - B El diseño es revisado y actualizado a la vez que el desempeño y los datos desempeño de sitio lleguen a estar disponibles a través del ciclo de vida de la instalación de relaves y/o en respuesta a los cambios materiales. | J60: =1/2 -> 0.5 | L60: 1
A61: C060 | B61: III | C61: DISEÑO, CONSTRUCCIÓN, OPERACIÓN Y MONITOREO DE LAS INSTALACIONES DE RELAVES | D61: Principio 05 | E61: Desarrollar un diseño sólido que integre la base de conocimientos y minimice el riesgo de falla que pueda afectar a las personas y el medio ambiente durante todas las fases del ciclo de vida de la instalación de relaves, incluso el cierre y post cierre. | F61: Requisito 05.3 | G61: Requisito 05.3 Desarrollar, implementar y mantener un modelo de balance de aguas y planes de tratamiento de aguas asociados para la instalación de relaves, tomando en cuenta la base del conocimiento, incluyendo el cambio climático, las cuencas hidrológicas e hidrogeológicas aguas arriba y aguas abajo, el sitio de la mina, planificación minera y operaciones en general y la integridad de la instalación de relaves a lo largo de su ciclo de vida. El programa de tratamiento de aguas debe diseñarse para protegerse contra descargas involuntarias. | H61: 5.3 - A | I61: 5.3 - A Un plan de tratamiento de aguas1,3 que tome en consideración la base del conocimiento, el plan minero para el estado actual del ciclo de vida de la instalación de relaves, cuencas hidrológicas e hidrogeológicas aguas arriba y aguas abajo, y el potencial para el cambio climático. | J61: =1/3 -> 0.33333333 | L61: 3
A62: C061 | B62: III | C62: DISEÑO, CONSTRUCCIÓN, OPERACIÓN Y MONITOREO DE LAS INSTALACIONES DE RELAVES | D62: Principio 05 | E62: Desarrollar un diseño sólido que integre la base de conocimientos y minimice el riesgo de falla que pueda afectar a las personas y el medio ambiente durante todas las fases del ciclo de vida de la instalación de relaves, incluso el cierre y post cierre. | F62: Requisito 05.3 | G62: Requisito 05.3 Desarrollar, implementar y mantener un modelo de balance de aguas y planes de tratamiento de aguas asociados para la instalación de relaves, tomando en cuenta la base del conocimiento, incluyendo el cambio climático, las cuencas hidrológicas e hidrogeológicas aguas arriba y aguas abajo, el sitio de la mina, planificación minera y operaciones en general y la integridad de la instalación de relaves a lo largo de su ciclo de vida. El programa de tratamiento de aguas debe diseñarse para protegerse contra descargas involuntarias. | H62: 5.3 - B | I62: 5.3 - B Un modelo de balance de aguas2,3 que considere el plan general de tratamiento de aguas. | J62: =1/3 -> 0.33333333 | L62: 3
A63: C062 | B63: III | C63: DISEÑO, CONSTRUCCIÓN, OPERACIÓN Y MONITOREO DE LAS INSTALACIONES DE RELAVES | D63: Principio 05 | E63: Desarrollar un diseño sólido que integre la base de conocimientos y minimice el riesgo de falla que pueda afectar a las personas y el medio ambiente durante todas las fases del ciclo de vida de la instalación de relaves, incluso el cierre y post cierre. | F63: Requisito 05.3 | G63: Requisito 05.3 Desarrollar, implementar y mantener un modelo de balance de aguas y planes de tratamiento de aguas asociados para la instalación de relaves, tomando en cuenta la base del conocimiento, incluyendo el cambio climático, las cuencas hidrológicas e hidrogeológicas aguas arriba y aguas abajo, el sitio de la mina, planificación minera y operaciones en general y la integridad de la instalación de relaves a lo largo de su ciclo de vida. El programa de tratamiento de aguas debe diseñarse para protegerse contra descargas involuntarias. | H63: 5.3 - C | I63: 5.3 - C El plan de tratamiento de aguas y el balance de aguas abarcan la seguridad de la instalación de relaves y la prevención de descargas involuntarias. | J63: =1/3 -> 0.33333333 | L63: 3
A64: C063 | B64: III | C64: DISEÑO, CONSTRUCCIÓN, OPERACIÓN Y MONITOREO DE LAS INSTALACIONES DE RELAVES | D64: Principio 05 | E64: Desarrollar un diseño sólido que integre la base de conocimientos y minimice el riesgo de falla que pueda afectar a las personas y el medio ambiente durante todas las fases del ciclo de vida de la instalación de relaves, incluso el cierre y post cierre. | F64: Requisito 05.4 | G64: Requisito 05.4 Abarcar todos los modelos de falla potencial de la estructura, su fundación, estribos, reservorio (depósitos de relaves y poza de agua recuperada), borde del embalse y estructuras de apertura para minimizar el riesgo con ALARP. Se deben utilizar las evaluaciones de riegos para informar el diseño. | H64: 5.4 - A | I64: 5.4 - A Modelos de falla potencial a la estructura, su fundación, estribos, reservorio (depósitos de relaves y poza de agua recuperada)), Borde del embalse, y estructuras de apertura son identificadas y categorizadas por las evaluaciones de riesgos, y abarcadas a través de medidas preventivas incorporadas en el diseño y/o a través de controles operativos. | J64: =1/2 -> 0.5 | L64: 3
A65: C064 | B65: III | C65: DISEÑO, CONSTRUCCIÓN, OPERACIÓN Y MONITOREO DE LAS INSTALACIONES DE RELAVES | D65: Principio 05 | E65: Desarrollar un diseño sólido que integre la base de conocimientos y minimice el riesgo de falla que pueda afectar a las personas y el medio ambiente durante todas las fases del ciclo de vida de la instalación de relaves, incluso el cierre y post cierre. | F65: Requisito 05.4 | G65: Requisito 05.4 Abarcar todos los modelos de falla potencial de la estructura, su fundación, estribos, reservorio (depósitos de relaves y poza de agua recuperada), borde del embalse y estructuras de apertura para minimizar el riesgo con ALARP. Se deben utilizar las evaluaciones de riegos para informar el diseño. | H65: 5.4 - B | I65: 5.4 - B Evaluaciones de riesgos son utilizadas para informar el diseño para minimizar el riesgo al ALARP. Evaluaciones de riesgo deben utilizarse para determinar si los modelos/escenarios de falla creíbles son fiables. | J65: =1/2 -> 0.5 | L65: 3
A66: C065 | B66: III | C66: DISEÑO, CONSTRUCCIÓN, OPERACIÓN Y MONITOREO DE LAS INSTALACIONES DE RELAVES | D66: Principio 05 | E66: Desarrollar un diseño sólido que integre la base de conocimientos y minimice el riesgo de falla que pueda afectar a las personas y el medio ambiente durante todas las fases del ciclo de vida de la instalación de relaves, incluso el cierre y post cierre. | F66: Requisito 05.5 | G66: Requisito 05.5 Desarrollar un diseño para cada etapa para la construcción de la instalación de relaves, incluyendo, pero no limitándose al inicio, levantamiento parcial y configuraciones internas, levantamiento final y todas las etapas de cierre. | H66: 5.5 - A | I66: 5.5 - A Se realizan diseños para cada etapa de construcción1 de la instalación de relaves, incluyendo, pero no limitándose al inicio, levantamiento parcial y configuraciones internas, levantamiento final, y todas las etapas de cierre previas a la construcción. El nivel de detalle del diseño debe ser acorde a la fase del ciclo de vida de la instalación de relaves. | J66: 1 | L66: 3
A67: C066 | B67: III | C67: DISEÑO, CONSTRUCCIÓN, OPERACIÓN Y MONITOREO DE LAS INSTALACIONES DE RELAVES | D67: Principio 05 | E67: Desarrollar un diseño sólido que integre la base de conocimientos y minimice el riesgo de falla que pueda afectar a las personas y el medio ambiente durante todas las fases del ciclo de vida de la instalación de relaves, incluso el cierre y post cierre. | F67: Requisito 05.6 | G67: Requisito 05.6 Diseñar la fase de cierre de forma tal que cumpla con todos los Requisitos del Estándar con suficiente detalle para demostrar la factibilidad del escenario de cierre y permitir la implementación de los elementos del diseño durante la construcción y operación según sea adecuado. El diseño debe incluir el cierre progresivo y la recuperación durante operaciones. | H67: 5.6 - A | I67: 5.6 - A El diseño de cierre1 cumple con todos los Requisitos del Estándar con suficiente detalle para demostrar la factibilidad del escenario de cierre. | J67: =1/3 -> 0.33333333 | L67: 3
A68: C067 | B68: III | C68: DISEÑO, CONSTRUCCIÓN, OPERACIÓN Y MONITOREO DE LAS INSTALACIONES DE RELAVES | D68: Principio 05 | E68: Desarrollar un diseño sólido que integre la base de conocimientos y minimice el riesgo de falla que pueda afectar a las personas y el medio ambiente durante todas las fases del ciclo de vida de la instalación de relaves, incluso el cierre y post cierre. | F68: Requisito 05.6 | G68: Requisito 05.6 Diseñar la fase de cierre de forma tal que cumpla con todos los Requisitos del Estándar con suficiente detalle para demostrar la factibilidad del escenario de cierre y permitir la implementación de los elementos del diseño durante la construcción y operación según sea adecuado. El diseño debe incluir el cierre progresivo y la recuperación durante operaciones. | H68: 5.6 - B | I68: 5.6 - B El diseño de cierre permite la implementación del diseño de cierre durante la construcción y operación según sea adecuado. | J68: =1/3 -> 0.33333333 | L68: 3
A69: C068 | B69: III | C69: DISEÑO, CONSTRUCCIÓN, OPERACIÓN Y MONITOREO DE LAS INSTALACIONES DE RELAVES | D69: Principio 05 | E69: Desarrollar un diseño sólido que integre la base de conocimientos y minimice el riesgo de falla que pueda afectar a las personas y el medio ambiente durante todas las fases del ciclo de vida de la instalación de relaves, incluso el cierre y post cierre. | F69: Requisito 05.6 | G69: Requisito 05.6 Diseñar la fase de cierre de forma tal que cumpla con todos los Requisitos del Estándar con suficiente detalle para demostrar la factibilidad del escenario de cierre y permitir la implementación de los elementos del diseño durante la construcción y operación según sea adecuado. El diseño debe incluir el cierre progresivo y la recuperación durante operaciones. | H69: 5.6 - C | I69: 5.6 - C El diseño incluye el cierre progresivo y la recuperación durante operaciones. | J69: =1/3 -> 0.33333333 | L69: 3
A70: C069 | B70: III | C70: DISEÑO, CONSTRUCCIÓN, OPERACIÓN Y MONITOREO DE LAS INSTALACIONES DE RELAVES | D70: Principio 05 | E70: Desarrollar un diseño sólido que integre la base de conocimientos y minimice el riesgo de falla que pueda afectar a las personas y el medio ambiente durante todas las fases del ciclo de vida de la instalación de relaves, incluso el cierre y post cierre. | F70: Requisito 05.7 | G70: Requisito 05.7 Para una nueva instalación de relaves propuesta clasificada como "Alta", "Muy Alta" o "Extrema", el Ejecutivo Responsable deberá confirmar que el diseño cumpla con el ALARP y deberá aprobar pasos razonables adicionales que puedan tomarse aguas abajo, para poder reducir aún más las consecuencias potenciales hacia las personas y medioambiente. El Ejecutivo Responsable deberá explicar y documentar las decisiones con respecto al ALARP y las medidas de reducción de consecuencias adicionales. Para una instalación de relaves existente clasificada como "Alta", "Muy Alta" o "Extrema", el Ejecutivo Responsable, al momento de cada RSR o por lo menos cada cinco años, deberá confirmar que el diseño cumpla con el ALARP y deberá buscar identificar e implementar pasos adicionales razonables que puedan tomarse para poder reducir aún más las potenciales consecuencias hacia las personas y medioambiente. El Ejecutivo Responsable deberá explicar y documentar las decisiones con respecto al ALARP y las medidas de reducción de consecuencias adicionales, consultando con grupos externos de ser adecuado. | H70: 5.7 - A | I70: 5.7 - A Confirmar que el diseño cumpla con ALARP. | J70: =1/6 -> 0.16666667 | L70: 3
A71: C070 | B71: III | C71: DISEÑO, CONSTRUCCIÓN, OPERACIÓN Y MONITOREO DE LAS INSTALACIONES DE RELAVES | D71: Principio 05 | E71: Desarrollar un diseño sólido que integre la base de conocimientos y minimice el riesgo de falla que pueda afectar a las personas y el medio ambiente durante todas las fases del ciclo de vida de la instalación de relaves, incluso el cierre y post cierre. | F71: Requisito 05.7 | G71: Requisito 05.7 Para una nueva instalación de relaves propuesta clasificada como "Alta", "Muy Alta" o "Extrema", el Ejecutivo Responsable deberá confirmar que el diseño cumpla con el ALARP y deberá aprobar pasos razonables adicionales que puedan tomarse aguas abajo, para poder reducir aún más las consecuencias potenciales hacia las personas y medioambiente. El Ejecutivo Responsable deberá explicar y documentar las decisiones con respecto al ALARP y las medidas de reducción de consecuencias adicionales. Para una instalación de relaves existente clasificada como "Alta", "Muy Alta" o "Extrema", el Ejecutivo Responsable, al momento de cada RSR o por lo menos cada cinco años, deberá confirmar que el diseño cumpla con el ALARP y deberá buscar identificar e implementar pasos adicionales razonables que puedan tomarse para poder reducir aún más las potenciales consecuencias hacia las personas y medioambiente. El Ejecutivo Responsable deberá explicar y documentar las decisiones con respecto al ALARP y las medidas de reducción de consecuencias adicionales, consultando con grupos externos de ser adecuado. | H71: 5.7 - B | I71: 5.7 - B Aprobar pasos adicionales razonables que se puedan tomar aguas abajo, para reducir aún más las consecuencias potenciales hacia las personas y medioambiente. | J71: =1/6 -> 0.16666667 | L71: 3
A72: C071 | B72: III | C72: DISEÑO, CONSTRUCCIÓN, OPERACIÓN Y MONITOREO DE LAS INSTALACIONES DE RELAVES | D72: Principio 05 | E72: Desarrollar un diseño sólido que integre la base de conocimientos y minimice el riesgo de falla que pueda afectar a las personas y el medio ambiente durante todas las fases del ciclo de vida de la instalación de relaves, incluso el cierre y post cierre. | F72: Requisito 05.7 | G72: Requisito 05.7 Para una nueva instalación de relaves propuesta clasificada como "Alta", "Muy Alta" o "Extrema", el Ejecutivo Responsable deberá confirmar que el diseño cumpla con el ALARP y deberá aprobar pasos razonables adicionales que puedan tomarse aguas abajo, para poder reducir aún más las consecuencias potenciales hacia las personas y medioambiente. El Ejecutivo Responsable deberá explicar y documentar las decisiones con respecto al ALARP y las medidas de reducción de consecuencias adicionales. Para una instalación de relaves existente clasificada como "Alta", "Muy Alta" o "Extrema", el Ejecutivo Responsable, al momento de cada RSR o por lo menos cada cinco años, deberá confirmar que el diseño cumpla con el ALARP y deberá buscar identificar e implementar pasos adicionales razonables que puedan tomarse para poder reducir aún más las potenciales consecuencias hacia las personas y medioambiente. El Ejecutivo Responsable deberá explicar y documentar las decisiones con respecto al ALARP y las medidas de reducción de consecuencias adicionales, consultando con grupos externos de ser adecuado. | H72: 5.7 - C | I72: 5.7 - C Explicar y documentar las decisiones con respecto al ALARP y medidas de reducción de consecuencias adicionales. Para una instalación de relaves existente, el Ejecutivo Responsable, al momento de cada DSR o al menos cada cinco años, deberá: | J72: =1/6 -> 0.16666667 | L72: 3
A73: C072 | B73: III | C73: DISEÑO, CONSTRUCCIÓN, OPERACIÓN Y MONITOREO DE LAS INSTALACIONES DE RELAVES | D73: Principio 05 | E73: Desarrollar un diseño sólido que integre la base de conocimientos y minimice el riesgo de falla que pueda afectar a las personas y el medio ambiente durante todas las fases del ciclo de vida de la instalación de relaves, incluso el cierre y post cierre. | F73: Requisito 05.7 | G73: Requisito 05.7 Para una nueva instalación de relaves propuesta clasificada como "Alta", "Muy Alta" o "Extrema", el Ejecutivo Responsable deberá confirmar que el diseño cumpla con el ALARP y deberá aprobar pasos razonables adicionales que puedan tomarse aguas abajo, para poder reducir aún más las consecuencias potenciales hacia las personas y medioambiente. El Ejecutivo Responsable deberá explicar y documentar las decisiones con respecto al ALARP y las medidas de reducción de consecuencias adicionales. Para una instalación de relaves existente clasificada como "Alta", "Muy Alta" o "Extrema", el Ejecutivo Responsable, al momento de cada RSR o por lo menos cada cinco años, deberá confirmar que el diseño cumpla con el ALARP y deberá buscar identificar e implementar pasos adicionales razonables que puedan tomarse para poder reducir aún más las potenciales consecuencias hacia las personas y medioambiente. El Ejecutivo Responsable deberá explicar y documentar las decisiones con respecto al ALARP y las medidas de reducción de consecuencias adicionales, consultando con grupos externos de ser adecuado. | H73: 5.7 - D | I73: 5.7 - D Confirmar que el diseño cumpla con ALARP. | J73: =1/6 -> 0.16666667 | L73: 3
A74: C073 | B74: III | C74: DISEÑO, CONSTRUCCIÓN, OPERACIÓN Y MONITOREO DE LAS INSTALACIONES DE RELAVES | D74: Principio 05 | E74: Desarrollar un diseño sólido que integre la base de conocimientos y minimice el riesgo de falla que pueda afectar a las personas y el medio ambiente durante todas las fases del ciclo de vida de la instalación de relaves, incluso el cierre y post cierre. | F74: Requisito 05.7 | G74: Requisito 05.7 Para una nueva instalación de relaves propuesta clasificada como "Alta", "Muy Alta" o "Extrema", el Ejecutivo Responsable deberá confirmar que el diseño cumpla con el ALARP y deberá aprobar pasos razonables adicionales que puedan tomarse aguas abajo, para poder reducir aún más las consecuencias potenciales hacia las personas y medioambiente. El Ejecutivo Responsable deberá explicar y documentar las decisiones con respecto al ALARP y las medidas de reducción de consecuencias adicionales. Para una instalación de relaves existente clasificada como "Alta", "Muy Alta" o "Extrema", el Ejecutivo Responsable, al momento de cada RSR o por lo menos cada cinco años, deberá confirmar que el diseño cumpla con el ALARP y deberá buscar identificar e implementar pasos adicionales razonables que puedan tomarse para poder reducir aún más las potenciales consecuencias hacia las personas y medioambiente. El Ejecutivo Responsable deberá explicar y documentar las decisiones con respecto al ALARP y las medidas de reducción de consecuencias adicionales, consultando con grupos externos de ser adecuado. | H74: 5.7 - E | I74: 5.7 - E Buscar la identificación e implementación de pasos razonables adicionales que se puedan tomar para reducir aún más las consecuencias potenciales hacia las personas y medioambiente. | J74: =1/6 -> 0.16666667 | L74: 3
A75: C074 | B75: III | C75: DISEÑO, CONSTRUCCIÓN, OPERACIÓN Y MONITOREO DE LAS INSTALACIONES DE RELAVES | D75: Principio 05 | E75: Desarrollar un diseño sólido que integre la base de conocimientos y minimice el riesgo de falla que pueda afectar a las personas y el medio ambiente durante todas las fases del ciclo de vida de la instalación de relaves, incluso el cierre y post cierre. | F75: Requisito 05.7 | G75: Requisito 05.7 Para una nueva instalación de relaves propuesta clasificada como "Alta", "Muy Alta" o "Extrema", el Ejecutivo Responsable deberá confirmar que el diseño cumpla con el ALARP y deberá aprobar pasos razonables adicionales que puedan tomarse aguas abajo, para poder reducir aún más las consecuencias potenciales hacia las personas y medioambiente. El Ejecutivo Responsable deberá explicar y documentar las decisiones con respecto al ALARP y las medidas de reducción de consecuencias adicionales. Para una instalación de relaves existente clasificada como "Alta", "Muy Alta" o "Extrema", el Ejecutivo Responsable, al momento de cada RSR o por lo menos cada cinco años, deberá confirmar que el diseño cumpla con el ALARP y deberá buscar identificar e implementar pasos adicionales razonables que puedan tomarse para poder reducir aún más las potenciales consecuencias hacia las personas y medioambiente. El Ejecutivo Responsable deberá explicar y documentar las decisiones con respecto al ALARP y las medidas de reducción de consecuencias adicionales, consultando con grupos externos de ser adecuado. | H75: 5.7 - F | I75: 5.7 - F Explicar y documentar las decisiones con respecto al ALARP y medidas de reducción de consecuencias adicionales, consultando con grupos externos de ser adecuado. | J75: =1/6 -> 0.16666667 | L75: 3
A76: C075 | B76: III | C76: DISEÑO, CONSTRUCCIÓN, OPERACIÓN Y MONITOREO DE LAS INSTALACIONES DE RELAVES | D76: Principio 05 | E76: Desarrollar un diseño sólido que integre la base de conocimientos y minimice el riesgo de falla que pueda afectar a las personas y el medio ambiente durante todas las fases del ciclo de vida de la instalación de relaves, incluso el cierre y post cierre. | F76: Requisito 05.8 | G76: Requisito 05.8 Al haberse agotado las medidas para reducir las consecuencias de un modelo de falla creíble de una instalación de relaves conforme al análisis de brechas, y al no poderse evitar un reasentamiento preventivo, el Operador deberá demostrar cumplimiento con los estándares internacionales respecto al reasentamiento involuntario. | H76: 5.8 - A | I76: 5.8 - A Los Operadores que poseen una instalación con un modelo de falla creíble, conforme al análisis de brecha, han agotado las medidas para reducir las consecuencias y no pueden evitar un reasentamiento preventivo. | J76: =1/2 -> 0.5 | L76: 1
A77: C076 | B77: III | C77: DISEÑO, CONSTRUCCIÓN, OPERACIÓN Y MONITOREO DE LAS INSTALACIONES DE RELAVES | D77: Principio 05 | E77: Desarrollar un diseño sólido que integre la base de conocimientos y minimice el riesgo de falla que pueda afectar a las personas y el medio ambiente durante todas las fases del ciclo de vida de la instalación de relaves, incluso el cierre y post cierre. | F77: Requisito 05.8 | G77: Requisito 05.8 Al haberse agotado las medidas para reducir las consecuencias de un modelo de falla creíble de una instalación de relaves conforme al análisis de brechas, y al no poderse evitar un reasentamiento preventivo, el Operador deberá demostrar cumplimiento con los estándares internacionales respecto al reasentamiento involuntario. | H77: 5.8 - B | I77: 5.8 - B El Operador ha cumplido con los estándares internacionales para el reasentamiento involuntario. | J77: =1/2 -> 0.5 | L77: 1
A78: C077 | B78: III | C78: DISEÑO, CONSTRUCCIÓN, OPERACIÓN Y MONITOREO DE LAS INSTALACIONES DE RELAVES | D78: Principio 06 | E78: Planificar, construir y operar la instalación de relaves para gestionar el riesgo en todas las fases de su ciclo de vida, incluidas la fase de cierre y el post cierre. | F78: Requisito 06.1 | G78: Requisito 06.1 Construir, operar, monitorear y crear la instalación de relaves de acuerdo a la intención del diseño en todas las fases del ciclo de vida de la instalación de relaves, utilizando personal calificado y metodología, equipo y procedimientos adecuados, métodos de adquisición de datos, el Sistema de Tratamiento de Relaves (STR) y el Sistema de Gestión Medioambiental y Social (SGMS) general para la mina e infraestructura asociada. | H78: 6.1 - A | I78: 6.1 - A La intención del diseño, establecida en el DBR, es comprendida e implementada para la construcción, operación y cierre de cada fase del ciclo de vida de la instalación de relaves. | J78: =1/4 -> 0.25 | L78: 3
A79: C078 | B79: III | C79: DISEÑO, CONSTRUCCIÓN, OPERACIÓN Y MONITOREO DE LAS INSTALACIONES DE RELAVES | D79: Principio 06 | E79: Planificar, construir y operar la instalación de relaves para gestionar el riesgo en todas las fases de su ciclo de vida, incluidas la fase de cierre y el post cierre. | F79: Requisito 06.1 | G79: Requisito 06.1 Construir, operar, monitorear y crear la instalación de relaves de acuerdo a la intención del diseño en todas las fases del ciclo de vida de la instalación de relaves, utilizando personal calificado y metodología, equipo y procedimientos adecuados, métodos de adquisición de datos, el Sistema de Tratamiento de Relaves (STR) y el Sistema de Gestión Medioambiental y Social (SGMS) general para la mina e infraestructura asociada. | H79: 6.1 - B | I79: 6.1 - B El personal de construcción y operación asignado a las tareas relacionadas a los relaves están calificados en base a las cualidades definidas en el Sistema de Tratamiento de Relaves (TMS). | J79: =1/4 -> 0.25 | L79: 3
A80: C079 | B80: III | C80: DISEÑO, CONSTRUCCIÓN, OPERACIÓN Y MONITOREO DE LAS INSTALACIONES DE RELAVES | D80: Principio 06 | E80: Planificar, construir y operar la instalación de relaves para gestionar el riesgo en todas las fases de su ciclo de vida, incluidas la fase de cierre y el post cierre. | F80: Requisito 06.1 | G80: Requisito 06.1 Construir, operar, monitorear y crear la instalación de relaves de acuerdo a la intención del diseño en todas las fases del ciclo de vida de la instalación de relaves, utilizando personal calificado y metodología, equipo y procedimientos adecuados, métodos de adquisición de datos, el Sistema de Tratamiento de Relaves (STR) y el Sistema de Gestión Medioambiental y Social (SGMS) general para la mina e infraestructura asociada. | H80: 6.1 - C | I80: 6.1 - C A lo largo de las etapas del ciclo de vida de la instalación de relaves se utiliza la metodología, equipo y procedimientos1 adecuados, métodos de adquisición de datos son utilizados e incorporados dentro del TMS y en el Sistema de Gestión Medioambiental y Social (ESMS) para la mina e infraestructura asociada. | J80: =1/4 -> 0.25 | L80: 3
A81: C080 | B81: III | C81: DISEÑO, CONSTRUCCIÓN, OPERACIÓN Y MONITOREO DE LAS INSTALACIONES DE RELAVES | D81: Principio 06 | E81: Planificar, construir y operar la instalación de relaves para gestionar el riesgo en todas las fases de su ciclo de vida, incluidas la fase de cierre y el post cierre. | F81: Requisito 06.1 | G81: Requisito 06.1 Construir, operar, monitorear y crear la instalación de relaves de acuerdo a la intención del diseño en todas las fases del ciclo de vida de la instalación de relaves, utilizando personal calificado y metodología, equipo y procedimientos adecuados, métodos de adquisición de datos, el Sistema de Tratamiento de Relaves (STR) y el Sistema de Gestión Medioambiental y Social (SGMS) general para la mina e infraestructura asociada. | H81: 6.1 - D | I81: 6.1 - D El TMS y el ESMS son implementados durante la construcción, operación y cierre. | J81: =1/4 -> 0.25 | L81: 3
A82: C081 | B82: III | C82: DISEÑO, CONSTRUCCIÓN, OPERACIÓN Y MONITOREO DE LAS INSTALACIONES DE RELAVES | D82: Principio 06 | E82: Planificar, construir y operar la instalación de relaves para gestionar el riesgo en todas las fases de su ciclo de vida, incluidas la fase de cierre y el post cierre. | F82: Requisito 06.2 | G82: Requisito 06.2 Gestionar la calidad y adecuación de los procesos de construcción y operación al implementar Control de Calidad, Aseguramiento de Calidad y Construcción frente a Verificación de Intención del Diseño (CDIV). El Operador utilizará el CDIV para asegurar que la intención del diseño se implemente y se siga cumpliendo si las condiciones del sitio difieren de las suposiciones del diseño. | H82: 6.2 - A | I82: 6.2 - A Programas de Control de Calidad1 (QC) y Aseguramiento de Calidad2 (QA) sean establecidos para supervisar la calidad y adecuación de los procesos de construcción2 y operación. | J82: 1 | L82: 2
A83: C082 | B83: III | C83: DISEÑO, CONSTRUCCIÓN, OPERACIÓN Y MONITOREO DE LAS INSTALACIONES DE RELAVES | D83: Principio 06 | E83: Planificar, construir y operar la instalación de relaves para gestionar el riesgo en todas las fases de su ciclo de vida, incluidas la fase de cierre y el post cierre. | F83: Requisito 06.2 | G83: Requisito 06.2 Gestionar la calidad y adecuación de los procesos de construcción y operación al implementar Control de Calidad, Aseguramiento de Calidad y Construcción frente a Verificación de Intención del Diseño (CDIV). El Operador utilizará el CDIV para asegurar que la intención del diseño se implemente y se siga cumpliendo si las condiciones del sitio difieren de las suposiciones del diseño. | H83: 6.2 - B | I83: 6.2 - B Se cumple con un programa CDIV que confirme que se cumpla con la intención de diseño si las condiciones varían a las hipótesis de diseño. | J83: 1 | L83: 3
A84: C083 | B84: III | C84: DISEÑO, CONSTRUCCIÓN, OPERACIÓN Y MONITOREO DE LAS INSTALACIONES DE RELAVES | D84: Principio 06 | E84: Planificar, construir y operar la instalación de relaves para gestionar el riesgo en todas las fases de su ciclo de vida, incluidas la fase de cierre y el post cierre. | F84: Requisito 06.3 | G84: Requisito 06.3 Preparar un Reporte de Registros de Construcción (informe “según obra”) detallado cuando haya un cambio material en la instalación de relaves, su infraestructura o sistema de monitoreo. El EOR y el Ingeniero Responsable de la Instalación de Relaves (RTFE) deberán firmar este reporte. | H84: 6.3 - A | I84: 6.3 - A Los Reportes de Registros de Construcción (CRR) 1,2,3 están actualizados y listos para cuando haya un cambio material en la instalación de relaves, su infraestructura, o sistema de monitoreo. | J84: =1/2 -> 0.5 | L84: 2
A85: C084 | B85: III | C85: DISEÑO, CONSTRUCCIÓN, OPERACIÓN Y MONITOREO DE LAS INSTALACIONES DE RELAVES | D85: Principio 06 | E85: Planificar, construir y operar la instalación de relaves para gestionar el riesgo en todas las fases de su ciclo de vida, incluidas la fase de cierre y el post cierre. | F85: Requisito 06.3 | G85: Requisito 06.3 Preparar un Reporte de Registros de Construcción (informe “según obra”) detallado cuando haya un cambio material en la instalación de relaves, su infraestructura o sistema de monitoreo. El EOR y el Ingeniero Responsable de la Instalación de Relaves (RTFE) deberán firmar este reporte. | H85: 6.3 - B | I85: 6.3 - B Los CRRs han sido firmados por el RTFE y el EOR. | J85: =1/2 -> 0.5 | L85: 3
A86: C085 | B86: III | C86: DISEÑO, CONSTRUCCIÓN, OPERACIÓN Y MONITOREO DE LAS INSTALACIONES DE RELAVES | D86: Principio 06 | E86: Planificar, construir y operar la instalación de relaves para gestionar el riesgo en todas las fases de su ciclo de vida, incluidas la fase de cierre y el post cierre. | F86: Requisito 06.4 | G86: Requisito 06.4 Desarrollar, implementar, revisar anualmente y actualizar cuando es debido un Manual de Operación, Mantenimiento y Supervisión (OMS) que respalde la gestión efectiva de riesgos como parte de la TMS. El Manual de OMS debe seguir las mejores prácticas, proporcionar los contextos claros y controles fundamentales para las operaciones seguras y ser revisado para su efectividad. El RTFE debe proporcionar acceso al Manual de OMS y capacitación al personal en todos los niveles involucrados en el TMS con el respaldo del EOR. | H86: 6.4 - A | I86: 6.4 - A Se implementa un Manual de Operación, Mantenimiento y Supervisión (OMS), cubre todas las instalaciones de relaves e incluye los requisitos para las actividades del manual de OMS necesarias para la gestión eficaz de riesgos basadas en las mejores prácticas. | J86: =1/5 -> 0.2 | L86: 3
A87: C086 | B87: III | C87: DISEÑO, CONSTRUCCIÓN, OPERACIÓN Y MONITOREO DE LAS INSTALACIONES DE RELAVES | D87: Principio 06 | E87: Planificar, construir y operar la instalación de relaves para gestionar el riesgo en todas las fases de su ciclo de vida, incluidas la fase de cierre y el post cierre. | F87: Requisito 06.4 | G87: Requisito 06.4 Desarrollar, implementar, revisar anualmente y actualizar cuando es debido un Manual de Operación, Mantenimiento y Supervisión (OMS) que respalde la gestión efectiva de riesgos como parte de la TMS. El Manual de OMS debe seguir las mejores prácticas, proporcionar los contextos claros y controles fundamentales para las operaciones seguras y ser revisado para su efectividad. El RTFE debe proporcionar acceso al Manual de OMS y capacitación al personal en todos los niveles involucrados en el TMS con el respaldo del EOR. | H87: 6.4 - B | I87: 6.4 - B El manual de OMS se revisa anualmente o más frecuentemente si hay alguna actualización debido a un cambio material según lo defina el Operador. | J87: =1/5 -> 0.2 | L87: 3
A88: C087 | B88: III | C88: DISEÑO, CONSTRUCCIÓN, OPERACIÓN Y MONITOREO DE LAS INSTALACIONES DE RELAVES | D88: Principio 06 | E88: Planificar, construir y operar la instalación de relaves para gestionar el riesgo en todas las fases de su ciclo de vida, incluidas la fase de cierre y el post cierre. | F88: Requisito 06.4 | G88: Requisito 06.4 Desarrollar, implementar, revisar anualmente y actualizar cuando es debido un Manual de Operación, Mantenimiento y Supervisión (OMS) que respalde la gestión efectiva de riesgos como parte de la TMS. El Manual de OMS debe seguir las mejores prácticas, proporcionar los contextos claros y controles fundamentales para las operaciones seguras y ser revisado para su efectividad. El RTFE debe proporcionar acceso al Manual de OMS y capacitación al personal en todos los niveles involucrados en el TMS con el respaldo del EOR. | H88: 6.4 - C | I88: 6.4 - C El manual de OMS proporciona un contexto claro e incluye la inspección, mantenimiento y monitoreo de los requisitos identificados incluyendo los controles fundamentales para la operación segura y es revisado para su eficacia. | J88: =1/5 -> 0.2 | L88: 3
A89: C088 | B89: III | C89: DISEÑO, CONSTRUCCIÓN, OPERACIÓN Y MONITOREO DE LAS INSTALACIONES DE RELAVES | D89: Principio 06 | E89: Planificar, construir y operar la instalación de relaves para gestionar el riesgo en todas las fases de su ciclo de vida, incluidas la fase de cierre y el post cierre. | F89: Requisito 06.4 | G89: Requisito 06.4 Desarrollar, implementar, revisar anualmente y actualizar cuando es debido un Manual de Operación, Mantenimiento y Supervisión (OMS) que respalde la gestión efectiva de riesgos como parte de la TMS. El Manual de OMS debe seguir las mejores prácticas, proporcionar los contextos claros y controles fundamentales para las operaciones seguras y ser revisado para su efectividad. El RTFE debe proporcionar acceso al Manual de OMS y capacitación al personal en todos los niveles involucrados en el TMS con el respaldo del EOR. | H89: 6.4 - D | I89: 6.4 - D El RTFE asegura que el personal involucrado en el TMS tiene acceso al Manual de OMS, | J89: =1/5 -> 0.2 | L89: 3
A90: C089 | B90: III | C90: DISEÑO, CONSTRUCCIÓN, OPERACIÓN Y MONITOREO DE LAS INSTALACIONES DE RELAVES | D90: Principio 06 | E90: Planificar, construir y operar la instalación de relaves para gestionar el riesgo en todas las fases de su ciclo de vida, incluidas la fase de cierre y el post cierre. | F90: Requisito 06.4 | G90: Requisito 06.4 Desarrollar, implementar, revisar anualmente y actualizar cuando es debido un Manual de Operación, Mantenimiento y Supervisión (OMS) que respalde la gestión efectiva de riesgos como parte de la TMS. El Manual de OMS debe seguir las mejores prácticas, proporcionar los contextos claros y controles fundamentales para las operaciones seguras y ser revisado para su efectividad. El RTFE debe proporcionar acceso al Manual de OMS y capacitación al personal en todos los niveles involucrados en el TMS con el respaldo del EOR. | H90: 6.4 - E | I90: 6.4 - E El RTFE debe proporcionar acceso a la capacitación del personal en todos los niveles involucrados en el TMS | J90: =1/5 -> 0.2 | L90: 1
A91: C090 | B91: III | C91: DISEÑO, CONSTRUCCIÓN, OPERACIÓN Y MONITOREO DE LAS INSTALACIONES DE RELAVES | D91: Principio 06 | E91: Planificar, construir y operar la instalación de relaves para gestionar el riesgo en todas las fases de su ciclo de vida, incluidas la fase de cierre y el post cierre. | F91: Requisito 06.5 | G91: Requisito 06.5 Implementar un sistema de gestión de cambio formal que desencadene en la evaluación, revisión, aprobación y documentación de cambios al diseño, construcción, operación o monitoreo durante el ciclo de vida de la instalación de relaves. El sistema de gestión de cambio también deberá incluir el requisito para que el EOR prepare un Reporte de Responsabilidad por Desviación (DAR por sus siglas en inglés) que proporcione una evaluación del impacto acumulativo de los cambios a nivel de riesgo de la instalación construida. El DAR deberá proporcionar recomendaciones para la gestión de riesgos, de ser necesario, y de cualquier actualización resultante al diseño, DBR, OMS, y al programa de monitoreo. El DAR deberá ser aprobado por el Ejecutivo Responsable. | H91: 6.5 - A | I91: 6.5 - A Se establece un Sistema de Gestión de Cambios. | J91: =1/6 -> 0.16666667 | L91: 1
A92: C091 | B92: III | C92: DISEÑO, CONSTRUCCIÓN, OPERACIÓN Y MONITOREO DE LAS INSTALACIONES DE RELAVES | D92: Principio 06 | E92: Planificar, construir y operar la instalación de relaves para gestionar el riesgo en todas las fases de su ciclo de vida, incluidas la fase de cierre y el post cierre. | F92: Requisito 06.5 | G92: Requisito 06.5 Implementar un sistema de gestión de cambio formal que desencadene en la evaluación, revisión, aprobación y documentación de cambios al diseño, construcción, operación o monitoreo durante el ciclo de vida de la instalación de relaves. El sistema de gestión de cambio también deberá incluir el requisito para que el EOR prepare un Reporte de Responsabilidad por Desviación (DAR por sus siglas en inglés) que proporcione una evaluación del impacto acumulativo de los cambios a nivel de riesgo de la instalación construida. El DAR deberá proporcionar recomendaciones para la gestión de riesgos, de ser necesario, y de cualquier actualización resultante al diseño, DBR, OMS, y al programa de monitoreo. El DAR deberá ser aprobado por el Ejecutivo Responsable. | H92: 6.5 - B | I92: 6.5 - B El Sistema de Gestión de Cambios incluye procesos para la identificación de cambios y procesos para la evaluación, revisión, aprobación y documentación de cambios a lo largo del ciclo de vida de la instalación. | J92: =1/6 -> 0.16666667 | L92: 1
A93: C092 | B93: III | C93: DISEÑO, CONSTRUCCIÓN, OPERACIÓN Y MONITOREO DE LAS INSTALACIONES DE RELAVES | D93: Principio 06 | E93: Planificar, construir y operar la instalación de relaves para gestionar el riesgo en todas las fases de su ciclo de vida, incluidas la fase de cierre y el post cierre. | F93: Requisito 06.5 | G93: Requisito 06.5 Implementar un sistema de gestión de cambio formal que desencadene en la evaluación, revisión, aprobación y documentación de cambios al diseño, construcción, operación o monitoreo durante el ciclo de vida de la instalación de relaves. El sistema de gestión de cambio también deberá incluir el requisito para que el EOR prepare un Reporte de Responsabilidad por Desviación (DAR por sus siglas en inglés) que proporcione una evaluación del impacto acumulativo de los cambios a nivel de riesgo de la instalación construida. El DAR deberá proporcionar recomendaciones para la gestión de riesgos, de ser necesario, y de cualquier actualización resultante al diseño, DBR, OMS, y al programa de monitoreo. El DAR deberá ser aprobado por el Ejecutivo Responsable. | H93: 6.5 - C | I93: 6.5 - C El Sistema de Gestión de Cambios abarca y documenta cambios materiales al diseño, construcción, operaciones o monitoreo. | J93: =1/6 -> 0.16666667 | L93: 1
A94: C093 | B94: III | C94: DISEÑO, CONSTRUCCIÓN, OPERACIÓN Y MONITOREO DE LAS INSTALACIONES DE RELAVES | D94: Principio 06 | E94: Planificar, construir y operar la instalación de relaves para gestionar el riesgo en todas las fases de su ciclo de vida, incluidas la fase de cierre y el post cierre. | F94: Requisito 06.5 | G94: Requisito 06.5 Implementar un sistema de gestión de cambio formal que desencadene en la evaluación, revisión, aprobación y documentación de cambios al diseño, construcción, operación o monitoreo durante el ciclo de vida de la instalación de relaves. El sistema de gestión de cambio también deberá incluir el requisito para que el EOR prepare un Reporte de Responsabilidad por Desviación (DAR por sus siglas en inglés) que proporcione una evaluación del impacto acumulativo de los cambios a nivel de riesgo de la instalación construida. El DAR deberá proporcionar recomendaciones para la gestión de riesgos, de ser necesario, y de cualquier actualización resultante al diseño, DBR, OMS, y al programa de monitoreo. El DAR deberá ser aprobado por el Ejecutivo Responsable. | H94: 6.5 - D | I94: 6.5 - D Un DAR es preparado y actualizado periódicamente por el EOR, el cual abarcar el impacto acumulativo de los cambios materiales a la instalación construida. | J94: =1/6 -> 0.16666667 | L94: 3
A95: C094 | B95: III | C95: DISEÑO, CONSTRUCCIÓN, OPERACIÓN Y MONITOREO DE LAS INSTALACIONES DE RELAVES | D95: Principio 06 | E95: Planificar, construir y operar la instalación de relaves para gestionar el riesgo en todas las fases de su ciclo de vida, incluidas la fase de cierre y el post cierre. | F95: Requisito 06.5 | G95: Requisito 06.5 Implementar un sistema de gestión de cambio formal que desencadene en la evaluación, revisión, aprobación y documentación de cambios al diseño, construcción, operación o monitoreo durante el ciclo de vida de la instalación de relaves. El sistema de gestión de cambio también deberá incluir el requisito para que el EOR prepare un Reporte de Responsabilidad por Desviación (DAR por sus siglas en inglés) que proporcione una evaluación del impacto acumulativo de los cambios a nivel de riesgo de la instalación construida. El DAR deberá proporcionar recomendaciones para la gestión de riesgos, de ser necesario, y de cualquier actualización resultante al diseño, DBR, OMS, y al programa de monitoreo. El DAR deberá ser aprobado por el Ejecutivo Responsable. | H95: 6.5 - E | I95: 6.5 - E Se han implementado recomendaciones del DAR a través de actualizaciones para la construcción, diseño, DBR, Manual de OMS y al programa de monitoreo. | J95: =1/6 -> 0.16666667 | L95: 3
A96: C095 | B96: III | C96: DISEÑO, CONSTRUCCIÓN, OPERACIÓN Y MONITOREO DE LAS INSTALACIONES DE RELAVES | D96: Principio 06 | E96: Planificar, construir y operar la instalación de relaves para gestionar el riesgo en todas las fases de su ciclo de vida, incluidas la fase de cierre y el post cierre. | F96: Requisito 06.5 | G96: Requisito 06.5 Implementar un sistema de gestión de cambio formal que desencadene en la evaluación, revisión, aprobación y documentación de cambios al diseño, construcción, operación o monitoreo durante el ciclo de vida de la instalación de relaves. El sistema de gestión de cambio también deberá incluir el requisito para que el EOR prepare un Reporte de Responsabilidad por Desviación (DAR por sus siglas en inglés) que proporcione una evaluación del impacto acumulativo de los cambios a nivel de riesgo de la instalación construida. El DAR deberá proporcionar recomendaciones para la gestión de riesgos, de ser necesario, y de cualquier actualización resultante al diseño, DBR, OMS, y al programa de monitoreo. El DAR deberá ser aprobado por el Ejecutivo Responsable. | H96: 6.5 - F | I96: 6.5 - F El Ejecutivo Responsable ha aprobado el DAR. | J96: =1/6 -> 0.16666667 | L96: 3
A97: C096 | B97: III | C97: DISEÑO, CONSTRUCCIÓN, OPERACIÓN Y MONITOREO DE LAS INSTALACIONES DE RELAVES | D97: Principio 06 | E97: Planificar, construir y operar la instalación de relaves para gestionar el riesgo en todas las fases de su ciclo de vida, incluidas la fase de cierre y el post cierre. | F97: Requisito 06.6 | G97: Requisito 06.6 Incluir tecnologías y enfoques nuevos y emergentes y utilizar el conocimiento en evolución para la mejora del diseño, construcción y operación de la instalación de relaves. | H97: 6.6 - A | I97: 6.6 - A Revisiones de nuevas tecnologías y enfoques para el tratamiento de relaves se llevan a cabo considerando el ciclo de vida de la instalación de relaves. | J97: =1/2 -> 0.5 | L97: 1
A98: C097 | B98: III | C98: DISEÑO, CONSTRUCCIÓN, OPERACIÓN Y MONITOREO DE LAS INSTALACIONES DE RELAVES | D98: Principio 06 | E98: Planificar, construir y operar la instalación de relaves para gestionar el riesgo en todas las fases de su ciclo de vida, incluidas la fase de cierre y el post cierre. | F98: Requisito 06.6 | G98: Requisito 06.6 Incluir tecnologías y enfoques nuevos y emergentes y utilizar el conocimiento en evolución para la mejora del diseño, construcción y operación de la instalación de relaves. | H98: 6.6 - B | I98: 6.6 - B Los resultados materiales de las revisiones han sido incorporados en las mejoras del diseño, construcción y operación de la instalación. | J98: =1/2 -> 0.5 | L98: 1
A99: C098 | B99: III | C99: DISEÑO, CONSTRUCCIÓN, OPERACIÓN Y MONITOREO DE LAS INSTALACIONES DE RELAVES | D99: Principio 07 | E99: Diseñar, establecer y operar sistemas de monitoreo para la gestión de riesgos en todas las fases del ciclo de vida de la instalación de relaves, incluso su cierre. | F99: Requisito 07.1 | G99: Requisito 07.1 Diseñar, implementar y operar un programa de monitoreo de desempeño completo e integrado para la instalación de relaves y sus estructuras correspondientes como parte del TMS y para aquellos aspectos del ESMS relacionados a la instalación de relaves en cumplimiento a los principios de Gestión Adaptativa. | H99: 7.1 - A | I99: 7.1 - A Se ha desarrollado un programa de monitoreo de desempeño integrado completo para la instalación de relaves y sus estructuras correspondientes y forma parte del TMS, e incluye actividades para la inspección, revisión, y requisitos de monitoreo en regla con la instalación del manual de OMS. | J99: =1/3 -> 0.33333333 | L99: 2
A100: C099 | B100: III | C100: DISEÑO, CONSTRUCCIÓN, OPERACIÓN Y MONITOREO DE LAS INSTALACIONES DE RELAVES | D100: Principio 07 | E100: Diseñar, establecer y operar sistemas de monitoreo para la gestión de riesgos en todas las fases del ciclo de vida de la instalación de relaves, incluso su cierre. | F100: Requisito 07.1 | G100: Requisito 07.1 Diseñar, implementar y operar un programa de monitoreo de desempeño completo e integrado para la instalación de relaves y sus estructuras correspondientes como parte del TMS y para aquellos aspectos del ESMS relacionados a la instalación de relaves en cumplimiento a los principios de Gestión Adaptativa. | H100: 7.1 - B | I100: 7.1 - B Los aspectos del ESMS que están vinculados al monitoreo del desempeño de la instalación de relaves son identificados e incluidos en el programa de monitoreo de desempeño. | J100: =1/3 -> 0.33333333 | L100: 2
...

Sheet Documento_x_Criterio
A1: ID_Documento | B1: Documento | C1: ID_Criterio | D1: Principio | E1: Criterio | F1: % Contribución | G1: Ponderación Criterio | H1: % Avance Documento | I1: Avance Ponderado Efectivo | J1: Rango de páginas | K1: Fragmentos
A2: D001 | B2: =IFERROR(INDEX(Documentos!$B$2:$B$59,MATCH($A2,Documentos!$A$2:$A$59,0)),"") -> Compromiso de DDHH | C2: C001 | D2: =IFERROR(INDEX('Criterios GISTM'!$D$2:$D$222,MATCH($C2,'Criterios GISTM'!$A$2:$A$222,0)),"") -> Principio 01 | E2: =IFERROR(INDEX('Criterios GISTM'!$H$2:$H$222,MATCH($C2,'Criterios GISTM'!$A$2:$A$222,0)),"") -> 1.1 - A | F2: 1 | G2: =IFERROR(INDEX('Criterios GISTM'!$J$2:$J$222,MATCH($C2,'Criterios GISTM'!$A$2:$A$222,0)),0) -> 0.33333333 | H2: =IFERROR(INDEX(Documentos!$F$2:$F$59,MATCH($A2,Documentos!$A$2:$A$59,0)),0) -> 1 | I2: =F2*G2*H2 -> 0.33333333 | J2: 120-130 | K2: -
A3: D002 | B3: =IFERROR(INDEX(Documentos!$B$2:$B$59,MATCH($A3,Documentos!$A$2:$A$59,0)),"") -> Informe de Proceso de Debida Diligencia | C3: C002 | D3: =IFERROR(INDEX('Criterios GISTM'!$D$2:$D$222,MATCH($C3,'Criterios GISTM'!$A$2:$A$222,0)),"") -> Principio 01 | E3: =IFERROR(INDEX('Criterios GISTM'!$H$2:$H$222,MATCH($C3,'Criterios GISTM'!$A$2:$A$222,0)),"") -> 1.1 - B | F3: 1 | G3: =IFERROR(INDEX('Criterios GISTM'!$J$2:$J$222,MATCH($C3,'Criterios GISTM'!$A$2:$A$222,0)),0) -> 0.33333333 | H3: =IFERROR(INDEX(Documentos!$F$2:$F$59,MATCH($A3,Documentos!$A$2:$A$59,0)),0) -> 0.7 | I3: =F3*G3*H3 -> 0.23333333 | J3: 120-131 | K3: -
A4: D002 | B4: =IFERROR(INDEX(Documentos!$B$2:$B$59,MATCH($A4,Documentos!$A$2:$A$59,0)),"") -> Informe de Proceso de Debida Diligencia | C4: C003 | D4: =IFERROR(INDEX('Criterios GISTM'!$D$2:$D$222,MATCH($C4,'Criterios GISTM'!$A$2:$A$222,0)),"") -> Principio 01 | E4: =IFERROR(INDEX('Criterios GISTM'!$H$2:$H$222,MATCH($C4,'Criterios GISTM'!$A$2:$A$222,0)),"") -> 1.1 - C | F4: 1 | G4: =IFERROR(INDEX('Criterios GISTM'!$J$2:$J$222,MATCH($C4,'Criterios GISTM'!$A$2:$A$222,0)),0) -> 0.33333333 | H4: =IFERROR(INDEX(Documentos!$F$2:$F$59,MATCH($A4,Documentos!$A$2:$A$59,0)),0) -> 0.7 | I4: =F4*G4*H4 -> 0.23333333 | J4: 120-132 | K4: -
A5: D003 | B5: =IFERROR(INDEX(Documentos!$B$2:$B$59,MATCH($A5,Documentos!$A$2:$A$59,0)),"") -> Nota Técnica No Afectación Pueblos Indígenas | C5: C004 | D5: =IFERROR(INDEX('Criterios GISTM'!$D$2:$D$222,MATCH($C5,'Criterios GISTM'!$A$2:$A$222,0)),"") -> Principio 01 | E5: =IFERROR(INDEX('Criterios GISTM'!$H$2:$H$222,MATCH($C5,'Criterios GISTM'!$A$2:$A$222,0)),"") -> 1.2 - A | F5: 1 | G5: =IFERROR(INDEX('Criterios GISTM'!$J$2:$J$222,MATCH($C5,'Criterios GISTM'!$A$2:$A$222,0)),0) -> 0.5 | H5: =IFERROR(INDEX(Documentos!$F$2:$F$59,MATCH($A5,Documentos!$A$2:$A$59,0)),0) -> 0.2 | I5: =F5*G5*H5 -> 0.1 | J5: 120-133 | K5: -
A6: D003 | B6: =IFERROR(INDEX(Documentos!$B$2:$B$59,MATCH($A6,Documentos!$A$2:$A$59,0)),"") -> Nota Técnica No Afectación Pueblos Indígenas | C6: C005 | D6: =IFERROR(INDEX('Criterios GISTM'!$D$2:$D$222,MATCH($C6,'Criterios GISTM'!$A$2:$A$222,0)),"") -> Principio 01 | E6: =IFERROR(INDEX('Criterios GISTM'!$H$2:$H$222,MATCH($C6,'Criterios GISTM'!$A$2:$A$222,0)),"") -> 1.2 - B | F6: 1 | G6: =IFERROR(INDEX('Criterios GISTM'!$J$2:$J$222,MATCH($C6,'Criterios GISTM'!$A$2:$A$222,0)),0) -> 0.5 | H6: =IFERROR(INDEX(Documentos!$F$2:$F$59,MATCH($A6,Documentos!$A$2:$A$59,0)),0) -> 0.2 | I6: =F6*G6*H6 -> 0.1 | J6: 120-134 | K6: -
A7: D004 | B7: =IFERROR(INDEX(Documentos!$B$2:$B$59,MATCH($A7,Documentos!$A$2:$A$59,0)),"") -> Informe de Identificación de Grupos Potenciales Afectados | C7: C006 | D7: =IFERROR(INDEX('Criterios GISTM'!$D$2:$D$222,MATCH($C7,'Criterios GISTM'!$A$2:$A$222,0)),"") -> Principio 01 | E7: =IFERROR(INDEX('Criterios GISTM'!$H$2:$H$222,MATCH($C7,'Criterios GISTM'!$A$2:$A$222,0)),"") -> 1.3 - A | F7: 1 | G7: =IFERROR(INDEX('Criterios GISTM'!$J$2:$J$222,MATCH($C7,'Criterios GISTM'!$A$2:$A$222,0)),0) -> 0.5 | H7: =IFERROR(INDEX(Documentos!$F$2:$F$59,MATCH($A7,Documentos!$A$2:$A$59,0)),0) -> 0.2 | I7: =F7*G7*H7 -> 0.1 | J7: 120-135 | K7: -
A8: D005 | B8: =IFERROR(INDEX(Documentos!$B$2:$B$59,MATCH($A8,Documentos!$A$2:$A$59,0)),"") -> Procedimiento de Comunicación | C8: C007 | D8: =IFERROR(INDEX('Criterios GISTM'!$D$2:$D$222,MATCH($C8,'Criterios GISTM'!$A$2:$A$222,0)),"") -> Principio 01 | E8: =IFERROR(INDEX('Criterios GISTM'!$H$2:$H$222,MATCH($C8,'Criterios GISTM'!$A$2:$A$222,0)),"") -> 1.3 - B | F8: 1 | G8: =IFERROR(INDEX('Criterios GISTM'!$J$2:$J$222,MATCH($C8,'Criterios GISTM'!$A$2:$A$222,0)),0) -> 0.5 | H8: =IFERROR(INDEX(Documentos!$F$2:$F$59,MATCH($A8,Documentos!$A$2:$A$59,0)),0) -> 0.2 | I8: =F8*G8*H8 -> 0.1 | J8: 120-136 | K8: -
A9: D005 | B9: =IFERROR(INDEX(Documentos!$B$2:$B$59,MATCH($A9,Documentos!$A$2:$A$59,0)),"") -> Procedimiento de Comunicación | C9: C007 | D9: =IFERROR(INDEX('Criterios GISTM'!$D$2:$D$222,MATCH($C9,'Criterios GISTM'!$A$2:$A$222,0)),"") -> Principio 01 | E9: =IFERROR(INDEX('Criterios GISTM'!$H$2:$H$222,MATCH($C9,'Criterios GISTM'!$A$2:$A$222,0)),"") -> 1.3 - B | F9: 1 | G9: =IFERROR(INDEX('Criterios GISTM'!$J$2:$J$222,MATCH($C9,'Criterios GISTM'!$A$2:$A$222,0)),0) -> 0.5 | H9: =IFERROR(INDEX(Documentos!$F$2:$F$59,MATCH($A9,Documentos!$A$2:$A$59,0)),0) -> 0.2 | I9: =F9*G9*H9 -> 0.1 | J9: 120-137 | K9: -
A10: D005 | B10: =IFERROR(INDEX(Documentos!$B$2:$B$59,MATCH($A10,Documentos!$A$2:$A$59,0)),"") -> Procedimiento de Comunicación | C10: C008 | D10: =IFERROR(INDEX('Criterios GISTM'!$D$2:$D$222,MATCH($C10,'Criterios GISTM'!$A$2:$A$222,0)),"") -> Principio 01 | E10: =IFERROR(INDEX('Criterios GISTM'!$H$2:$H$222,MATCH($C10,'Criterios GISTM'!$A$2:$A$222,0)),"") -> 1.4 - A | F10: 1 | G10: =IFERROR(INDEX('Criterios GISTM'!$J$2:$J$222,MATCH($C10,'Criterios GISTM'!$A$2:$A$222,0)),0) -> 0.33333333 | H10: =IFERROR(INDEX(Documentos!$F$2:$F$59,MATCH($A10,Documentos!$A$2:$A$59,0)),0) -> 0.2 | I10: =F10*G10*H10 -> 0.066666667 | J10: 120-138 | K10: -
A11: D005 | B11: =IFERROR(INDEX(Documentos!$B$2:$B$59,MATCH($A11,Documentos!$A$2:$A$59,0)),"") -> Procedimiento de Comunicación | C11: C009 | D11: =IFERROR(INDEX('Criterios GISTM'!$D$2:$D$222,MATCH($C11,'Criterios GISTM'!$A$2:$A$222,0)),"") -> Principio 01 | E11: =IFERROR(INDEX('Criterios GISTM'!$H$2:$H$222,MATCH($C11,'Criterios GISTM'!$A$2:$A$222,0)),"") -> 1.4 - B | F11: 1 | G11: =IFERROR(INDEX('Criterios GISTM'!$J$2:$J$222,MATCH($C11,'Criterios GISTM'!$A$2:$A$222,0)),0) -> 0.33333333 | H11: =IFERROR(INDEX(Documentos!$F$2:$F$59,MATCH($A11,Documentos!$A$2:$A$59,0)),0) -> 0.2 | I11: =F11*G11*H11 -> 0.066666667 | J11: 120-139 | K11: -
A12: D005 | B12: =IFERROR(INDEX(Documentos!$B$2:$B$59,MATCH($A12,Documentos!$A$2:$A$59,0)),"") -> Procedimiento de Comunicación | C12: C010 | D12: =IFERROR(INDEX('Criterios GISTM'!$D$2:$D$222,MATCH($C12,'Criterios GISTM'!$A$2:$A$222,0)),"") -> Principio 01 | E12: =IFERROR(INDEX('Criterios GISTM'!$H$2:$H$222,MATCH($C12,'Criterios GISTM'!$A$2:$A$222,0)),"") -> 1.4 - C | F12: 1 | G12: =IFERROR(INDEX('Criterios GISTM'!$J$2:$J$222,MATCH($C12,'Criterios GISTM'!$A$2:$A$222,0)),0) -> 0.33333333 | H12: =IFERROR(INDEX(Documentos!$F$2:$F$59,MATCH($A12,Documentos!$A$2:$A$59,0)),0) -> 0.2 | I12: =F12*G12*H12 -> 0.066666667 | J12: 120-140 | K12: -
A13: D006 | B13: =IFERROR(INDEX(Documentos!$B$2:$B$59,MATCH($A13,Documentos!$A$2:$A$59,0)),"") -> Informe de Contexto Social, Económico y Ambiental | C13: C011 | D13: =IFERROR(INDEX('Criterios GISTM'!$D$2:$D$222,MATCH($C13,'Criterios GISTM'!$A$2:$A$222,0)),"") -> Principio 02 | E13: =IFERROR(INDEX('Criterios GISTM'!$H$2:$H$222,MATCH($C13,'Criterios GISTM'!$A$2:$A$222,0)),"") -> 2.1 - A | F13: 1 | G13: =IFERROR(INDEX('Criterios GISTM'!$J$2:$J$222,MATCH($C13,'Criterios GISTM'!$A$2:$A$222,0)),0) -> 0.33333333 | H13: =IFERROR(INDEX(Documentos!$F$2:$F$59,MATCH($A13,Documentos!$A$2:$A$59,0)),0) -> 0.2 | I13: =F13*G13*H13 -> 0.066666667 | J13: 120-141 | K13: -
... A232: D058 | B232: =IFERROR(INDEX(Documentos!$B$2:$B$59,MATCH($A232,Documentos!$A$2:$A$59,0)),"") -> Procedimiento Gestión de Información Pública | C232: C216 | D232: =IFERROR(INDEX('Criterios GISTM'!$D$2:$D$222,MATCH($C232,'Criterios GISTM'!$A$2:$A$222,0)),"") -> Principio 15 | E232: =IFERROR(INDEX('Criterios GISTM'!$H$2:$H$222,MATCH($C232,'Criterios GISTM'!$A$2:$A$222,0)),"") -> 15.1 - A | F232: 1 | G232: =IFERROR(INDEX('Criterios GISTM'!$J$2:$J$222,MATCH($C232,'Criterios GISTM'!$A$2:$A$222,0)),0) -> 0.5 | H232: =IFERROR(INDEX(Documentos!$F$2:$F$59,MATCH($A232,Documentos!$A$2:$A$59,0)),0) -> 1 | I232: =F232*G232*H232 -> 0.5 | J232: 120-360 | K232: -

Sheet Avance por Principio
A1: Tema | B1: Nombre Tema | C1: Principio | D1: Descripción Principio | E1: N° Documentos Vinculados | F1: Suma Ponderación | G1: Avance Ponderado | H1: % Avance Principio
A2: I | B2: COMUNIDADES AFECTADAS | C2: Principio 01 | D2: Respetar los derechos de las personas afectadas por el proyecto y lograr su participación significativa en todas las fases del ciclo de vida de las instalaciones de relaves, incluido su cierre. | E2: =COUNTIFS(Documento_x_Criterio!$D$2:$D$232,$C2) -> 11 | F2: =SUMPRODUCT((Documento_x_Criterio!$D$2:$D$232=$C2)*Documento_x_Criterio!$F$2:$F$232*Documento_x_Criterio!$G$2:$G$232) -> 4.5 | G2: =SUMIFS(Documento_x_Criterio!$I$2:$I$232,Documento_x_Criterio!$D$2:$D$232,$C2) -> 1.5 | H2: =IFERROR(G2/F2,0) -> 0.33333333
A3: II | B3: BASE DE CONOCIMIENTOS INTEGRADA | C3: Principio 02 | D3: Elaborar y mantener una base de conocimientos interdisciplinaria para respaldar la gestión de los relaves durante todo su ciclo de vida, incluido su cierre. | E3: =COUNTIFS(Documento_x_Criterio!$D$2:$D$232,$C3) -> 19 | F3: =SUMPRODUCT((Documento_x_Criterio!$D$2:$D$232=$C3)*Documento_x_Criterio!$F$2:$F$232*Documento_x_Criterio!$G$2:$G$232) -> 6 | G3: =SUMIFS(Documento_x_Criterio!$I$2:$I$232,Documento_x_Criterio!$D$2:$D$232,$C3) -> 4.4 | H3: =IFERROR(G3/F3,0) -> 0.73333333
A4: II | B4: BASE DE CONOCIMIENTOS INTEGRADA | C4: Principio 03 | D4: Utilizar los elementos de la base de conocimientos – sociales, ambientales, de la economía local y técnicos – con el fin de informar las decisiones durante el ciclo de vida de la instalación de relaves, incluido su cierre | E4: =COUNTIFS(Documento_x_Criterio!$D$2:$D$232,$C4) -> 12 | F4: =SUMPRODUCT((Documento_x_Criterio!$D$2:$D$232=$C4)*Documento_x_Criterio!$F$2:$F$232*Documento_x_Criterio!$G$2:$G$232) -> 5 | G4: =SUMIFS(Documento_x_Criterio!$I$2:$I$232,Documento_x_Criterio!$D$2:$D$232,$C4) -> 1.2 | H4: =IFERROR(G4/F4,0) -> 0.24
A5: III | B5: DISEÑO, CONSTRUCCIÓN, OPERACIÓN Y MONITOREO DE LAS INSTALACIONES DE RELAVES | C5: Principio 04 | D5: Desarrollar planes y criterios de diseño para la instalación de relaves con el fin de minimizar los riesgos para todas las fases del ciclo de vida, incluso el cierre y el post cierre. | E5: =COUNTIFS(Documento_x_Criterio!$D$2:$D$232,$C5) -> 21 | F5: =SUMPRODUCT((Documento_x_Criterio!$D$2:$D$232=$C5)*Documento_x_Criterio!$F$2:$F$232*Documento_x_Criterio!$G$2:$G$232) -> 8 | G5: =SUMIFS(Documento_x_Criterio!$I$2:$I$232,Documento_x_Criterio!$D$2:$D$232,$C5) -> 1.8 | H5: =IFERROR(G5/F5,0) -> 0.225
A6: III | B6: DISEÑO, CONSTRUCCIÓN, OPERACIÓN Y MONITOREO DE LAS INSTALACIONES DE RELAVES | C6: Principio 05 | D6: Desarrollar un diseño sólido que integre la base de conocimientos y minimice el riesgo de falla que pueda afectar a las personas y el medio ambiente durante todas las fases del ciclo de vida de la instalación de relaves, incluso el cierre y post cierre. | E6: =COUNTIFS(Documento_x_Criterio!$D$2:$D$232,$C6) -> 22 | F6: =SUMPRODUCT((Documento_x_Criterio!$D$2:$D$232=$C6)*Documento_x_Criterio!$F$2:$F$232*Documento_x_Criterio!$G$2:$G$232) -> 8 | G6: =SUMIFS(Documento_x_Criterio!$I$2:$I$232,Documento_x_Criterio!$D$2:$D$232,$C6) -> 4.5833333 | H6: =IFERROR(G6/F6,0) -> 0.57291667
A7: III | B7: DISEÑO, CONSTRUCCIÓN, OPERACIÓN Y MONITOREO DE LAS INSTALACIONES DE RELAVES | C7: Principio 06 | D7: Planificar, construir y operar la instalación de relaves para gestionar el riesgo en todas las fases de su ciclo de vida, incluidas la fase de cierre y el post cierre. | E7: =COUNTIFS(Documento_x_Criterio!$D$2:$D$232,$C7) -> 24 | F7: =SUMPRODUCT((Documento_x_Criterio!$D$2:$D$232=$C7)*Documento_x_Criterio!$F$2:$F$232*Documento_x_Criterio!$G$2:$G$232) -> 7.75 | G7: =SUMIFS(Documento_x_Criterio!$I$2:$I$232,Documento_x_Criterio!$D$2:$D$232,$C7) -> 2.36 | H7: =IFERROR(G7/F7,0) -> 0.30451613
A8: III | B8: DISEÑO, CONSTRUCCIÓN, OPERACIÓN Y MONITOREO DE LAS INSTALACIONES DE RELAVES | C8: Principio 07 | D8: Diseñar, establecer y operar sistemas de monitoreo para la gestión de riesgos en todas las fases del ciclo de vida de la instalación de relaves, incluso su cierre. | E8: =COUNTIFS(Documento_x_Criterio!$D$2:$D$232,$C8) -> 16 | F8: =SUMPRODUCT((Documento_x_Criterio!$D$2:$D$232=$C8)*Documento_x_Criterio!$F$2:$F$232*Documento_x_Criterio!$G$2:$G$232) -> 5 | G8: =SUMIFS(Documento_x_Criterio!$I$2:$I$232,Documento_x_Criterio!$D$2:$D$232,$C8) -> 1.1333333 | H8: =IFERROR(G8/F8,0) -> 0.22666667
A9: IV | B9: GESTIÓN Y GOBERNANZA | C9: Principio 08 | D9: Establecer las políticas, sistemas y rendiciones de cuenta (accountability) para respaldar la seguridad e integridad de las instalaciones de relaves. | E9: =COUNTIFS(Documento_x_Criterio!$D$2:$D$232,$C9) -> 26 | F9: =SUMPRODUCT((Documento_x_Criterio!$D$2:$D$232=$C9)*Documento_x_Criterio!$F$2:$F$232*Documento_x_Criterio!$G$2:$G$232) -> 7.2 | G9: =SUMIFS(Documento_x_Criterio!$I$2:$I$232,Documento_x_Criterio!$D$2:$D$232,$C9) -> 3.58 | H9: =IFERROR(G9/F9,0) -> 0.49722222
A10: IV | B10: GESTIÓN Y GOBERNANZA | C10: Principio 09 | D10: Nombrar y dotar de facultades a un ingeniero de registro. | E10: =COUNTIFS(Documento_x_Criterio!$D$2:$D$232,$C10) -> 14 | F10: =SUMPRODUCT((Documento_x_Criterio!$D$2:$D$232=$C10)*Documento_x_Criterio!$F$2:$F$232*Documento_x_Criterio!$G$2:$G$232) -> 5 | G10: =SUMIFS(Documento_x_Criterio!$I$2:$I$232,Documento_x_Criterio!$D$2:$D$232,$C10) -> 4.7 | H10: =IFERROR(G10/F10,0) -> 0.94
A11: IV | B11: GESTIÓN Y GOBERNANZA | C11: Principio 10 | D11: Establecer e implementar niveles de revisión como parte de un sistema de gestión de riesgos y de calidad sólido para todas las fases del ciclo de vida de la instalación de relaves, incluido su cierre. | E11: =COUNTIFS(Documento_x_Criterio!$D$2:$D$232,$C11) -> 24 | F11: =SUMPRODUCT((Documento_x_Criterio!$D$2:$D$232=$C11)*Documento_x_Criterio!$F$2:$F$232*Documento_x_Criterio!$G$2:$G$232) -> 7 | G11: =SUMIFS(Documento_x_Criterio!$I$2:$I$232,Documento_x_Criterio!$D$2:$D$232,$C11) -> 5.6333333 | H11: =IFERROR(G11/F11,0) -> 0.8047619
A12: IV | B12: GESTIÓN Y GOBERNANZA | C12: Principio 11 | D12: Desarrollar una cultura organizacional que promueva el aprendizaje, la comunicación y el reconocimiento temprano de los problemas. | E12: =COUNTIFS(Documento_x_Criterio!$D$2:$D$232,$C12) -> 11 | F12: =SUMPRODUCT((Documento_x_Criterio!$D$2:$D$232=$C12)*Documento_x_Criterio!$F$2:$F$232*Documento_x_Criterio!$G$2:$G$232) -> 7 | G12: =SUMIFS(Documento_x_Criterio!$I$2:$I$232,Documento_x_Criterio!$D$2:$D$232,$C12) -> 3.5 | H12: =IFERROR(G12/F12,0) -> 0.5
A13: IV | B13: GESTIÓN Y GOBERNANZA | C13: Principio 12 | D13: Establecer un proceso para informar y abordar las preocupaciones e implementar protecciones para los denunciantes. | E13: =COUNTIFS(Documento_x_Criterio!$D$2:$D$232,$C13) -> 2 | F13: =SUMPRODUCT((Documento_x_Criterio!$D$2:$D$232=$C13)*Documento_x_Criterio!$F$2:$F$232*Documento_x_Criterio!$G$2:$G$232) -> 2 | G13: =SUMIFS(Documento_x_Criterio!$I$2:$I$232,Documento_x_Criterio!$D$2:$D$232,$C13) -> 0.8 | H13: =IFERROR(G13/F13,0) -> 0.4
... A16: VI | B16: DIVULGACIÓN PÚBLICA Y ACCESO A LA INFORMACIÓN | C16: Principio 15 | D16: Hacer pública y permitir el acceso a la información sobre instalaciones de relaves para respaldar la rendición de cuentas al público general. | E16: =COUNTIFS(Documento_x_Criterio!$D$2:$D$232,$C16) -> 1 | F16: =SUMPRODUCT((Documento_x_Criterio!$D$2:$D$232=$C16)*Documento_x_Criterio!$F$2:$F$232*Documento_x_Criterio!$G$2:$G$232) -> 0.5 | G16: =SUMIFS(Documento_x_Criterio!$I$2:$I$232,Documento_x_Criterio!$D$2:$D$232,$C16) -> 0.5 | H16: =IFERROR(G16/F16,0) -> 1

Sheet Avance por Tema
A1: Tema | B1: Nombre Tema | C1: Suma Ponderación | D1: Avance Ponderado | E1: % Avance Tema
A2: I | B2: COMUNIDADES AFECTADAS | C2: =SUMIFS('Avance por Principio'!$F$2:$F$16,'Avance por Principio'!$A$2:$A$16,$A2) -> 4.5 | D2: =SUMIFS('Avance por Principio'!$G$2:$G$16,'Avance por Principio'!$A$2:$A$16,$A2) -> 1.5 | E2: =IFERROR(D2/C2,0) -> 0.33333333
A3: II | B3: BASE DE CONOCIMIENTOS INTEGRADA | C3: =SUMIFS('Avance por Principio'!$F$2:$F$16,'Avance por Principio'!$A$2:$A$16,$A3) -> 11 | D3: =SUMIFS('Avance por Principio'!$G$2:$G$16,'Avance por Principio'!$A$2:$A$16,$A3) -> 5.6 | E3: =IFERROR(D3/C3,0) -> 0.50909091
A4: III | B4: DISEÑO, CONSTRUCCIÓN, OPERACIÓN Y MONITOREO DE LAS INSTALACIONES DE RELAVES | C4: =SUMIFS('Avance por Principio'!$F$2:$F$16,'Avance por Principio'!$A$2:$A$16,$A4) -> 28.75 | D4: =SUMIFS('Avance por Principio'!$G$2:$G$16,'Avance por Principio'!$A$2:$A$16,$A4) -> 9.8766667 | E4: =IFERROR(D4/C4,0) -> 0.34353623
A5: IV | B5: GESTIÓN Y GOBERNANZA | C5: =SUMIFS('Avance por Principio'!$F$2:$F$16,'Avance por Principio'!$A$2:$A$16,$A5) -> 28.2 | D5: =SUMIFS('Avance por Principio'!$G$2:$G$16,'Avance por Principio'!$A$2:$A$16,$A5) -> 18.213333 | E5: =IFERROR(D5/C5,0) -> 0.64586288
A6: V | B6: RESPUESTA ANTE EMERGENCIAS Y RECUPERACIÓN A LARGO PLAZO | C6: =SUMIFS('Avance por Principio'!$F$2:$F$16,'Avance por Principio'!$A$2:$A$16,$A6) -> 9 | D6: =SUMIFS('Avance por Principio'!$G$2:$G$16,'Avance por Principio'!$A$2:$A$16,$A6) -> 5.1 | E6: =IFERROR(D6/C6,0) -> 0.56666667
A7: VI | B7: DIVULGACIÓN PÚBLICA Y ACCESO A LA INFORMACIÓN | C7: =SUMIFS('Avance por Principio'!$F$2:$F$16,'Avance por Principio'!$A$2:$A$16,$A7) -> 0.5 | D7: =SUMIFS('Avance por Principio'!$G$2:$G$16,'Avance por Principio'!$A$2:$A$16,$A7) -> 0.5 | E7: =IFERROR(D7/C7,0) -> 1

Sheet Curva de avance
A1: Fecha | B1: Plan | C1: Real | D1: Forecast
A2: 45292 | B2: 0 | C2: 0
A3: 45323 | B3: 0 | C3: 0.225
A4: 45352 | B4: 0.01 | C4: 0.24423077
A5: 45383 | B5: 0.06 | C5: 0.24423077
A6: 45413 | B6: 0.09 | C6: 0.24423077
A7: 45444 | B7: 0.12 | C7: 0.24423077
A8: 45474 | B8: 0.15 | C8: 0.24423077
A9: 45505 | B9: 0.19 | C9: 0.26153846
A10: 45536 | B10: 0.33 | C10: 0.26153846
A11: 45566 | B11: 0.36 | C11: 0.27115385
A12: 45597 | B12: 0.41 | C12: 0.28076923
A13: 45627 | B13: 0.44 | C13: 0.29519231
... A20: 45839 | B20: 0.85 | C20: 0.93365385
A21: 45870 | B21: 0.87 | C21: 0.93365385 | D21: 0.93
A22: 45901 | B22: 0.87 | D22: 0.93365385
A23: 45931 | B23: 0.88 | D23: 0.95288462
A24: 45962 | B24: 0.93 | D24: 0.95865385
A25: 45992 | B25: 0.95 | D25: 0.97788462
A26: 46023 | B26: 0.98 | D26: 1
A27: 46054 | B27: 1 | D27: 1

Sheet Documentos referenciales
A1: ID_Documento | B1: Documento | C1: ID_Criterio | D1: Principio | E1: Criterio
A2: DR001 | B2: Compromiso de DDHH | C2: C001 | D2: =IFERROR(INDEX('Criterios GISTM'!$D$2:$D$222,MATCH($C2,'Criterios GISTM'!$A$2:$A$222,0)),"") -> Principio 01 | E2: =IFERROR(INDEX('Criterios GISTM'!$H$2:$H$222,MATCH($C2,'Criterios GISTM'!$A$2:$A$222,0)),"") -> 1.1 - A
A3: DR002 | B3: Informe de Proceso de Debida Diligencia | C3: C002 | D3: =IFERROR(INDEX('Criterios GISTM'!$D$2:$D$222,MATCH($C3,'Criterios GISTM'!$A$2:$A$222,0)),"") -> Principio 01 | E3: =IFERROR(INDEX('Criterios GISTM'!$H$2:$H$222,MATCH($C3,'Criterios GISTM'!$A$2:$A$222,0)),"") -> 1.1 - B
A4: DR003 | B4: Informe de Proceso de Debida Diligencia | C4: C003 | D4: =IFERROR(INDEX('Criterios GISTM'!$D$2:$D$222,MATCH($C4,'Criterios GISTM'!$A$2:$A$222,0)),"") -> Principio 01 | E4: =IFERROR(INDEX('Criterios GISTM'!$H$2:$H$222,MATCH($C4,'Criterios GISTM'!$A$2:$A$222,0)),"") -> 1.1 - C
A5: DR004 | B5: Nota Técnica No Afectación Pueblos Indígenas | C5: C004 | D5: =IFERROR(INDEX('Criterios GISTM'!$D$2:$D$222,MATCH($C5,'Criterios GISTM'!$A$2:$A$222,0)),"") -> Principio 01 | E5: =IFERROR(INDEX('Criterios GISTM'!$H$2:$H$222,MATCH($C5,'Criterios GISTM'!$A$2:$A$222,0)),"") -> 1.2 - A
A6: DR005 | B6: Nota Técnica No Afectación Pueblos Indígenas | C6: C005 | D6: =IFERROR(INDEX('Criterios GISTM'!$D$2:$D$222,MATCH($C6,'Criterios GISTM'!$A$2:$A$222,0)),"") -> Principio 01 | E6: =IFERROR(INDEX('Criterios GISTM'!$H$2:$H$222,MATCH($C6,'Criterios GISTM'!$A$2:$A$222,0)),"") -> 1.2 - B
A7: DR006 | B7: Informe de Identificación de Grupos Potenciales Afectados | C7: C006 | D7: =IFERROR(INDEX('Criterios GISTM'!$D$2:$D$222,MATCH($C7,'Criterios GISTM'!$A$2:$A$222,0)),"") -> Principio 01 | E7: =IFERROR(INDEX('Criterios GISTM'!$H$2:$H$222,MATCH($C7,'Criterios GISTM'!$A$2:$A$222,0)),"") -> 1.3 - A
A8: DR007 | B8: Procedimiento de Comunicación | C8: C007 | D8: =IFERROR(INDEX('Criterios GISTM'!$D$2:$D$222,MATCH($C8,'Criterios GISTM'!$A$2:$A$222,0)),"") -> Principio 01 | E8: =IFERROR(INDEX('Criterios GISTM'!$H$2:$H$222,MATCH($C8,'Criterios GISTM'!$A$2:$A$222,0)),"") -> 1.3 - B
A9: DR008 | B9: Procedimiento de Comunicación | C9: C007 | D9: =IFERROR(INDEX('Criterios GISTM'!$D$2:$D$222,MATCH($C9,'Criterios GISTM'!$A$2:$A$222,0)),"") -> Principio 01 | E9: =IFERROR(INDEX('Criterios GISTM'!$H$2:$H$222,MATCH($C9,'Criterios GISTM'!$A$2:$A$222,0)),"") -> 1.3 - B
A10: DR009 | B10: Procedimiento de Comunicación | C10: C008 | D10: =IFERROR(INDEX('Criterios GISTM'!$D$2:$D$222,MATCH($C10,'Criterios GISTM'!$A$2:$A$222,0)),"") -> Principio 01 | E10: =IFERROR(INDEX('Criterios GISTM'!$H$2:$H$222,MATCH($C10,'Criterios GISTM'!$A$2:$A$222,0)),"") -> 1.4 - A
A11: DR010 | B11: Procedimiento de Comunicación | C11: C009 | D11: =IFERROR(INDEX('Criterios GISTM'!$D$2:$D$222,MATCH($C11,'Criterios GISTM'!$A$2:$A$222,0)),"") -> Principio 01 | E11: =IFERROR(INDEX('Criterios GISTM'!$H$2:$H$222,MATCH($C11,'Criterios GISTM'!$A$2:$A$222,0)),"") -> 1.4 - B
A12: DR011 | B12: Procedimiento de Comunicación | C12: C010 | D12: =IFERROR(INDEX('Criterios GISTM'!$D$2:$D$222,MATCH($C12,'Criterios GISTM'!$A$2:$A$222,0)),"") -> Principio 01 | E12: =IFERROR(INDEX('Criterios GISTM'!$H$2:$H$222,MATCH($C12,'Criterios GISTM'!$A$2:$A$222,0)),"") -> 1.4 - C
A13: DR012 | B13: Informe de Contexto Social, Económico y Ambiental | C13: C011 | D13: =IFERROR(INDEX('Criterios GISTM'!$D$2:$D$222,MATCH($C13,'Criterios GISTM'!$A$2:$A$222,0)),"") -> Principio 02 | E13: =IFERROR(INDEX('Criterios GISTM'!$H$2:$H$222,MATCH($C13,'Criterios GISTM'!$A$2:$A$222,0)),"") -> 2.1 - A
... A232: DR231 | B232: Procedimiento Gestión de Información Pública | C232: C216 | D232: =IFERROR(INDEX('Criterios GISTM'!$D$2:$D$222,MATCH($C232,'Criterios GISTM'!$A$2:$A$222,0)),"") -> Principio 15 | E232: =IFERROR(INDEX('Criterios GISTM'!$H$2:$H$222,MATCH($C232,'Criterios GISTM'!$A$2:$A$222,0)),"") -> 15.1 - A
